{"schema_version":1,"mode":"shadow_research_only","production_weights_changed":false,"generated_at":"2026-07-15T13:01:29+00:00","latest_trade_date":"2026-07-15","universe_count":89,"formal_universe_count":91,"rotation_universe_count":89,"defense_monitor":[{"symbol":"511110","name":"公司债ETF易方达","trade_date":"2026-07-15","close":102.877,"ret20":0.2221,"ret60":0.6979,"rsi14":67.34,"ema12":102.8432,"ema26":102.7721,"technical_vote":1,"hv20_annualized":0.3549,"hv_percentile":9.72,"max_drawdown60":-0.2946,"amount_ma20":5240728104.7},{"symbol":"511260","name":"十年国债ETF国泰","trade_date":"2026-07-15","close":134.934,"ret20":0.2712,"ret60":0.9131,"rsi14":60.45,"ema12":134.8613,"ema26":134.7441,"technical_vote":1,"hv20_annualized":1.1578,"hv_percentile":20.83,"max_drawdown60":-0.4664,"amount_ma20":3334819176.45}],"minimum_observations":60,"factor_definition":{"ret20":0.35,"ret60":0.25,"technical_vote":0.2,"volatility_penalty":-0.1,"drawdown_quality":0.1},"shadow_top12":["561980","159992","159502","512480","159938","588000","512170","159985","560080","513060","513500","162411"],"portfolio_risk":{"symbols":["561980","159992","159502","512480","159938","588000","512170","159985","560080","513060","513500","162411"],"observations":91,"annualized_volatility_pct":18.8113,"var95_daily_pct":-1.5019,"cvar95_daily_pct":-2.0183,"max_drawdown_pct":-7.3128},"correlation":{"observations":91,"mean_pairwise_correlation":0.22,"highest_pairs":[{"left":"512480","right":"588000","correlation":0.983},{"left":"159992","right":"159938","correlation":0.971},{"left":"561980","right":"512480","correlation":0.953},{"left":"159938","right":"512170","correlation":0.939},{"left":"561980","right":"588000","correlation":0.929},{"left":"159992","right":"512170","correlation":0.894},{"left":"159992","right":"513060","correlation":0.874},{"left":"159938","right":"513060","correlation":0.865},{"left":"512170","right":"513060","correlation":0.804},{"left":"159938","right":"560080","correlation":0.802}]},"items":[{"symbol":"561980","name":"半导体设备ETF招商","trade_date":"2026-07-15","close":0.787,"ret20":16.0767,"ret60":71.8341,"rsi14":49.45,"ema12":0.8382,"ema26":0.7948,"technical_vote":2,"hv20_annualized":76.2786,"hv_percentile":100.0,"max_drawdown60":-16.0637,"amount_ma20":737716530.69,"factor_score":1.8274,"shadow_rank":1,"execution":{"order_cny":100000,"participation_pct":0.014,"estimated_impact_bps":2.12,"formula":"2 + 10*sqrt(order/avg_amount_20d)"}},{"symbol":"159992","name":"创新药ETF银华","trade_date":"2026-07-15","close":0.912,"ret20":26.8428,"ret60":5.0691,"rsi14":69.75,"ema12":0.8455,"ema26":0.8155,"technical_vote":2,"hv20_annualized":47.8608,"hv_percentile":98.61,"max_drawdown60":-16.6274,"amount_ma20":1312548227.85,"factor_score":1.5234,"shadow_rank":2,"execution":{"order_cny":100000,"participation_pct":0.008,"estimated_impact_bps":2.09,"formula":"2 + 10*sqrt(order/avg_amount_20d)"}},{"symbol":"159502","name":"标普生物科技ETF嘉实","trade_date":"2026-07-15","close":1.611,"ret20":18.2819,"ret60":16.8238,"rsi14":57.44,"ema12":1.6108,"ema26":1.5451,"technical_vote":2,"hv20_annualized":49.2707,"hv_percentile":100.0,"max_drawdown60":-9.3696,"amount_ma20":551549380.12,"factor_score":1.4361,"shadow_rank":3,"execution":{"order_cny":100000,"participation_pct":0.018,"estimated_impact_bps":2.13,"formula":"2 + 10*sqrt(order/avg_amount_20d)"}},{"symbol":"512480","name":"半导体ETF国联安","trade_date":"2026-07-15","close":1.232,"ret20":9.3168,"ret60":52.0988,"rsi14":46.56,"ema12":1.3252,"ema26":1.2795,"technical_vote":2,"hv20_annualized":76.4819,"hv_percentile":100.0,"max_drawdown60":-18.0306,"amount_ma20":2323844263.0,"factor_score":1.2458,"shadow_rank":4,"execution":{"order_cny":100000,"participation_pct":0.004,"estimated_impact_bps":2.07,"formula":"2 + 10*sqrt(order/avg_amount_20d)"}},{"symbol":"159938","name":"医药ETF广发","trade_date":"2026-07-15","close":0.66,"ret20":16.4021,"ret60":0.4566,"rsi14":67.43,"ema12":0.6235,"ema26":0.6111,"technical_vote":2,"hv20_annualized":36.8152,"hv_percentile":100.0,"max_drawdown60":-13.2716,"amount_ma20":70705858.36,"factor_score":1.151,"shadow_rank":5,"execution":{"order_cny":100000,"participation_pct":0.141,"estimated_impact_bps":2.38,"formula":"2 + 10*sqrt(order/avg_amount_20d)"}},{"symbol":"588000","name":"科创50ETF华夏","trade_date":"2026-07-15","close":2.028,"ret20":9.3261,"ret60":35.3805,"rsi14":48.14,"ema12":2.129,"ema26":2.0663,"technical_vote":2,"hv20_annualized":65.7569,"hv_percentile":100.0,"max_drawdown60":-15.7658,"amount_ma20":8431384887.0,"factor_score":1.1189,"shadow_rank":6,"execution":{"order_cny":100000,"participation_pct":0.001,"estimated_impact_bps":2.03,"formula":"2 + 10*sqrt(order/avg_amount_20d)"}},{"symbol":"512170","name":"医疗ETF华宝","trade_date":"2026-07-15","close":0.332,"ret20":13.3106,"ret60":-1.4837,"rsi14":65.57,"ema12":0.3137,"ema26":0.3106,"technical_vote":2,"hv20_annualized":33.5025,"hv_percentile":100.0,"max_drawdown60":-14.4118,"amount_ma20":733210835.45,"factor_score":0.9999,"shadow_rank":7,"execution":{"order_cny":100000,"participation_pct":0.014,"estimated_impact_bps":2.12,"formula":"2 + 10*sqrt(order/avg_amount_20d)"}},{"symbol":"159985","name":"豆粕ETF华夏","trade_date":"2026-07-15","close":2.231,"ret20":10.7196,"ret60":5.6845,"rsi14":73.72,"ema12":2.1426,"ema26":2.0991,"technical_vote":1,"hv20_annualized":21.3193,"hv_percentile":72.22,"max_drawdown60":-8.7137,"amount_ma20":368494064.15,"factor_score":0.9811,"shadow_rank":8,"execution":{"order_cny":100000,"participation_pct":0.027,"estimated_impact_bps":2.16,"formula":"2 + 10*sqrt(order/avg_amount_20d)"}},{"symbol":"560080","name":"中药ETF汇添富","trade_date":"2026-07-15","close":1.008,"ret20":10.1639,"ret60":-0.9823,"rsi14":69.11,"ema12":0.946,"ema26":0.9342,"technical_vote":2,"hv20_annualized":34.1856,"hv_percentile":98.61,"max_drawdown60":-14.6825,"amount_ma20":82655854.65,"factor_score":0.8685,"shadow_rank":9,"execution":{"order_cny":100000,"participation_pct":0.121,"estimated_impact_bps":2.35,"formula":"2 + 10*sqrt(order/avg_amount_20d)"}},{"symbol":"513060","name":"恒生医疗ETF博时","trade_date":"2026-07-15","close":0.55,"ret20":18.0258,"ret60":-11.2903,"rsi14":65.46,"ema12":0.5209,"ema26":0.5102,"technical_vote":2,"hv20_annualized":41.1907,"hv_percentile":83.33,"max_drawdown60":-24.6732,"amount_ma20":848650537.4,"factor_score":0.8516,"shadow_rank":10,"execution":{"order_cny":100000,"participation_pct":0.012,"estimated_impact_bps":2.11,"formula":"2 + 10*sqrt(order/avg_amount_20d)"}},{"symbol":"513500","name":"标普500ETF博时","trade_date":"2026-07-15","close":2.564,"ret20":-0.8507,"ret60":8.4144,"rsi14":59.95,"ema12":2.5254,"ema26":2.5192,"technical_vote":2,"hv20_annualized":13.0255,"hv_percentile":16.67,"max_drawdown60":-5.6,"amount_ma20":377954991.65,"factor_score":0.8174,"shadow_rank":11,"execution":{"order_cny":100000,"participation_pct":0.026,"estimated_impact_bps":2.16,"formula":"2 + 10*sqrt(order/avg_amount_20d)"}},{"symbol":"162411","name":"华宝油气LOF","trade_date":"2026-07-15","close":0.88,"ret20":6.2802,"ret60":1.1494,"rsi14":59.8,"ema12":0.849,"ema26":0.8463,"technical_vote":2,"hv20_annualized":25.8872,"hv_percentile":6.94,"max_drawdown60":-15.2615,"amount_ma20":88679973.32,"factor_score":0.7806,"shadow_rank":12,"execution":{"order_cny":100000,"participation_pct":0.113,"estimated_impact_bps":2.34,"formula":"2 + 10*sqrt(order/avg_amount_20d)"}},{"symbol":"510050","name":"上证50ETF华夏","trade_date":"2026-07-15","close":3.064,"ret20":2.3722,"ret60":1.6589,"rsi14":53.78,"ema12":3.0428,"ema26":3.0314,"technical_vote":2,"hv20_annualized":25.6892,"hv_percentile":95.83,"max_drawdown60":-7.1085,"amount_ma20":2304232022.5,"factor_score":0.7548,"shadow_rank":13,"execution":{"order_cny":100000,"participation_pct":0.004,"estimated_impact_bps":2.07,"formula":"2 + 10*sqrt(order/avg_amount_20d)"}},{"symbol":"560800","name":"数字经济ETF鹏扬","trade_date":"2026-07-15","close":1.305,"ret20":5.5825,"ret60":28.9526,"rsi14":45.91,"ema12":1.3754,"ema26":1.3505,"technical_vote":1,"hv20_annualized":61.1575,"hv_percentile":98.61,"max_drawdown60":-14.3139,"amount_ma20":18866186.72,"factor_score":0.7524,"shadow_rank":14,"execution":{"order_cny":100000,"participation_pct":0.53,"estimated_impact_bps":2.73,"formula":"2 + 10*sqrt(order/avg_amount_20d)"}},{"symbol":"513400","name":"道琼斯ETF鹏华","trade_date":"2026-07-15","close":1.312,"ret20":1.9425,"ret60":6.8404,"rsi14":54.31,"ema12":1.3127,"ema26":1.3009,"technical_vote":1,"hv20_annualized":16.4223,"hv_percentile":34.72,"max_drawdown60":-3.9028,"amount_ma20":270171627.6,"factor_score":0.7408,"shadow_rank":15,"execution":{"order_cny":100000,"participation_pct":0.037,"estimated_impact_bps":2.19,"formula":"2 + 10*sqrt(order/avg_amount_20d)"}},{"symbol":"515000","name":"科技ETF华宝","trade_date":"2026-07-15","close":1.466,"ret20":1.9471,"ret60":32.3105,"rsi14":46.64,"ema12":1.5327,"ema26":1.5114,"technical_vote":1,"hv20_annualized":62.2671,"hv_percentile":100.0,"max_drawdown60":-14.3692,"amount_ma20":333558572.45,"factor_score":0.6408,"shadow_rank":16,"execution":{"order_cny":100000,"participation_pct":0.03,"estimated_impact_bps":2.17,"formula":"2 + 10*sqrt(order/avg_amount_20d)"}},{"symbol":"164824","name":"印度基金LOF","trade_date":"2026-07-15","close":1.286,"ret20":-1.9069,"ret60":-2.3538,"rsi14":45.26,"ema12":1.2971,"ema26":1.2959,"technical_vote":2,"hv20_annualized":10.4385,"hv_percentile":1.39,"max_drawdown60":-6.6319,"amount_ma20":36795824.65,"factor_score":0.6261,"shadow_rank":17,"execution":{"order_cny":100000,"participation_pct":0.272,"estimated_impact_bps":2.52,"formula":"2 + 10*sqrt(order/avg_amount_20d)"}},{"symbol":"515260","name":"电子ETF华宝","trade_date":"2026-07-15","close":0.975,"ret20":0.9317,"ret60":38.4943,"rsi14":45.93,"ema12":1.0289,"ema26":1.0148,"technical_vote":1,"hv20_annualized":67.6649,"hv_percentile":98.61,"max_drawdown60":-16.0929,"amount_ma20":116109228.25,"factor_score":0.6232,"shadow_rank":18,"execution":{"order_cny":100000,"participation_pct":0.086,"estimated_impact_bps":2.29,"formula":"2 + 10*sqrt(order/avg_amount_20d)"}},{"symbol":"515980","name":"人工智能ETF华富","trade_date":"2026-07-15","close":1.17,"ret20":3.3569,"ret60":20.0,"rsi14":48.08,"ema12":1.2008,"ema26":1.1886,"technical_vote":1,"hv20_annualized":59.8424,"hv_percentile":93.06,"max_drawdown60":-10.5666,"amount_ma20":409915838.4,"factor_score":0.6043,"shadow_rank":19,"execution":{"order_cny":100000,"participation_pct":0.024,"estimated_impact_bps":2.16,"formula":"2 + 10*sqrt(order/avg_amount_20d)"}},{"symbol":"513030","name":"德国ETF华安","trade_date":"2026-07-15","close":1.773,"ret20":-0.7834,"ret60":-2.1523,"rsi14":47.32,"ema12":1.7852,"ema26":1.7847,"technical_vote":2,"hv20_annualized":20.0915,"hv_percentile":27.78,"max_drawdown60":-7.5936,"amount_ma20":76833718.65,"factor_score":0.5998,"shadow_rank":20,"execution":{"order_cny":100000,"participation_pct":0.13,"estimated_impact_bps":2.36,"formula":"2 + 10*sqrt(order/avg_amount_20d)"}},{"symbol":"512800","name":"银行ETF华宝","trade_date":"2026-07-15","close":0.79,"ret20":-0.2525,"ret60":-1.3733,"rsi14":59.96,"ema12":0.7697,"ema26":0.7697,"technical_vote":2,"hv20_annualized":20.8766,"hv_percentile":86.11,"max_drawdown60":-9.828,"amount_ma20":1032349598.55,"factor_score":0.5927,"shadow_rank":21,"execution":{"order_cny":100000,"participation_pct":0.01,"estimated_impact_bps":2.1,"formula":"2 + 10*sqrt(order/avg_amount_20d)"}},{"symbol":"159939","name":"信息技术ETF广发","trade_date":"2026-07-15","close":1.248,"ret20":1.8776,"ret60":32.0635,"rsi14":45.69,"ema12":1.3221,"ema26":1.301,"technical_vote":1,"hv20_annualized":66.8572,"hv_percentile":100.0,"max_drawdown60":-15.7895,"amount_ma20":95216950.73,"factor_score":0.5837,"shadow_rank":22,"execution":{"order_cny":100000,"participation_pct":0.105,"estimated_impact_bps":2.32,"formula":"2 + 10*sqrt(order/avg_amount_20d)"}},{"symbol":"512070","name":"证券保险ETF易方达","trade_date":"2026-07-15","close":0.808,"ret20":2.2785,"ret60":0.1239,"rsi14":55.57,"ema12":0.7944,"ema26":0.7897,"technical_vote":2,"hv20_annualized":43.5884,"hv_percentile":94.44,"max_drawdown60":-9.6224,"amount_ma20":780276127.95,"factor_score":0.5786,"shadow_rank":23,"execution":{"order_cny":100000,"participation_pct":0.013,"estimated_impact_bps":2.11,"formula":"2 + 10*sqrt(order/avg_amount_20d)"}},{"symbol":"512880","name":"证券ETF国泰","trade_date":"2026-07-15","close":1.13,"ret20":4.4362,"ret60":4.5328,"rsi14":54.9,"ema12":1.1195,"ema26":1.1068,"technical_vote":1,"hv20_annualized":44.2253,"hv_percentile":93.06,"max_drawdown60":-9.1652,"amount_ma20":3483416530.0,"factor_score":0.5559,"shadow_rank":24,"execution":{"order_cny":100000,"participation_pct":0.003,"estimated_impact_bps":2.05,"formula":"2 + 10*sqrt(order/avg_amount_20d)"}},{"symbol":"516560","name":"养老ETF华宝","trade_date":"2026-07-15","close":0.756,"ret20":5.2925,"ret60":-8.4746,"rsi14":60.89,"ema12":0.7256,"ema26":0.7249,"technical_vote":2,"hv20_annualized":31.4064,"hv_percentile":100.0,"max_drawdown60":-17.561,"amount_ma20":4410759.4,"factor_score":0.5374,"shadow_rank":25,"execution":{"order_cny":100000,"participation_pct":2.267,"estimated_impact_bps":3.51,"formula":"2 + 10*sqrt(order/avg_amount_20d)"}},{"symbol":"159940","name":"金融地产ETF广发","trade_date":"2026-07-15","close":1.195,"ret20":1.0144,"ret60":-0.8299,"rsi14":58.86,"ema12":1.1693,"ema26":1.167,"technical_vote":1,"hv20_annualized":27.7006,"hv_percentile":93.06,"max_drawdown60":-6.3584,"amount_ma20":7705662.65,"factor_score":0.4883,"shadow_rank":26,"execution":{"order_cny":100000,"participation_pct":1.298,"estimated_impact_bps":3.14,"formula":"2 + 10*sqrt(order/avg_amount_20d)"}},{"symbol":"588220","name":"科创100ETF鹏华","trade_date":"2026-07-15","close":1.913,"ret20":-0.8808,"ret60":22.4712,"rsi14":44.39,"ema12":2.0272,"ema26":1.998,"technical_vote":1,"hv20_annualized":52.6404,"hv_percentile":98.61,"max_drawdown60":-14.1768,"amount_ma20":647218881.85,"factor_score":0.4523,"shadow_rank":27,"execution":{"order_cny":100000,"participation_pct":0.015,"estimated_impact_bps":2.12,"formula":"2 + 10*sqrt(order/avg_amount_20d)"}},{"symbol":"159998","name":"计算机ETF天弘","trade_date":"2026-07-15","close":0.999,"ret20":2.0429,"ret60":-5.5766,"rsi14":45.24,"ema12":1.0269,"ema26":1.0267,"technical_vote":2,"hv20_annualized":44.7294,"hv_percentile":98.61,"max_drawdown60":-20.1544,"amount_ma20":141477609.56,"factor_score":0.3194,"shadow_rank":28,"execution":{"order_cny":100000,"participation_pct":0.071,"estimated_impact_bps":2.27,"formula":"2 + 10*sqrt(order/avg_amount_20d)"}},{"symbol":"159329","name":"沙特ETF南方","trade_date":"2026-07-15","close":0.887,"ret20":-3.3769,"ret60":-8.273,"rsi14":29.84,"ema12":0.8961,"ema26":0.9024,"technical_vote":1,"hv20_annualized":5.9696,"hv_percentile":4.17,"max_drawdown60":-7.9876,"amount_ma20":26311503.93,"factor_score":0.3157,"shadow_rank":29,"execution":{"order_cny":100000,"participation_pct":0.38,"estimated_impact_bps":2.62,"formula":"2 + 10*sqrt(order/avg_amount_20d)"}},{"symbol":"513520","name":"日经ETF华夏","trade_date":"2026-07-15","close":2.35,"ret20":-4.316,"ret60":14.9144,"rsi14":48.52,"ema12":2.371,"ema26":2.3709,"technical_vote":1,"hv20_annualized":43.3976,"hv_percentile":72.22,"max_drawdown60":-12.7015,"amount_ma20":612741146.15,"factor_score":0.2877,"shadow_rank":30,"execution":{"order_cny":100000,"participation_pct":0.016,"estimated_impact_bps":2.13,"formula":"2 + 10*sqrt(order/avg_amount_20d)"}},{"symbol":"159732","name":"消费电子ETF华夏","trade_date":"2026-07-15","close":1.571,"ret20":-3.2635,"ret60":28.7705,"rsi14":44.12,"ema12":1.6752,"ema26":1.6706,"technical_vote":1,"hv20_annualized":70.0814,"hv_percentile":98.61,"max_drawdown60":-18.4896,"amount_ma20":825640687.05,"factor_score":0.2643,"shadow_rank":31,"execution":{"order_cny":100000,"participation_pct":0.012,"estimated_impact_bps":2.11,"formula":"2 + 10*sqrt(order/avg_amount_20d)"}},{"symbol":"513310","name":"中韩半导体ETF华泰柏瑞","trade_date":"2026-07-15","close":5.574,"ret20":-6.4451,"ret60":45.8017,"rsi14":42.81,"ema12":5.9116,"ema26":5.9475,"technical_vote":0,"hv20_annualized":61.4609,"hv_percentile":30.56,"max_drawdown60":-19.1444,"amount_ma20":14151872406.5,"factor_score":0.2354,"shadow_rank":32,"execution":{"order_cny":100000,"participation_pct":0.001,"estimated_impact_bps":2.03,"formula":"2 + 10*sqrt(order/avg_amount_20d)"}},{"symbol":"159920","name":"恒生ETF华夏","trade_date":"2026-07-15","close":1.468,"ret20":2.2284,"ret60":-5.6555,"rsi14":61.57,"ema12":1.4219,"ema26":1.4228,"technical_vote":0,"hv20_annualized":21.7889,"hv_percentile":73.61,"max_drawdown60":-14.377,"amount_ma20":463016209.05,"factor_score":0.2088,"shadow_rank":33,"execution":{"order_cny":100000,"participation_pct":0.022,"estimated_impact_bps":2.15,"formula":"2 + 10*sqrt(order/avg_amount_20d)"}},{"symbol":"510210","name":"上证指数ETF富国","trade_date":"2026-07-15","close":0.997,"ret20":-2.9211,"ret60":-2.159,"rsi14":41.82,"ema12":1.0076,"ema26":1.0148,"technical_vote":0,"hv20_annualized":16.7551,"hv_percentile":65.28,"max_drawdown60":-7.3102,"amount_ma20":1012115407.5,"factor_score":0.1861,"shadow_rank":34,"execution":{"order_cny":100000,"participation_pct":0.01,"estimated_impact_bps":2.1,"formula":"2 + 10*sqrt(order/avg_amount_20d)"}},{"symbol":"159941","name":"纳指ETF广发","trade_date":"2026-07-15","close":1.629,"ret20":-3.7234,"ret60":15.3683,"rsi14":51.4,"ema12":1.6224,"ema26":1.6227,"technical_vote":-1,"hv20_annualized":22.1291,"hv_percentile":16.67,"max_drawdown60":-11.0544,"amount_ma20":1697086298.0,"factor_score":0.1264,"shadow_rank":35,"execution":{"order_cny":100000,"participation_pct":0.006,"estimated_impact_bps":2.08,"formula":"2 + 10*sqrt(order/avg_amount_20d)"}},{"symbol":"515180","name":"红利ETF易方达","trade_date":"2026-07-15","close":1.374,"ret20":-0.8658,"ret60":-4.0503,"rsi14":56.05,"ema12":1.3393,"ema26":1.3502,"technical_vote":0,"hv20_annualized":21.8057,"hv_percentile":100.0,"max_drawdown60":-13.0701,"amount_ma20":458567720.75,"factor_score":0.1235,"shadow_rank":36,"execution":{"order_cny":100000,"participation_pct":0.022,"estimated_impact_bps":2.15,"formula":"2 + 10*sqrt(order/avg_amount_20d)"}},{"symbol":"516530","name":"物流ETF银华","trade_date":"2026-07-15","close":0.974,"ret20":0.6198,"ret60":-7.0611,"rsi14":51.73,"ema12":0.9571,"ema26":0.9668,"technical_vote":0,"hv20_annualized":32.6492,"hv_percentile":86.11,"max_drawdown60":-12.2159,"amount_ma20":712402.36,"factor_score":0.0889,"shadow_rank":37,"execution":{"order_cny":100000,"participation_pct":14.037,"estimated_impact_bps":5.75,"formula":"2 + 10*sqrt(order/avg_amount_20d)"}},{"symbol":"510310","name":"沪深300ETF易方达","trade_date":"2026-07-15","close":4.695,"ret20":-1.3241,"ret60":2.2653,"rsi14":47.8,"ema12":4.7126,"ema26":4.7302,"technical_vote":-1,"hv20_annualized":27.0,"hv_percentile":100.0,"max_drawdown60":-6.7302,"amount_ma20":3763333507.1,"factor_score":0.0823,"shadow_rank":38,"execution":{"order_cny":100000,"participation_pct":0.003,"estimated_impact_bps":2.05,"formula":"2 + 10*sqrt(order/avg_amount_20d)"}},{"symbol":"513180","name":"恒生科技ETF华夏","trade_date":"2026-07-15","close":0.603,"ret20":2.2034,"ret60":-7.2308,"rsi14":55.81,"ema12":0.5893,"ema26":0.5899,"technical_vote":0,"hv20_annualized":32.7151,"hv_percentile":80.56,"max_drawdown60":-17.1254,"amount_ma20":3745904499.3,"factor_score":0.075,"shadow_rank":39,"execution":{"order_cny":100000,"participation_pct":0.003,"estimated_impact_bps":2.05,"formula":"2 + 10*sqrt(order/avg_amount_20d)"}},{"symbol":"512890","name":"红利低波ETF华泰柏瑞","trade_date":"2026-07-15","close":1.152,"ret20":0.6114,"ret60":-3.1119,"rsi14":59.91,"ema12":1.1195,"ema26":1.123,"technical_vote":-1,"hv20_annualized":19.6582,"hv_percentile":98.61,"max_drawdown60":-10.9349,"amount_ma20":911338377.85,"factor_score":0.0687,"shadow_rank":40,"execution":{"order_cny":100000,"participation_pct":0.011,"estimated_impact_bps":2.1,"formula":"2 + 10*sqrt(order/avg_amount_20d)"}},{"symbol":"511380","name":"可转债ETF博时","trade_date":"2026-07-15","close":13.801,"ret20":-2.9397,"ret60":-3.3746,"rsi14":43.7,"ema12":13.879,"ema26":13.936,"technical_vote":-1,"hv20_annualized":10.0608,"hv_percentile":1.39,"max_drawdown60":-5.5319,"amount_ma20":8225723274.5,"factor_score":0.0629,"shadow_rank":41,"execution":{"order_cny":100000,"participation_pct":0.001,"estimated_impact_bps":2.03,"formula":"2 + 10*sqrt(order/avg_amount_20d)"}},{"symbol":"159996","name":"家电ETF国泰","trade_date":"2026-07-15","close":1.456,"ret20":-1.1541,"ret60":-0.4785,"rsi14":49.97,"ema12":1.4453,"ema26":1.4554,"technical_vote":-1,"hv20_annualized":20.8927,"hv_percentile":80.56,"max_drawdown60":-10.1716,"amount_ma20":70480123.79,"factor_score":0.0362,"shadow_rank":42,"execution":{"order_cny":100000,"participation_pct":0.142,"estimated_impact_bps":2.38,"formula":"2 + 10*sqrt(order/avg_amount_20d)"}},{"symbol":"513080","name":"法国ETF华安","trade_date":"2026-07-15","close":1.739,"ret20":-2.1935,"ret60":-3.8695,"rsi14":47.47,"ema12":1.7473,"ema26":1.7496,"technical_vote":-1,"hv20_annualized":17.8509,"hv_percentile":27.78,"max_drawdown60":-6.4942,"amount_ma20":64937735.9,"factor_score":0.0231,"shadow_rank":43,"execution":{"order_cny":100000,"participation_pct":0.154,"estimated_impact_bps":2.39,"formula":"2 + 10*sqrt(order/avg_amount_20d)"}},{"symbol":"159883","name":"医疗器械ETF永赢","trade_date":"2026-07-15","close":0.436,"ret20":1.8692,"ret60":-9.7308,"rsi14":54.43,"ema12":0.4241,"ema26":0.4285,"technical_vote":0,"hv20_annualized":31.5361,"hv_percentile":90.28,"max_drawdown60":-18.6235,"amount_ma20":98225458.78,"factor_score":0.0109,"shadow_rank":44,"execution":{"order_cny":100000,"participation_pct":0.102,"estimated_impact_bps":2.32,"formula":"2 + 10*sqrt(order/avg_amount_20d)"}},{"symbol":"159928","name":"消费ETF汇添富","trade_date":"2026-07-15","close":0.656,"ret20":2.3401,"ret60":-12.8818,"rsi14":57.77,"ema12":0.6328,"ema26":0.6388,"technical_vote":0,"hv20_annualized":27.1178,"hv_percentile":100.0,"max_drawdown60":-19.2771,"amount_ma20":327784807.75,"factor_score":0.0045,"shadow_rank":45,"execution":{"order_cny":100000,"participation_pct":0.031,"estimated_impact_bps":2.17,"formula":"2 + 10*sqrt(order/avg_amount_20d)"}},{"symbol":"563360","name":"A500ETF华泰柏瑞","trade_date":"2026-07-15","close":1.34,"ret20":-2.2611,"ret60":1.3616,"rsi14":45.23,"ema12":1.3573,"ema26":1.365,"technical_vote":-1,"hv20_annualized":30.1436,"hv_percentile":97.22,"max_drawdown60":-7.9609,"amount_ma20":3614911854.0,"factor_score":-0.0076,"shadow_rank":46,"execution":{"order_cny":100000,"participation_pct":0.003,"estimated_impact_bps":2.05,"formula":"2 + 10*sqrt(order/avg_amount_20d)"}},{"symbol":"513730","name":"东南亚科技ETF华泰柏瑞","trade_date":"2026-07-15","close":1.17,"ret20":-0.8475,"ret60":-7.2165,"rsi14":52.1,"ema12":1.1608,"ema26":1.1637,"technical_vote":-1,"hv20_annualized":21.9093,"hv_percentile":26.39,"max_drawdown60":-10.5723,"amount_ma20":39283305.1,"factor_score":-0.0563,"shadow_rank":47,"execution":{"order_cny":100000,"participation_pct":0.255,"estimated_impact_bps":2.5,"formula":"2 + 10*sqrt(order/avg_amount_20d)"}},{"symbol":"159865","name":"养殖ETF国泰","trade_date":"2026-07-15","close":0.534,"ret20":4.501,"ret60":-15.5063,"rsi14":56.49,"ema12":0.5192,"ema26":0.5203,"technical_vote":0,"hv20_annualized":35.8609,"hv_percentile":100.0,"max_drawdown60":-23.3974,"amount_ma20":231931376.7,"factor_score":-0.0614,"shadow_rank":48,"execution":{"order_cny":100000,"participation_pct":0.043,"estimated_impact_bps":2.21,"formula":"2 + 10*sqrt(order/avg_amount_20d)"}},{"symbol":"159869","name":"游戏ETF华夏","trade_date":"2026-07-15","close":1.117,"ret20":5.08,"ret60":-17.2593,"rsi14":51.69,"ema12":1.0957,"ema26":1.106,"technical_vote":0,"hv20_annualized":40.074,"hv_percentile":83.33,"max_drawdown60":-22.8381,"amount_ma20":701646881.4,"factor_score":-0.0792,"shadow_rank":49,"execution":{"order_cny":100000,"participation_pct":0.014,"estimated_impact_bps":2.12,"formula":"2 + 10*sqrt(order/avg_amount_20d)"}},{"symbol":"516950","name":"基建ETF银华","trade_date":"2026-07-15","close":1.033,"ret20":-2.5472,"ret60":-10.8714,"rsi14":46.42,"ema12":1.0294,"ema26":1.0436,"technical_vote":0,"hv20_annualized":25.7326,"hv_percentile":80.56,"max_drawdown60":-14.237,"amount_ma20":10238067.05,"factor_score":-0.0822,"shadow_rank":50,"execution":{"order_cny":100000,"participation_pct":0.977,"estimated_impact_bps":2.99,"formula":"2 + 10*sqrt(order/avg_amount_20d)"}},{"symbol":"159201","name":"自由现金流ETF华夏","trade_date":"2026-07-15","close":1.131,"ret20":-1.2227,"ret60":-14.5125,"rsi14":51.9,"ema12":1.1018,"ema26":1.1221,"technical_vote":0,"hv20_annualized":24.128,"hv_percentile":98.61,"max_drawdown60":-19.9849,"amount_ma20":437004698.4,"factor_score":-0.1571,"shadow_rank":51,"execution":{"order_cny":100000,"participation_pct":0.023,"estimated_impact_bps":2.15,"formula":"2 + 10*sqrt(order/avg_amount_20d)"}},{"symbol":"159915","name":"创业板ETF易方达","trade_date":"2026-07-15","close":3.828,"ret20":-6.884,"ret60":5.6291,"rsi14":43.07,"ema12":3.9503,"ema26":4.0034,"technical_vote":0,"hv20_annualized":46.7221,"hv_percentile":91.67,"max_drawdown60":-14.653,"amount_ma20":6418554101.0,"factor_score":-0.1722,"shadow_rank":52,"execution":{"order_cny":100000,"participation_pct":0.002,"estimated_impact_bps":2.04,"formula":"2 + 10*sqrt(order/avg_amount_20d)"}},{"symbol":"516510","name":"云计算ETF易方达","trade_date":"2026-07-15","close":1.72,"ret20":1.0576,"ret60":-5.5464,"rsi14":47.55,"ema12":1.7422,"ema26":1.7432,"technical_vote":-1,"hv20_annualized":46.0043,"hv_percentile":83.33,"max_drawdown60":-18.2093,"amount_ma20":220625405.65,"factor_score":-0.2246,"shadow_rank":53,"execution":{"order_cny":100000,"participation_pct":0.045,"estimated_impact_bps":2.21,"formula":"2 + 10*sqrt(order/avg_amount_20d)"}},{"symbol":"515220","name":"煤炭ETF国泰","trade_date":"2026-07-15","close":1.186,"ret20":-3.1837,"ret60":-1.0017,"rsi14":52.76,"ema12":1.1441,"ema26":1.1673,"technical_vote":0,"hv20_annualized":38.6498,"hv_percentile":66.67,"max_drawdown60":-25.3846,"amount_ma20":918015628.1,"factor_score":-0.2274,"shadow_rank":54,"execution":{"order_cny":100000,"participation_pct":0.011,"estimated_impact_bps":2.1,"formula":"2 + 10*sqrt(order/avg_amount_20d)"}},{"symbol":"513360","name":"教育ETF博时","trade_date":"2026-07-15","close":0.437,"ret20":1.1574,"ret60":-14.4814,"rsi14":47.9,"ema12":0.4358,"ema26":0.4389,"technical_vote":-1,"hv20_annualized":21.6102,"hv_percentile":75.0,"max_drawdown60":-21.2355,"amount_ma20":45541785.6,"factor_score":-0.2377,"shadow_rank":55,"execution":{"order_cny":100000,"participation_pct":0.22,"estimated_impact_bps":2.47,"formula":"2 + 10*sqrt(order/avg_amount_20d)"}},{"symbol":"512690","name":"酒ETF鹏华","trade_date":"2026-07-15","close":0.416,"ret20":-0.716,"ret60":-15.6187,"rsi14":54.98,"ema12":0.3986,"ema26":0.4068,"technical_vote":0,"hv20_annualized":33.0286,"hv_percentile":100.0,"max_drawdown60":-21.9959,"amount_ma20":746778777.6,"factor_score":-0.2384,"shadow_rank":56,"execution":{"order_cny":100000,"participation_pct":0.013,"estimated_impact_bps":2.12,"formula":"2 + 10*sqrt(order/avg_amount_20d)"}},{"symbol":"510500","name":"中证500ETF南方","trade_date":"2026-07-15","close":8.151,"ret20":-5.5723,"ret60":-1.2359,"rsi14":37.85,"ema12":8.5244,"ema26":8.6071,"technical_vote":-1,"hv20_annualized":32.0193,"hv_percentile":83.33,"max_drawdown60":-11.4314,"amount_ma20":3398195148.5,"factor_score":-0.2456,"shadow_rank":57,"execution":{"order_cny":100000,"participation_pct":0.003,"estimated_impact_bps":2.05,"formula":"2 + 10*sqrt(order/avg_amount_20d)"}},{"symbol":"512100","name":"中证1000ETF南方","trade_date":"2026-07-15","close":3.169,"ret20":-9.2237,"ret60":-3.9115,"rsi14":35.19,"ema12":3.3211,"ema26":3.3808,"technical_vote":0,"hv20_annualized":29.7346,"hv_percentile":84.72,"max_drawdown60":-12.229,"amount_ma20":3374894935.5,"factor_score":-0.2556,"shadow_rank":58,"execution":{"order_cny":100000,"participation_pct":0.003,"estimated_impact_bps":2.05,"formula":"2 + 10*sqrt(order/avg_amount_20d)"}},{"symbol":"512200","name":"房地产ETF南方","trade_date":"2026-07-15","close":1.195,"ret20":-5.0834,"ret60":-13.4685,"rsi14":41.48,"ema12":1.1961,"ema26":1.225,"technical_vote":0,"hv20_annualized":22.1664,"hv_percentile":45.83,"max_drawdown60":-22.4503,"amount_ma20":147839312.5,"factor_score":-0.3281,"shadow_rank":59,"execution":{"order_cny":100000,"participation_pct":0.068,"estimated_impact_bps":2.26,"formula":"2 + 10*sqrt(order/avg_amount_20d)"}},{"symbol":"516520","name":"智能驾驶ETF华泰柏瑞","trade_date":"2026-07-15","close":1.102,"ret20":-6.4516,"ret60":-10.6245,"rsi14":37.96,"ema12":1.1487,"ema26":1.1716,"technical_vote":0,"hv20_annualized":38.9588,"hv_percentile":97.22,"max_drawdown60":-16.0522,"amount_ma20":79723044.55,"factor_score":-0.3508,"shadow_rank":60,"execution":{"order_cny":100000,"participation_pct":0.125,"estimated_impact_bps":2.35,"formula":"2 + 10*sqrt(order/avg_amount_20d)"}},{"symbol":"560280","name":"工程机械ETF广发","trade_date":"2026-07-15","close":1.527,"ret20":-6.6626,"ret60":-10.0177,"rsi14":40.98,"ema12":1.5445,"ema26":1.5808,"technical_vote":0,"hv20_annualized":31.5269,"hv_percentile":66.67,"max_drawdown60":-19.5676,"amount_ma20":171337810.45,"factor_score":-0.3594,"shadow_rank":61,"execution":{"order_cny":100000,"participation_pct":0.058,"estimated_impact_bps":2.24,"formula":"2 + 10*sqrt(order/avg_amount_20d)"}},{"symbol":"159825","name":"农业ETF富国","trade_date":"2026-07-15","close":0.705,"ret20":1.585,"ret60":-18.2135,"rsi14":53.4,"ema12":0.6878,"ema26":0.6948,"technical_vote":-1,"hv20_annualized":31.4899,"hv_percentile":98.61,"max_drawdown60":-23.4118,"amount_ma20":83368826.17,"factor_score":-0.367,"shadow_rank":62,"execution":{"order_cny":100000,"participation_pct":0.12,"estimated_impact_bps":2.35,"formula":"2 + 10*sqrt(order/avg_amount_20d)"}},{"symbol":"515880","name":"通信ETF国泰","trade_date":"2026-07-15","close":0.759,"ret20":-12.2543,"ret60":20.0949,"rsi14":43.94,"ema12":0.7894,"ema26":0.8048,"technical_vote":0,"hv20_annualized":67.1334,"hv_percentile":97.22,"max_drawdown60":-21.6561,"amount_ma20":6226867537.0,"factor_score":-0.4318,"shadow_rank":63,"execution":{"order_cny":100000,"participation_pct":0.002,"estimated_impact_bps":2.04,"formula":"2 + 10*sqrt(order/avg_amount_20d)"}},{"symbol":"562500","name":"机器人ETF华夏","trade_date":"2026-07-15","close":1.046,"ret20":-8.4063,"ret60":4.3912,"rsi14":39.72,"ema12":1.0952,"ema26":1.1128,"technical_vote":-1,"hv20_annualized":49.3949,"hv_percentile":95.83,"max_drawdown60":-14.3092,"amount_ma20":1038889937.75,"factor_score":-0.4387,"shadow_rank":64,"execution":{"order_cny":100000,"participation_pct":0.01,"estimated_impact_bps":2.1,"formula":"2 + 10*sqrt(order/avg_amount_20d)"}},{"symbol":"512980","name":"传媒ETF广发","trade_date":"2026-07-15","close":0.816,"ret20":-2.2754,"ret60":-20.9302,"rsi14":45.22,"ema12":0.8133,"ema26":0.8331,"technical_vote":0,"hv20_annualized":35.2769,"hv_percentile":72.22,"max_drawdown60":-25.2622,"amount_ma20":205947267.9,"factor_score":-0.4406,"shadow_rank":65,"execution":{"order_cny":100000,"participation_pct":0.049,"estimated_impact_bps":2.22,"formula":"2 + 10*sqrt(order/avg_amount_20d)"}},{"symbol":"159309","name":"油气ETF汇添富","trade_date":"2026-07-15","close":1.286,"ret20":-3.8864,"ret60":-14.2667,"rsi14":43.43,"ema12":1.2899,"ema26":1.3187,"technical_vote":-1,"hv20_annualized":30.4215,"hv_percentile":90.28,"max_drawdown60":-19.0077,"amount_ma20":57874237.92,"factor_score":-0.4631,"shadow_rank":66,"execution":{"order_cny":100000,"participation_pct":0.173,"estimated_impact_bps":2.42,"formula":"2 + 10*sqrt(order/avg_amount_20d)"}},{"symbol":"159766","name":"旅游ETF富国","trade_date":"2026-07-15","close":0.552,"ret20":-6.1224,"ret60":-20.2312,"rsi14":45.32,"ema12":0.5479,"ema26":0.5617,"technical_vote":0,"hv20_annualized":28.345,"hv_percentile":70.83,"max_drawdown60":-22.3358,"amount_ma20":164195189.95,"factor_score":-0.5007,"shadow_rank":67,"execution":{"order_cny":100000,"participation_pct":0.061,"estimated_impact_bps":2.25,"formula":"2 + 10*sqrt(order/avg_amount_20d)"}},{"symbol":"563300","name":"中证2000ETF华泰柏瑞","trade_date":"2026-07-15","close":1.443,"ret20":-10.1494,"ret60":-5.1905,"rsi14":35.13,"ema12":1.5122,"ema26":1.5437,"technical_vote":-1,"hv20_annualized":30.8995,"hv_percentile":73.61,"max_drawdown60":-14.0024,"amount_ma20":534023384.3,"factor_score":-0.5217,"shadow_rank":68,"execution":{"order_cny":100000,"participation_pct":0.019,"estimated_impact_bps":2.14,"formula":"2 + 10*sqrt(order/avg_amount_20d)"}},{"symbol":"516110","name":"汽车ETF国泰","trade_date":"2026-07-15","close":1.125,"ret20":-4.0102,"ret60":-16.6049,"rsi14":45.1,"ema12":1.1207,"ema26":1.1451,"technical_vote":-1,"hv20_annualized":31.693,"hv_percentile":100.0,"max_drawdown60":-20.0447,"amount_ma20":36004298.0,"factor_score":-0.5244,"shadow_rank":69,"execution":{"order_cny":100000,"participation_pct":0.278,"estimated_impact_bps":2.53,"formula":"2 + 10*sqrt(order/avg_amount_20d)"}},{"symbol":"518880","name":"黄金ETF华安","trade_date":"2026-07-15","close":8.369,"ret20":-6.4812,"ret60":-17.114,"rsi14":36.56,"ema12":8.4957,"ema26":8.6576,"technical_vote":-1,"hv20_annualized":20.9672,"hv_percentile":34.72,"max_drawdown60":-17.5867,"amount_ma20":2893059700.5,"factor_score":-0.5279,"shadow_rank":70,"execution":{"order_cny":100000,"participation_pct":0.003,"estimated_impact_bps":2.06,"formula":"2 + 10*sqrt(order/avg_amount_20d)"}},{"symbol":"159611","name":"电力ETF广发","trade_date":"2026-07-15","close":1.028,"ret20":-9.9825,"ret60":-6.3752,"rsi14":39.45,"ema12":1.0301,"ema26":1.0613,"technical_vote":-1,"hv20_annualized":21.2676,"hv_percentile":25.0,"max_drawdown60":-19.9682,"amount_ma20":555440651.45,"factor_score":-0.5637,"shadow_rank":71,"execution":{"order_cny":100000,"participation_pct":0.018,"estimated_impact_bps":2.13,"formula":"2 + 10*sqrt(order/avg_amount_20d)"}},{"symbol":"159667","name":"工业母机ETF国泰","trade_date":"2026-07-15","close":0.747,"ret20":-14.1379,"ret60":17.2684,"rsi14":38.42,"ema12":0.81,"ema26":0.8222,"technical_vote":-1,"hv20_annualized":53.2957,"hv_percentile":97.22,"max_drawdown60":-18.716,"amount_ma20":363754877.8,"factor_score":-0.5912,"shadow_rank":72,"execution":{"order_cny":100000,"participation_pct":0.027,"estimated_impact_bps":2.17,"formula":"2 + 10*sqrt(order/avg_amount_20d)"}},{"symbol":"159852","name":"软件ETF嘉实","trade_date":"2026-07-15","close":0.682,"ret20":-3.125,"ret60":-16.9306,"rsi14":44.23,"ema12":0.6879,"ema26":0.7023,"technical_vote":-1,"hv20_annualized":38.9913,"hv_percentile":75.0,"max_drawdown60":-23.8426,"amount_ma20":390248446.45,"factor_score":-0.5972,"shadow_rank":73,"execution":{"order_cny":100000,"participation_pct":0.026,"estimated_impact_bps":2.16,"formula":"2 + 10*sqrt(order/avg_amount_20d)"}},{"symbol":"512580","name":"环保ETF广发","trade_date":"2026-07-15","close":1.178,"ret20":-13.8889,"ret60":-15.1908,"rsi14":28.21,"ema12":1.2332,"ema26":1.282,"technical_vote":0,"hv20_annualized":28.6093,"hv_percentile":77.78,"max_drawdown60":-20.8702,"amount_ma20":12187926.37,"factor_score":-0.7304,"shadow_rank":74,"execution":{"order_cny":100000,"participation_pct":0.82,"estimated_impact_bps":2.91,"formula":"2 + 10*sqrt(order/avg_amount_20d)"}},{"symbol":"159745","name":"建材ETF国泰","trade_date":"2026-07-15","close":0.53,"ret20":-8.9347,"ret60":-19.2073,"rsi14":33.98,"ema12":0.5392,"ema26":0.557,"technical_vote":-1,"hv20_annualized":24.9962,"hv_percentile":80.56,"max_drawdown60":-22.3388,"amount_ma20":57511969.5,"factor_score":-0.757,"shadow_rank":75,"execution":{"order_cny":100000,"participation_pct":0.174,"estimated_impact_bps":2.42,"formula":"2 + 10*sqrt(order/avg_amount_20d)"}},{"symbol":"560710","name":"船舶ETF富国","trade_date":"2026-07-15","close":0.856,"ret20":-7.2589,"ret60":-16.9738,"rsi14":39.32,"ema12":0.883,"ema26":0.9074,"technical_vote":-1,"hv20_annualized":41.9918,"hv_percentile":98.61,"max_drawdown60":-24.1993,"amount_ma20":90625462.45,"factor_score":-0.7926,"shadow_rank":76,"execution":{"order_cny":100000,"participation_pct":0.11,"estimated_impact_bps":2.33,"formula":"2 + 10*sqrt(order/avg_amount_20d)"}},{"symbol":"515210","name":"钢铁ETF国泰","trade_date":"2026-07-15","close":1.145,"ret20":-7.8842,"ret60":-22.7395,"rsi14":40.06,"ema12":1.1459,"ema26":1.1839,"technical_vote":-1,"hv20_annualized":25.8692,"hv_percentile":80.56,"max_drawdown60":-25.2539,"amount_ma20":83995103.4,"factor_score":-0.8131,"shadow_rank":77,"execution":{"order_cny":100000,"participation_pct":0.119,"estimated_impact_bps":2.35,"formula":"2 + 10*sqrt(order/avg_amount_20d)"}},{"symbol":"159870","name":"化工ETF鹏华","trade_date":"2026-07-15","close":0.773,"ret20":-9.6963,"ret60":-14.9615,"rsi14":36.3,"ema12":0.8095,"ema26":0.8313,"technical_vote":-1,"hv20_annualized":45.143,"hv_percentile":98.61,"max_drawdown60":-22.314,"amount_ma20":748486874.75,"factor_score":-0.8558,"shadow_rank":78,"execution":{"order_cny":100000,"participation_pct":0.013,"estimated_impact_bps":2.12,"formula":"2 + 10*sqrt(order/avg_amount_20d)"}},{"symbol":"512660","name":"军工ETF国泰","trade_date":"2026-07-15","close":1.143,"ret20":-9.7869,"ret60":-16.8727,"rsi14":34.73,"ema12":1.2223,"ema26":1.2508,"technical_vote":-1,"hv20_annualized":42.5032,"hv_percentile":100.0,"max_drawdown60":-23.1855,"amount_ma20":361813962.65,"factor_score":-0.8828,"shadow_rank":79,"execution":{"order_cny":100000,"participation_pct":0.028,"estimated_impact_bps":2.17,"formula":"2 + 10*sqrt(order/avg_amount_20d)"}},{"symbol":"515790","name":"光伏ETF华泰柏瑞","trade_date":"2026-07-15","close":0.85,"ret20":-17.795,"ret60":-20.5607,"rsi14":26.03,"ema12":0.9123,"ema26":0.9607,"technical_vote":1,"hv20_annualized":35.8094,"hv_percentile":91.67,"max_drawdown60":-25.9162,"amount_ma20":287578749.5,"factor_score":-0.9135,"shadow_rank":80,"execution":{"order_cny":100000,"participation_pct":0.035,"estimated_impact_bps":2.19,"formula":"2 + 10*sqrt(order/avg_amount_20d)"}},{"symbol":"159851","name":"金融科技ETF华宝","trade_date":"2026-07-15","close":0.593,"ret20":-8.7692,"ret60":-20.1884,"rsi14":38.76,"ema12":0.608,"ema26":0.629,"technical_vote":-1,"hv20_annualized":47.7243,"hv_percentile":84.72,"max_drawdown60":-24.349,"amount_ma20":340724915.75,"factor_score":-0.9372,"shadow_rank":81,"execution":{"order_cny":100000,"participation_pct":0.029,"estimated_impact_bps":2.17,"formula":"2 + 10*sqrt(order/avg_amount_20d)"}},{"symbol":"159326","name":"电网设备ETF华夏","trade_date":"2026-07-15","close":1.697,"ret20":-20.5896,"ret60":-11.2912,"rsi14":29.82,"ema12":1.8412,"ema26":1.9358,"technical_vote":0,"hv20_annualized":44.2644,"hv_percentile":87.5,"max_drawdown60":-25.0664,"amount_ma20":1066036745.9,"factor_score":-1.1165,"shadow_rank":82,"execution":{"order_cny":100000,"participation_pct":0.009,"estimated_impact_bps":2.1,"formula":"2 + 10*sqrt(order/avg_amount_20d)"}},{"symbol":"159206","name":"卫星ETF永赢","trade_date":"2026-07-15","close":1.471,"ret20":-9.8099,"ret60":-17.1734,"rsi14":37.95,"ema12":1.6347,"ema26":1.6647,"technical_vote":-1,"hv20_annualized":68.5183,"hv_percentile":100.0,"max_drawdown60":-27.5726,"amount_ma20":1828682860.75,"factor_score":-1.1191,"shadow_rank":83,"execution":{"order_cny":100000,"participation_pct":0.005,"estimated_impact_bps":2.07,"formula":"2 + 10*sqrt(order/avg_amount_20d)"}},{"symbol":"159566","name":"储能电池ETF易方达","trade_date":"2026-07-15","close":1.918,"ret20":-16.3541,"ret60":-17.7883,"rsi14":33.74,"ema12":2.0304,"ema26":2.1208,"technical_vote":-1,"hv20_annualized":41.4089,"hv_percentile":77.78,"max_drawdown60":-23.9646,"amount_ma20":423597211.9,"factor_score":-1.1714,"shadow_rank":84,"execution":{"order_cny":100000,"participation_pct":0.024,"estimated_impact_bps":2.15,"formula":"2 + 10*sqrt(order/avg_amount_20d)"}},{"symbol":"159755","name":"电池ETF广发","trade_date":"2026-07-15","close":0.958,"ret20":-15.5203,"ret60":-19.6982,"rsi14":31.91,"ema12":1.0133,"ema26":1.0549,"technical_vote":-1,"hv20_annualized":40.9883,"hv_percentile":93.06,"max_drawdown60":-26.1417,"amount_ma20":532013972.95,"factor_score":-1.1946,"shadow_rank":85,"execution":{"order_cny":100000,"participation_pct":0.019,"estimated_impact_bps":2.14,"formula":"2 + 10*sqrt(order/avg_amount_20d)"}},{"symbol":"512400","name":"有色金属ETF南方","trade_date":"2026-07-15","close":1.739,"ret20":-15.1293,"ret60":-19.8618,"rsi14":38.97,"ema12":1.7952,"ema26":1.8632,"technical_vote":-1,"hv20_annualized":50.6983,"hv_percentile":80.56,"max_drawdown60":-23.9928,"amount_ma20":1260139774.55,"factor_score":-1.208,"shadow_rank":86,"execution":{"order_cny":100000,"participation_pct":0.008,"estimated_impact_bps":2.09,"formula":"2 + 10*sqrt(order/avg_amount_20d)"}},{"symbol":"516150","name":"稀土ETF嘉实","trade_date":"2026-07-15","close":1.717,"ret20":-18.3159,"ret60":-13.3266,"rsi14":31.98,"ema12":1.8647,"ema26":1.9335,"technical_vote":-1,"hv20_annualized":48.9789,"hv_percentile":97.22,"max_drawdown60":-23.4899,"amount_ma20":333703597.0,"factor_score":-1.231,"shadow_rank":87,"execution":{"order_cny":100000,"participation_pct":0.03,"estimated_impact_bps":2.17,"formula":"2 + 10*sqrt(order/avg_amount_20d)"}},{"symbol":"159227","name":"航空航天ETF华夏","trade_date":"2026-07-15","close":0.995,"ret20":-12.6427,"ret60":-24.7352,"rsi14":35.04,"ema12":1.0719,"ema26":1.106,"technical_vote":-1,"hv20_annualized":49.8193,"hv_percentile":98.61,"max_drawdown60":-28.3141,"amount_ma20":404874094.9,"factor_score":-1.2342,"shadow_rank":88,"execution":{"order_cny":100000,"participation_pct":0.025,"estimated_impact_bps":2.16,"formula":"2 + 10*sqrt(order/avg_amount_20d)"}},{"symbol":"517520","name":"黄金股ETF永赢","trade_date":"2026-07-15","close":1.703,"ret20":-9.8465,"ret60":-26.5948,"rsi14":46.12,"ema12":1.7012,"ema26":1.7458,"technical_vote":-1,"hv20_annualized":56.9929,"hv_percentile":70.83,"max_drawdown60":-31.8103,"amount_ma20":489085667.35,"factor_score":-1.2438,"shadow_rank":89,"execution":{"order_cny":100000,"participation_pct":0.02,"estimated_impact_bps":2.14,"formula":"2 + 10*sqrt(order/avg_amount_20d)"}}],"promotion_gate":{"minimum_trading_days":20,"required_checks":["rank_ic","hit_rate","max_drawdown","turnover","net_of_cost_increment"]}}