{"market":"US","model_version":"US ETF Garden v3 · Flower Signals","generated_at":"2026-07-13T18:31:03.783491-04:00","model_date":"2026-07-13","quote_trade_date":"2026-07-13","timezone":"America/New_York","data_source":"Yahoo Chart API","session_state":"closed","stage":"美股收盘版","trigger_base_date":"2026-07-10","trigger_base_rows":{"HACK":{"symbol":"HACK","support":104.21,"target":113.75,"stop":101.51,"price":108.98,"trade_date":"2026-07-10"},"XBI":{"symbol":"XBI","support":152.69,"target":165.37,"stop":150.57,"price":159.03,"trade_date":"2026-07-10"},"CIBR":{"symbol":"CIBR","support":88.08,"target":95.68,"stop":86.81,"price":91.88,"trade_date":"2026-07-10"},"IBB":{"symbol":"IBB","support":186.47,"target":197.65,"stop":184.23,"price":192.06,"trade_date":"2026-07-10"},"KIE":{"symbol":"KIE","support":61.99,"target":64.93,"stop":60.71,"price":63.46,"trade_date":"2026-07-10"},"IHF":{"symbol":"IHF","support":55.78,"target":58.18,"stop":54.93,"price":56.98,"trade_date":"2026-07-10"},"XLK":{"symbol":"XLK","support":185.23,"target":192.78,"stop":176.45,"price":185.78,"trade_date":"2026-07-10"},"FDN":{"symbol":"FDN","support":268.73,"target":283.69,"stop":266.05,"price":276.21,"trade_date":"2026-07-10"},"ARKK":{"symbol":"ARKK","support":79.31,"target":84.18,"stop":75.0,"price":80.25,"trade_date":"2026-07-10"},"XLF":{"symbol":"XLF","support":54.67,"target":56.75,"stop":54.24,"price":55.71,"trade_date":"2026-07-10"},"QQQ":{"symbol":"QQQ","support":722.32,"target":745.33,"stop":699.09,"price":725.51,"trade_date":"2026-07-10"},"VTI":{"symbol":"VTI","support":367.5,"target":378.52,"stop":364.91,"price":372.69,"trade_date":"2026-07-10"},"XLV":{"symbol":"XLV","support":157.21,"target":164.47,"stop":156.0,"price":160.84,"trade_date":"2026-07-10"},"EWJ":{"symbol":"EWJ","support":93.65,"target":96.24,"stop":92.3,"price":94.55,"trade_date":"2026-07-10"},"IYT":{"symbol":"IYT","support":86.36,"target":90.17,"stop":85.38,"price":88.12,"trade_date":"2026-07-10"},"ETHA":{"symbol":"ETHA","support":12.88,"target":14.18,"stop":12.66,"price":13.53,"trade_date":"2026-07-10"},"EWZ":{"symbol":"EWZ","support":35.11,"target":36.75,"stop":34.49,"price":35.93,"trade_date":"2026-07-10"},"KRE":{"symbol":"KRE","support":73.71,"target":76.79,"stop":72.66,"price":75.02,"trade_date":"2026-07-10"},"XLI":{"symbol":"XLI","support":180.99,"target":186.08,"stop":176.37,"price":181.92,"trade_date":"2026-07-10"},"SPY":{"symbol":"SPY","support":743.33,"target":767.73,"stop":737.92,"price":754.95,"trade_date":"2026-07-10"},"DIA":{"symbol":"DIA","support":520.1,"target":533.16,"stop":515.94,"price":525.78,"trade_date":"2026-07-10"},"SKYY":{"symbol":"SKYY","support":134.44,"target":145.1,"stop":132.66,"price":139.77,"trade_date":"2026-07-10"},"RSP":{"symbol":"RSP","support":211.77,"target":217.17,"stop":210.47,"price":214.3,"trade_date":"2026-07-10"},"XLY":{"symbol":"XLY","support":116.35,"target":120.34,"stop":113.1,"price":117.24,"trade_date":"2026-07-10"},"SOXX":{"symbol":"SOXX","support":599.8,"target":619.87,"stop":529.96,"price":581.34,"trade_date":"2026-07-10"},"XRT":{"symbol":"XRT","support":87.14,"target":90.25,"stop":85.18,"price":88.08,"trade_date":"2026-07-10"},"VXUS":{"symbol":"VXUS","support":85.31,"target":86.8,"stop":83.4,"price":85.34,"trade_date":"2026-07-10"},"IHI":{"symbol":"IHI","support":50.23,"target":52.85,"stop":49.33,"price":51.34,"trade_date":"2026-07-10"},"EFA":{"symbol":"EFA","support":103.7,"target":105.66,"stop":102.56,"price":104.33,"trade_date":"2026-07-10"},"INDA":{"symbol":"INDA","support":49.23,"target":49.73,"stop":48.72,"price":49.3,"trade_date":"2026-07-10"},"SCHD":{"symbol":"SCHD","support":32.08,"target":32.84,"stop":31.82,"price":32.4,"trade_date":"2026-07-10"},"XLU":{"symbol":"XLU","support":45.1,"target":46.32,"stop":44.19,"price":45.41,"trade_date":"2026-07-10"},"UUP":{"symbol":"UUP","support":28.3,"target":28.51,"stop":28.23,"price":28.39,"trade_date":"2026-07-10"},"SMH":{"symbol":"SMH","support":621.64,"target":644.65,"stop":566.21,"price":611.03,"trade_date":"2026-07-10"},"VNQ":{"symbol":"VNQ","support":97.0,"target":99.13,"stop":94.9,"price":97.32,"trade_date":"2026-07-10"},"IBIT":{"symbol":"IBIT","support":35.4,"target":37.66,"stop":34.32,"price":36.23,"trade_date":"2026-07-10"},"SGOV":{"symbol":"SGOV","support":100.48,"target":100.52,"stop":100.35,"price":100.5,"trade_date":"2026-07-10"},"SHY":{"symbol":"SHY","support":81.85,"target":81.96,"stop":81.78,"price":81.88,"trade_date":"2026-07-10"},"XLRE":{"symbol":"XLRE","support":44.43,"target":45.33,"stop":43.28,"price":44.45,"trade_date":"2026-07-10"},"XLP":{"symbol":"XLP","support":84.05,"target":85.72,"stop":81.98,"price":84.12,"trade_date":"2026-07-10"},"SPMO":{"symbol":"SPMO","support":154.96,"target":159.48,"stop":146.11,"price":153.75,"trade_date":"2026-07-10"},"IGV":{"symbol":"IGV","support":90.64,"target":96.18,"stop":87.39,"price":92.41,"trade_date":"2026-07-10"},"KWEB":{"symbol":"KWEB","support":25.68,"target":27.08,"stop":25.34,"price":26.38,"trade_date":"2026-07-10"},"IWM":{"symbol":"IWM","support":296.06,"target":302.57,"stop":287.22,"price":295.99,"trade_date":"2026-07-10"},"XLC":{"symbol":"XLC","support":109.24,"target":114.08,"stop":108.39,"price":111.64,"trade_date":"2026-07-10"},"EEM":{"symbol":"EEM","support":67.72,"target":68.63,"stop":64.6,"price":66.9,"trade_date":"2026-07-10"},"MCHI":{"symbol":"MCHI","support":52.39,"target":53.96,"stop":52.03,"price":53.13,"trade_date":"2026-07-10"},"XLE":{"symbol":"XLE","support":54.38,"target":56.39,"stop":53.33,"price":55.08,"trade_date":"2026-07-10"},"ITA":{"symbol":"ITA","support":239.89,"target":245.28,"stop":230.77,"price":239.06,"trade_date":"2026-07-10"},"XOP":{"symbol":"XOP","support":156.52,"target":163.22,"stop":152.37,"price":158.57,"trade_date":"2026-07-10"},"PAVE":{"symbol":"PAVE","support":57.85,"target":58.21,"stop":54.67,"price":56.69,"trade_date":"2026-07-10"},"XHB":{"symbol":"XHB","support":110.66,"target":112.4,"stop":103.56,"price":108.61,"trade_date":"2026-07-10"},"XSD":{"symbol":"XSD","support":591.35,"target":603.55,"stop":509.93,"price":563.43,"trade_date":"2026-07-10"},"DBC":{"symbol":"DBC","support":27.34,"target":27.9,"stop":27.01,"price":27.52,"trade_date":"2026-07-10"},"XLB":{"symbol":"XLB","support":51.38,"target":52.05,"stop":49.34,"price":50.89,"trade_date":"2026-07-10"},"ITB":{"symbol":"ITB","support":99.86,"target":101.43,"stop":92.87,"price":97.76,"trade_date":"2026-07-10"},"FBND":{"symbol":"FBND","support":45.42,"target":45.48,"stop":44.94,"price":45.25,"trade_date":"2026-07-10"},"IEF":{"symbol":"IEF","support":94.04,"target":93.97,"stop":93.18,"price":93.63,"trade_date":"2026-07-10"},"XAR":{"symbol":"XAR","support":279.63,"target":281.45,"stop":258.12,"price":271.45,"trade_date":"2026-07-10"},"QTUM":{"symbol":"QTUM","support":159.99,"target":161.43,"stop":145.17,"price":154.46,"trade_date":"2026-07-10"},"BOTZ":{"symbol":"BOTZ","support":37.25,"target":37.79,"stop":35.73,"price":36.91,"trade_date":"2026-07-10"},"DRIV":{"symbol":"DRIV","support":38.14,"target":37.99,"stop":34.6,"price":36.54,"trade_date":"2026-07-10"},"TLT":{"symbol":"TLT","support":85.76,"target":85.09,"stop":83.64,"price":84.47,"trade_date":"2026-07-10"},"GLD":{"symbol":"GLD","support":379.43,"target":384.3,"stop":367.29,"price":377.01,"trade_date":"2026-07-10"},"URA":{"symbol":"URA","support":44.62,"target":45.2,"stop":39.99,"price":42.97,"trade_date":"2026-07-10"},"OIH":{"symbol":"OIH","support":384.12,"target":392.28,"stop":364.19,"price":380.24,"trade_date":"2026-07-10"},"ICLN":{"symbol":"ICLN","support":20.24,"target":20.13,"stop":18.07,"price":19.25,"trade_date":"2026-07-10"},"COPX":{"symbol":"COPX","support":79.67,"target":79.48,"stop":72.62,"price":76.54,"trade_date":"2026-07-10"},"GDX":{"symbol":"GDX","support":78.37,"target":79.03,"stop":70.86,"price":75.53,"trade_date":"2026-07-10"},"TAN":{"symbol":"TAN","support":58.37,"target":57.82,"stop":51.14,"price":54.96,"trade_date":"2026-07-10"},"LIT":{"symbol":"LIT","support":78.19,"target":74.11,"stop":69.94,"price":72.32,"trade_date":"2026-07-10"},"SLV":{"symbol":"SLV","support":56.37,"target":56.25,"stop":50.89,"price":53.95,"trade_date":"2026-07-10"},"USO":{"symbol":"USO","support":111.45,"target":112.54,"stop":103.58,"price":108.7,"trade_date":"2026-07-10"},"XME":{"symbol":"XME","support":110.21,"target":108.22,"stop":97.65,"price":103.69,"trade_date":"2026-07-10"}},"market_regime":{"state":"偏强","equity_allocation":"60%-80%","benchmark":"SPY"},"summary":{"universe":74,"valid":74,"momentum_pass":27},"recommendations":[{"symbol":"HACK","name":"Amplify Cybersecurity ETF","asset_type":"主题","theme":"网络安全","trade_date":"2026-07-13","price":109.28,"day_open":108.91,"day_high":109.92,"day_low":107.64,"adjusted_close":109.28,"ret3":0.4,"ret5":-0.9,"ret20":13.1,"ret60":43.88,"relative_spy20":11.29,"relative_spy60":36.57,"ma20":102.15,"ma60":93.05,"volume_ratio":1.36,"close_position":0.721,"max_drawdown20":-2.67,"volatility20":1.69,"trend_score":99.6,"strength_level":"A","trading_risk_score":18.1,"risk_level":"低","trade_state":"可持有","momentum_pass":true,"risk_flags":[],"support":104.69,"target":113.87,"stop":102.15,"trigger_price_basis":"raw_ohlc","return_basis":"adjusted_close"},{"symbol":"XBI","name":"SPDR S&P Biotech ETF","asset_type":"主题","theme":"生物科技","trade_date":"2026-07-13","price":155.34,"day_open":157.23,"day_high":157.25,"day_low":153.9,"adjusted_close":155.34,"ret3":-4.68,"ret5":-3.4,"ret20":17.14,"ret60":13.96,"relative_spy20":15.33,"relative_spy60":6.65,"ma20":151.72,"ma60":139.13,"volume_ratio":0.98,"close_position":0.431,"max_drawdown20":-5.44,"volatility20":1.72,"trend_score":87.7,"strength_level":"A","trading_risk_score":20.0,"risk_level":"低","trade_state":"可持有","momentum_pass":true,"risk_flags":[],"support":151.72,"target":161.67,"stop":146.91,"trigger_price_basis":"raw_ohlc","return_basis":"adjusted_close"},{"symbol":"KIE","name":"SPDR S&P Insurance","asset_type":"行业","theme":"保险","trade_date":"2026-07-13","price":64.46,"day_open":63.93,"day_high":64.49,"day_low":63.81,"adjusted_close":64.46,"ret3":1.38,"ret5":0.96,"ret20":11.42,"ret60":12.76,"relative_spy20":9.61,"relative_spy60":5.45,"ma20":61.04,"ma60":58.15,"volume_ratio":1.05,"close_position":0.963,"max_drawdown20":-1.52,"volatility20":1.25,"trend_score":84.4,"strength_level":"A","trading_risk_score":15.9,"risk_level":"低","trade_state":"可持有","momentum_pass":true,"risk_flags":[],"support":63.01,"target":65.91,"stop":61.04,"trigger_price_basis":"raw_ohlc","return_basis":"adjusted_close"},{"symbol":"IHF","name":"iShares U.S. Healthcare Providers","asset_type":"行业","theme":"医疗服务","trade_date":"2026-07-13","price":57.49,"day_open":57.2,"day_high":57.86,"day_low":57.2,"adjusted_close":57.49,"ret3":0.91,"ret5":1.09,"ret20":8.55,"ret60":29.22,"relative_spy20":6.74,"relative_spy60":21.91,"ma20":55.16,"ma60":51.38,"volume_ratio":0.56,"close_position":0.439,"max_drawdown20":-2.33,"volatility20":1.14,"trend_score":82.2,"strength_level":"A","trading_risk_score":16.4,"risk_level":"低","trade_state":"可持有","momentum_pass":true,"risk_flags":["量能不足"],"support":56.3,"target":58.68,"stop":55.16,"trigger_price_basis":"raw_ohlc","return_basis":"adjusted_close"},{"symbol":"SKYY","name":"First Trust Cloud Computing","asset_type":"主题","theme":"云计算","trade_date":"2026-07-13","price":139.99,"day_open":140.12,"day_high":141.68,"day_low":138.46,"adjusted_close":139.99,"ret3":0.82,"ret5":1.77,"ret20":4.64,"ret60":23.13,"relative_spy20":2.83,"relative_spy60":15.82,"ma20":134.48,"ma60":131.42,"volume_ratio":0.85,"close_position":0.475,"max_drawdown20":-7.47,"volatility20":1.52,"trend_score":77.1,"strength_level":"A","trading_risk_score":19.6,"risk_level":"低","trade_state":"可持有","momentum_pass":true,"risk_flags":[],"support":134.92,"target":145.06,"stop":133.23,"trigger_price_basis":"raw_ohlc","return_basis":"adjusted_close"}],"flower_signals":{"ready_plant":[{"symbol":"IBB","name":"iShares Biotechnology ETF","theme":"生物科技","price":189.55,"support":185.18,"target":195.23,"stop":181.98,"strength_level":"A","trend_score":79.1,"risk_level":"低","trade_state":"可持有","ret20":11.2,"relative_spy20":9.39,"support_gap":2.36,"target_gap":3.0,"trade_date":"2026-07-13","signal":"候场","trigger_level":185.18,"trigger_basis":"距伏击位3%以内"},{"symbol":"FDN","name":"First Trust Dow Jones Internet","theme":"互联网","price":274.81,"support":267.74,"target":281.88,"stop":265.38,"strength_level":"B","trend_score":68.4,"risk_level":"低","trade_state":"可持有","ret20":3.67,"relative_spy20":1.86,"support_gap":2.64,"target_gap":2.57,"trade_date":"2026-07-13","signal":"候场","trigger_level":267.74,"trigger_basis":"距伏击位3%以内"}],"plant":[],"ready_harvest":[{"symbol":"UUP","name":"Invesco DB US Dollar Bullish","theme":"美元","price":28.5,"support":28.38,"target":28.62,"stop":28.33,"strength_level":"B","trend_score":63.5,"risk_level":"低","trade_state":"可持有","ret20":1.97,"relative_spy20":0.16,"support_gap":0.42,"target_gap":0.42,"trade_date":"2026-07-13","signal":"止盈观察","trigger_level":28.62,"trigger_basis":"距兑现位3%以内或20日过热"},{"symbol":"SCHD","name":"Schwab U.S. Dividend Equity ETF","theme":"红利价值","price":32.56,"support":32.12,"target":33.0,"stop":31.97,"strength_level":"B","trend_score":63.7,"risk_level":"低","trade_state":"可持有","ret20":0.89,"relative_spy20":-0.92,"support_gap":1.37,"target_gap":1.35,"trade_date":"2026-07-13","signal":"止盈观察","trigger_level":33.0,"trigger_basis":"距兑现位3%以内或20日过热"},{"symbol":"RSP","name":"Invesco S&P 500 Equal Weight","theme":"美国宽基","price":214.23,"support":212.03,"target":217.15,"stop":210.33,"strength_level":"B","trend_score":64.2,"risk_level":"低","trade_state":"可持有","ret20":2.53,"relative_spy20":0.72,"support_gap":1.04,"target_gap":1.36,"trade_date":"2026-07-13","signal":"止盈观察","trigger_level":217.15,"trigger_basis":"距兑现位3%以内或20日过热"},{"symbol":"VNQ","name":"Vanguard Real Estate ETF","theme":"房地产","price":97.83,"support":97.05,"target":99.58,"stop":95.5,"strength_level":"B","trend_score":63.4,"risk_level":"低","trade_state":"可持有","ret20":1.11,"relative_spy20":-0.7,"support_gap":0.8,"target_gap":1.79,"trade_date":"2026-07-13","signal":"止盈观察","trigger_level":99.58,"trigger_basis":"距兑现位3%以内或20日过热"},{"symbol":"XLF","name":"Financial Select Sector","theme":"金融","price":56.07,"support":55.02,"target":57.12,"stop":54.42,"strength_level":"B","trend_score":71.3,"risk_level":"低","trade_state":"可持有","ret20":6.93,"relative_spy20":5.12,"support_gap":1.91,"target_gap":1.87,"trade_date":"2026-07-13","signal":"止盈观察","trigger_level":57.12,"trigger_basis":"距兑现位3%以内或20日过热"},{"symbol":"XLP","name":"Consumer Staples","theme":"防御","price":84.59,"support":84.05,"target":86.21,"stop":82.43,"strength_level":"C","trend_score":60.9,"risk_level":"低","trade_state":"观察","ret20":-0.11,"relative_spy20":-1.92,"support_gap":0.64,"target_gap":1.92,"trade_date":"2026-07-13","signal":"止盈观察","trigger_level":86.21,"trigger_basis":"距兑现位3%以内或20日过热"},{"symbol":"IHF","name":"iShares U.S. Healthcare Providers","theme":"医疗服务","price":57.49,"support":56.3,"target":58.68,"stop":55.16,"strength_level":"A","trend_score":82.2,"risk_level":"低","trade_state":"可持有","ret20":8.55,"relative_spy20":6.74,"support_gap":2.11,"target_gap":2.07,"trade_date":"2026-07-13","signal":"止盈观察","trigger_level":58.68,"trigger_basis":"距兑现位3%以内或20日过热"},{"symbol":"IYT","name":"iShares Transportation Average","theme":"运输","price":88.04,"support":86.46,"target":90.0,"stop":85.43,"strength_level":"B","trend_score":67.4,"risk_level":"低","trade_state":"可持有","ret20":2.41,"relative_spy20":0.6,"support_gap":1.83,"target_gap":2.23,"trade_date":"2026-07-13","signal":"止盈观察","trigger_level":90.0,"trigger_basis":"距兑现位3%以内或20日过热"}],"harvest":[{"symbol":"XOP","name":"SPDR S&P Oil & Gas Exploration & Production","theme":"油气勘探","price":165.19,"support":160.38,"target":170.0,"stop":156.65,"strength_level":"C","trend_score":60.9,"risk_level":"低","trade_state":"观察","ret20":1.58,"relative_spy20":-0.23,"support_gap":3.0,"target_gap":2.91,"trade_date":"2026-07-13","signal":"兑现触发","trigger_level":163.22,"trigger_basis":"当日最高价≥前一快照兑现位"},{"symbol":"XLE","name":"Energy Select Sector","theme":"能源","price":56.74,"support":55.41,"target":58.07,"stop":54.38,"strength_level":"C","trend_score":56.4,"risk_level":"低","trade_state":"观察","ret20":0.05,"relative_spy20":-1.76,"support_gap":2.4,"target_gap":2.34,"trade_date":"2026-07-13","signal":"兑现触发","trigger_level":56.39,"trigger_basis":"当日最高价≥前一快照兑现位"},{"symbol":"USO","name":"United States Oil Fund","theme":"原油","price":117.79,"support":113.34,"target":122.24,"stop":110.9,"strength_level":"C","trend_score":52.8,"risk_level":"中","trade_state":"观察","ret20":-8.57,"relative_spy20":-10.38,"support_gap":3.93,"target_gap":3.78,"trade_date":"2026-07-13","signal":"兑现触发","trigger_level":112.54,"trigger_basis":"当日最高价≥前一快照兑现位"}],"exit":[{"symbol":"INDA","name":"iShares MSCI India","theme":"印度","price":48.79,"support":49.28,"target":49.23,"stop":48.2,"strength_level":"D","trend_score":36.6,"risk_level":"低","trade_state":"退出","ret20":2.09,"relative_spy20":0.28,"support_gap":-0.99,"target_gap":0.9,"trade_date":"2026-07-13","signal":"破位撤退","trigger_level":48.72,"trigger_basis":"当日最低价≤前一快照防守线"},{"symbol":"EEM","name":"iShares MSCI Emerging Markets","theme":"新兴市场","price":64.5,"support":67.59,"target":66.26,"stop":62.15,"strength_level":"D","trend_score":24.9,"risk_level":"中","trade_state":"退出","ret20":-3.95,"relative_spy20":-5.76,"support_gap":-4.57,"target_gap":2.73,"trade_date":"2026-07-13","signal":"破位撤退","trigger_level":64.6,"trigger_basis":"当日最低价≤前一快照防守线"},{"symbol":"GLD","name":"SPDR Gold Shares","theme":"黄金","price":367.13,"support":378.47,"target":374.78,"stop":356.93,"strength_level":"D","trend_score":3.9,"risk_level":"低","trade_state":"退出","ret20":-4.97,"relative_spy20":-6.78,"support_gap":-3.0,"target_gap":2.08,"trade_date":"2026-07-13","signal":"破位撤退","trigger_level":367.29,"trigger_basis":"当日最低价≤前一快照防守线"}]},"flower_counts":{"ready_plant":2,"plant":0,"ready_harvest":8,"harvest":3,"exit":3},"breadth_groups":[{"group":"网络安全","members":["CIBR","HACK"],"passed":2,"total":2,"ratio":100.0,"avg_relative_spy20":8.52,"state":"全面扩散"},{"group":"医疗","members":["XLV","IHI","IHF","XBI","IBB"],"passed":5,"total":5,"ratio":100.0,"avg_relative_spy20":7.31,"state":"全面扩散"},{"group":"金融","members":["XLF","KRE","KIE"],"passed":3,"total":3,"ratio":100.0,"avg_relative_spy20":5.79,"state":"全面扩散"},{"group":"房地产","members":["XLRE","VNQ"],"passed":2,"total":2,"ratio":100.0,"avg_relative_spy20":-1.06,"state":"同步通过·相对偏弱"},{"group":"加密资产","members":["IBIT","ETHA"],"passed":1,"total":2,"ratio":50.0,"avg_relative_spy20":-0.32,"state":"局部走强"},{"group":"红利与动量因子","members":["SCHD","SPMO"],"passed":1,"total":2,"ratio":50.0,"avg_relative_spy20":-1.57,"state":"局部走强"},{"group":"科技","members":["XLK","QQQ","IGV","FDN","SKYY"],"passed":2,"total":5,"ratio":40.0,"avg_relative_spy20":-0.07,"state":"局部走强"},{"group":"房屋建筑","members":["ITB","XHB"],"passed":0,"total":2,"ratio":0.0,"avg_relative_spy20":-2.75,"state":"整体偏弱"},{"group":"能源","members":["XLE","XOP","OIH"],"passed":0,"total":3,"ratio":0.0,"avg_relative_spy20":-4.63,"state":"整体偏弱"},{"group":"国防","members":["ITA","XAR"],"passed":0,"total":2,"ratio":0.0,"avg_relative_spy20":-5.53,"state":"整体偏弱"},{"group":"量子计算","members":["QTUM"],"passed":0,"total":1,"ratio":0.0,"avg_relative_spy20":-8.14,"state":"整体偏弱"},{"group":"半导体","members":["SMH","SOXX","XSD"],"passed":0,"total":3,"ratio":0.0,"avg_relative_spy20":-8.34,"state":"整体偏弱"},{"group":"材料矿业","members":["XLB","XME","GDX","COPX"],"passed":0,"total":4,"ratio":0.0,"avg_relative_spy20":-9.42,"state":"整体偏弱"},{"group":"新能源","members":["TAN","ICLN","LIT"],"passed":0,"total":3,"ratio":0.0,"avg_relative_spy20":-14.25,"state":"整体偏弱"}],"rows":[{"symbol":"HACK","name":"Amplify Cybersecurity ETF","asset_type":"主题","theme":"网络安全","trade_date":"2026-07-13","price":109.28,"day_open":108.91,"day_high":109.92,"day_low":107.64,"adjusted_close":109.28,"ret3":0.4,"ret5":-0.9,"ret20":13.1,"ret60":43.88,"relative_spy20":11.29,"relative_spy60":36.57,"ma20":102.15,"ma60":93.05,"volume_ratio":1.36,"close_position":0.721,"max_drawdown20":-2.67,"volatility20":1.69,"trend_score":99.6,"strength_level":"A","trading_risk_score":18.1,"risk_level":"低","trade_state":"可持有","momentum_pass":true,"risk_flags":[],"support":104.69,"target":113.87,"stop":102.15,"trigger_price_basis":"raw_ohlc","return_basis":"adjusted_close"},{"symbol":"XBI","name":"SPDR S&P Biotech ETF","asset_type":"主题","theme":"生物科技","trade_date":"2026-07-13","price":155.34,"day_open":157.23,"day_high":157.25,"day_low":153.9,"adjusted_close":155.34,"ret3":-4.68,"ret5":-3.4,"ret20":17.14,"ret60":13.96,"relative_spy20":15.33,"relative_spy60":6.65,"ma20":151.72,"ma60":139.13,"volume_ratio":0.98,"close_position":0.431,"max_drawdown20":-5.44,"volatility20":1.72,"trend_score":87.7,"strength_level":"A","trading_risk_score":20.0,"risk_level":"低","trade_state":"可持有","momentum_pass":true,"risk_flags":[],"support":151.72,"target":161.67,"stop":146.91,"trigger_price_basis":"raw_ohlc","return_basis":"adjusted_close"},{"symbol":"CIBR","name":"First Trust Nasdaq Cybersecurity","asset_type":"主题","theme":"网络安全","trade_date":"2026-07-13","price":91.84,"day_open":91.84,"day_high":92.68,"day_low":90.54,"adjusted_close":91.84,"ret3":0.2,"ret5":-1.15,"ret20":7.55,"ret60":42.47,"relative_spy20":5.74,"relative_spy60":35.16,"ma20":88.02,"ma60":80.91,"volume_ratio":1.14,"close_position":0.607,"max_drawdown20":-3.12,"volatility20":1.54,"trend_score":87.6,"strength_level":"A","trading_risk_score":17.2,"risk_level":"低","trade_state":"可持有","momentum_pass":true,"risk_flags":[],"support":88.1,"target":95.58,"stop":86.86,"trigger_price_basis":"raw_ohlc","return_basis":"adjusted_close"},{"symbol":"KIE","name":"SPDR S&P Insurance","asset_type":"行业","theme":"保险","trade_date":"2026-07-13","price":64.46,"day_open":63.93,"day_high":64.49,"day_low":63.81,"adjusted_close":64.46,"ret3":1.38,"ret5":0.96,"ret20":11.42,"ret60":12.76,"relative_spy20":9.61,"relative_spy60":5.45,"ma20":61.04,"ma60":58.15,"volume_ratio":1.05,"close_position":0.963,"max_drawdown20":-1.52,"volatility20":1.25,"trend_score":84.4,"strength_level":"A","trading_risk_score":15.9,"risk_level":"低","trade_state":"可持有","momentum_pass":true,"risk_flags":[],"support":63.01,"target":65.91,"stop":61.04,"trigger_price_basis":"raw_ohlc","return_basis":"adjusted_close"},{"symbol":"IHF","name":"iShares U.S. Healthcare Providers","asset_type":"行业","theme":"医疗服务","trade_date":"2026-07-13","price":57.49,"day_open":57.2,"day_high":57.86,"day_low":57.2,"adjusted_close":57.49,"ret3":0.91,"ret5":1.09,"ret20":8.55,"ret60":29.22,"relative_spy20":6.74,"relative_spy60":21.91,"ma20":55.16,"ma60":51.38,"volume_ratio":0.56,"close_position":0.439,"max_drawdown20":-2.33,"volatility20":1.14,"trend_score":82.2,"strength_level":"A","trading_risk_score":16.4,"risk_level":"低","trade_state":"可持有","momentum_pass":true,"risk_flags":["量能不足"],"support":56.3,"target":58.68,"stop":55.16,"trigger_price_basis":"raw_ohlc","return_basis":"adjusted_close"},{"symbol":"IBB","name":"iShares Biotechnology ETF","asset_type":"主题","theme":"生物科技","trade_date":"2026-07-13","price":189.55,"day_open":191.17,"day_high":191.17,"day_low":187.91,"adjusted_close":189.55,"ret3":-3.46,"ret5":-2.95,"ret20":11.2,"ret60":7.72,"relative_spy20":9.39,"relative_spy60":0.41,"ma20":185.18,"ma60":174.93,"volume_ratio":1.2,"close_position":0.503,"max_drawdown20":-4.38,"volatility20":1.27,"trend_score":79.1,"strength_level":"A","trading_risk_score":17.6,"risk_level":"低","trade_state":"可持有","momentum_pass":true,"risk_flags":[],"support":185.18,"target":195.23,"stop":181.98,"trigger_price_basis":"raw_ohlc","return_basis":"adjusted_close"},{"symbol":"SKYY","name":"First Trust Cloud Computing","asset_type":"主题","theme":"云计算","trade_date":"2026-07-13","price":139.99,"day_open":140.12,"day_high":141.68,"day_low":138.46,"adjusted_close":139.99,"ret3":0.82,"ret5":1.77,"ret20":4.64,"ret60":23.13,"relative_spy20":2.83,"relative_spy60":15.82,"ma20":134.48,"ma60":131.42,"volume_ratio":0.85,"close_position":0.475,"max_drawdown20":-7.47,"volatility20":1.52,"trend_score":77.1,"strength_level":"A","trading_risk_score":19.6,"risk_level":"低","trade_state":"可持有","momentum_pass":true,"risk_flags":[],"support":134.92,"target":145.06,"stop":133.23,"trigger_price_basis":"raw_ohlc","return_basis":"adjusted_close"},{"symbol":"XLF","name":"Financial Select Sector","asset_type":"行业","theme":"金融","trade_date":"2026-07-13","price":56.07,"day_open":55.98,"day_high":56.16,"day_low":55.6,"adjusted_close":56.07,"ret3":2.0,"ret5":-0.12,"ret20":6.93,"ret60":7.85,"relative_spy20":5.12,"relative_spy60":0.54,"ma20":54.42,"ma60":52.52,"volume_ratio":0.87,"close_position":0.838,"max_drawdown20":-2.08,"volatility20":0.93,"trend_score":71.3,"strength_level":"B","trading_risk_score":16.3,"risk_level":"低","trade_state":"可持有","momentum_pass":true,"risk_flags":[],"support":55.02,"target":57.12,"stop":54.42,"trigger_price_basis":"raw_ohlc","return_basis":"adjusted_close"},{"symbol":"XLV","name":"Health Care Select Sector","asset_type":"行业","theme":"医疗","trade_date":"2026-07-13","price":161.41,"day_open":160.97,"day_high":162.24,"day_low":160.33,"adjusted_close":161.41,"ret3":-0.55,"ret5":-0.34,"ret20":5.21,"ret60":9.71,"relative_spy20":3.4,"relative_spy60":2.4,"ma20":157.19,"ma60":150.21,"volume_ratio":0.86,"close_position":0.565,"max_drawdown20":-2.87,"volatility20":1.26,"trend_score":71.2,"strength_level":"B","trading_risk_score":16.7,"risk_level":"低","trade_state":"可持有","momentum_pass":true,"risk_flags":[],"support":157.75,"target":165.07,"stop":156.52,"trigger_price_basis":"raw_ohlc","return_basis":"adjusted_close"},{"symbol":"FDN","name":"First Trust Dow Jones Internet","asset_type":"主题","theme":"互联网","trade_date":"2026-07-13","price":274.81,"day_open":275.62,"day_high":277.9,"day_low":273.94,"adjusted_close":274.81,"ret3":1.43,"ret5":1.61,"ret20":3.67,"ret60":6.2,"relative_spy20":1.86,"relative_spy60":-1.11,"ma20":266.54,"ma60":268.18,"volume_ratio":0.8,"close_position":0.219,"max_drawdown20":-5.87,"volatility20":1.4,"trend_score":68.4,"strength_level":"B","trading_risk_score":28.5,"risk_level":"低","trade_state":"可持有","momentum_pass":true,"risk_flags":["收盘偏弱"],"support":267.74,"target":281.88,"stop":265.38,"trigger_price_basis":"raw_ohlc","return_basis":"adjusted_close"},{"symbol":"KRE","name":"SPDR S&P Regional Banking","asset_type":"行业","theme":"区域银行","trade_date":"2026-07-13","price":75.12,"day_open":75.06,"day_high":75.35,"day_low":74.54,"adjusted_close":75.12,"ret3":2.43,"ret5":-0.58,"ret20":4.44,"ret60":9.24,"relative_spy20":2.63,"relative_spy60":1.93,"ma20":73.87,"ma60":70.66,"volume_ratio":0.84,"close_position":0.719,"max_drawdown20":-3.73,"volatility20":1.22,"trend_score":67.8,"strength_level":"B","trading_risk_score":17.2,"risk_level":"低","trade_state":"可持有","momentum_pass":true,"risk_flags":[],"support":73.87,"target":76.88,"stop":72.78,"trigger_price_basis":"raw_ohlc","return_basis":"adjusted_close"},{"symbol":"IYT","name":"iShares Transportation Average","asset_type":"行业","theme":"运输","trade_date":"2026-07-13","price":88.04,"day_open":88.13,"day_high":88.78,"day_low":88.0,"adjusted_close":88.04,"ret3":1.67,"ret5":0.73,"ret20":2.41,"ret60":11.64,"relative_spy20":0.6,"relative_spy60":4.33,"ma20":86.46,"ma60":83.29,"volume_ratio":0.81,"close_position":0.051,"max_drawdown20":-3.69,"volatility20":1.11,"trend_score":67.4,"strength_level":"B","trading_risk_score":27.2,"risk_level":"低","trade_state":"可持有","momentum_pass":true,"risk_flags":["收盘偏弱"],"support":86.46,"target":90.0,"stop":85.43,"trigger_price_basis":"raw_ohlc","return_basis":"adjusted_close"},{"symbol":"XLU","name":"Utilities Select Sector","asset_type":"行业","theme":"防御","trade_date":"2026-07-13","price":45.72,"day_open":45.45,"day_high":45.88,"day_low":45.43,"adjusted_close":45.72,"ret3":0.79,"ret5":0.93,"ret20":4.45,"ret60":-0.02,"relative_spy20":2.64,"relative_spy60":-7.33,"ma20":45.2,"ma60":44.9,"volume_ratio":0.82,"close_position":0.648,"max_drawdown20":-3.1,"volatility20":0.96,"trend_score":65.7,"strength_level":"B","trading_risk_score":16.9,"risk_level":"低","trade_state":"可持有","momentum_pass":true,"risk_flags":[],"support":45.2,"target":46.63,"stop":44.51,"trigger_price_basis":"raw_ohlc","return_basis":"adjusted_close"},{"symbol":"VTI","name":"Vanguard Total Stock Market","asset_type":"宽基","theme":"美国宽基","trade_date":"2026-07-13","price":369.78,"day_open":371.59,"day_high":372.22,"day_low":369.25,"adjusted_close":369.78,"ret3":0.42,"ret5":-0.51,"ret20":1.8,"ret60":7.42,"relative_spy20":-0.01,"relative_spy60":0.11,"ma20":367.83,"ma60":362.52,"volume_ratio":1.05,"close_position":0.178,"max_drawdown20":-2.49,"volatility20":0.82,"trend_score":64.2,"strength_level":"B","trading_risk_score":26.5,"risk_level":"低","trade_state":"可持有","momentum_pass":true,"risk_flags":["收盘偏弱"],"support":367.83,"target":375.57,"stop":362.06,"trigger_price_basis":"raw_ohlc","return_basis":"adjusted_close"},{"symbol":"RSP","name":"Invesco S&P 500 Equal Weight","asset_type":"宽基","theme":"美国宽基","trade_date":"2026-07-13","price":214.23,"day_open":214.48,"day_high":215.5,"day_low":213.8,"adjusted_close":214.23,"ret3":0.96,"ret5":-0.36,"ret20":2.53,"ret60":7.68,"relative_spy20":0.72,"relative_spy60":0.37,"ma20":212.03,"ma60":206.68,"volume_ratio":0.84,"close_position":0.253,"max_drawdown20":-1.83,"volatility20":0.68,"trend_score":64.2,"strength_level":"B","trading_risk_score":26.1,"risk_level":"低","trade_state":"可持有","momentum_pass":true,"risk_flags":["收盘偏弱"],"support":212.03,"target":217.15,"stop":210.33,"trigger_price_basis":"raw_ohlc","return_basis":"adjusted_close"},{"symbol":"SCHD","name":"Schwab U.S. Dividend Equity ETF","asset_type":"因子","theme":"红利价值","trade_date":"2026-07-13","price":32.56,"day_open":32.58,"day_high":32.72,"day_low":32.47,"adjusted_close":32.56,"ret3":0.68,"ret5":0.99,"ret20":0.89,"ret60":7.08,"relative_spy20":-0.92,"relative_spy60":-0.23,"ma20":32.09,"ma60":31.78,"volume_ratio":0.86,"close_position":0.36,"max_drawdown20":-2.93,"volatility20":0.75,"trend_score":63.7,"strength_level":"B","trading_risk_score":16.8,"risk_level":"低","trade_state":"可持有","momentum_pass":true,"risk_flags":[],"support":32.12,"target":33.0,"stop":31.97,"trigger_price_basis":"raw_ohlc","return_basis":"adjusted_close"},{"symbol":"DIA","name":"SPDR Dow Jones ETF","asset_type":"宽基","theme":"美国宽基","trade_date":"2026-07-13","price":524.47,"day_open":525.84,"day_high":527.86,"day_low":522.9,"adjusted_close":524.47,"ret3":0.33,"ret5":-1.06,"ret20":3.25,"ret60":8.6,"relative_spy20":1.44,"relative_spy60":1.29,"ma20":520.92,"ma60":505.79,"volume_ratio":0.73,"close_position":0.317,"max_drawdown20":-1.38,"volatility20":0.55,"trend_score":63.5,"strength_level":"B","trading_risk_score":15.8,"risk_level":"低","trade_state":"可持有","momentum_pass":true,"risk_flags":["量能不足"],"support":520.92,"target":532.07,"stop":514.34,"trigger_price_basis":"raw_ohlc","return_basis":"adjusted_close"},{"symbol":"UUP","name":"Invesco DB US Dollar Bullish","asset_type":"宏观","theme":"美元","trade_date":"2026-07-13","price":28.5,"day_open":28.38,"day_high":28.5,"day_low":28.37,"adjusted_close":28.5,"ret3":0.49,"ret5":0.64,"ret20":1.97,"ret60":4.43,"relative_spy20":0.16,"relative_spy60":-2.88,"ma20":28.33,"ma60":27.86,"volume_ratio":0.85,"close_position":1.0,"max_drawdown20":-0.74,"volatility20":0.3,"trend_score":63.5,"strength_level":"B","trading_risk_score":15.4,"risk_level":"低","trade_state":"可持有","momentum_pass":true,"risk_flags":[],"support":28.38,"target":28.62,"stop":28.33,"trigger_price_basis":"raw_ohlc","return_basis":"adjusted_close"},{"symbol":"VNQ","name":"Vanguard Real Estate ETF","asset_type":"行业","theme":"房地产","trade_date":"2026-07-13","price":97.83,"day_open":97.63,"day_high":98.37,"day_low":97.45,"adjusted_close":97.83,"ret3":1.06,"ret5":0.61,"ret20":1.11,"ret60":4.67,"relative_spy20":-0.7,"relative_spy60":-2.64,"ma20":97.05,"ma60":95.76,"volume_ratio":0.96,"close_position":0.413,"max_drawdown20":-2.99,"volatility20":1.07,"trend_score":63.4,"strength_level":"B","trading_risk_score":16.8,"risk_level":"低","trade_state":"可持有","momentum_pass":true,"risk_flags":[],"support":97.05,"target":99.58,"stop":95.5,"trigger_price_basis":"raw_ohlc","return_basis":"adjusted_close"},{"symbol":"SPY","name":"SPDR S&P 500 ETF","asset_type":"宽基","theme":"美国宽基","trade_date":"2026-07-13","price":749.17,"day_open":752.47,"day_high":753.91,"day_low":748.03,"adjusted_close":749.17,"ret3":0.51,"ret5":-0.28,"ret20":1.81,"ret60":7.31,"relative_spy20":0.0,"relative_spy60":0.0,"ma20":744.0,"ma60":735.22,"volume_ratio":0.76,"close_position":0.194,"max_drawdown20":-3.17,"volatility20":0.86,"trend_score":62.2,"strength_level":"B","trading_risk_score":26.9,"risk_level":"低","trade_state":"可持有","momentum_pass":true,"risk_flags":["收盘偏弱"],"support":744.0,"target":761.82,"stop":732.3,"trigger_price_basis":"raw_ohlc","return_basis":"adjusted_close"},{"symbol":"IHI","name":"iShares U.S. Medical Devices","asset_type":"行业","theme":"医疗器械","trade_date":"2026-07-13","price":51.34,"day_open":51.31,"day_high":51.79,"day_low":51.13,"adjusted_close":51.34,"ret3":0.16,"ret5":-1.48,"ret20":3.52,"ret60":-5.2,"relative_spy20":1.71,"relative_spy60":-12.51,"ma20":50.32,"ma60":50.31,"volume_ratio":1.02,"close_position":0.318,"max_drawdown20":-3.17,"volatility20":1.53,"trend_score":62.1,"strength_level":"B","trading_risk_score":17.2,"risk_level":"低","trade_state":"可持有","momentum_pass":true,"risk_flags":[],"support":50.32,"target":52.84,"stop":49.34,"trigger_price_basis":"raw_ohlc","return_basis":"adjusted_close"},{"symbol":"XLP","name":"Consumer Staples","asset_type":"行业","theme":"防御","trade_date":"2026-07-13","price":84.59,"day_open":84.55,"day_high":85.54,"day_low":84.38,"adjusted_close":84.59,"ret3":0.24,"ret5":0.58,"ret20":-0.11,"ret60":5.08,"relative_spy20":-1.92,"relative_spy60":-2.23,"ma20":84.05,"ma60":83.43,"volume_ratio":0.88,"close_position":0.185,"max_drawdown20":-3.58,"volatility20":1.1,"trend_score":60.9,"strength_level":"C","trading_risk_score":27.1,"risk_level":"低","trade_state":"观察","momentum_pass":true,"risk_flags":["收盘偏弱"],"support":84.05,"target":86.21,"stop":82.43,"trigger_price_basis":"raw_ohlc","return_basis":"adjusted_close"},{"symbol":"XOP","name":"SPDR S&P Oil & Gas Exploration & Production","asset_type":"行业","theme":"油气勘探","trade_date":"2026-07-13","price":165.19,"day_open":161.65,"day_high":166.09,"day_low":161.49,"adjusted_close":165.19,"ret3":1.98,"ret5":7.29,"ret20":1.58,"ret60":1.06,"relative_spy20":-0.23,"relative_spy60":-6.25,"ma20":156.65,"ma60":164.74,"volume_ratio":1.2,"close_position":0.804,"max_drawdown20":-7.25,"volatility20":1.78,"trend_score":60.9,"strength_level":"C","trading_risk_score":21.5,"risk_level":"低","trade_state":"观察","momentum_pass":false,"risk_flags":["趋势未通过"],"support":160.38,"target":170.0,"stop":156.65,"trigger_price_basis":"raw_ohlc","return_basis":"adjusted_close"},{"symbol":"EWZ","name":"iShares MSCI Brazil","asset_type":"海外","theme":"巴西","trade_date":"2026-07-13","price":35.39,"day_open":35.82,"day_high":35.91,"day_low":35.38,"adjusted_close":35.39,"ret3":2.85,"ret5":1.35,"ret20":2.63,"ret60":-13.83,"relative_spy20":0.82,"relative_spy60":-21.14,"ma20":34.53,"ma60":36.35,"volume_ratio":0.96,"close_position":0.019,"max_drawdown20":-2.99,"volatility20":1.15,"trend_score":60.4,"strength_level":"C","trading_risk_score":26.8,"risk_level":"低","trade_state":"观察","momentum_pass":true,"risk_flags":["收盘偏弱"],"support":34.55,"target":36.23,"stop":34.28,"trigger_price_basis":"raw_ohlc","return_basis":"adjusted_close"},{"symbol":"XLRE","name":"Real Estate Select Sector","asset_type":"行业","theme":"房地产","trade_date":"2026-07-13","price":44.7,"day_open":44.61,"day_high":44.96,"day_low":44.5,"adjusted_close":44.7,"ret3":1.25,"ret5":0.93,"ret20":0.38,"ret60":3.87,"relative_spy20":-1.43,"relative_spy60":-3.44,"ma20":44.44,"ma60":44.01,"volume_ratio":0.71,"close_position":0.44,"max_drawdown20":-3.31,"volatility20":1.13,"trend_score":60.3,"strength_level":"C","trading_risk_score":17.0,"risk_level":"低","trade_state":"观察","momentum_pass":true,"risk_flags":["量能不足"],"support":44.44,"target":45.55,"stop":43.57,"trigger_price_basis":"raw_ohlc","return_basis":"adjusted_close"},{"symbol":"XRT","name":"SPDR S&P Retail ETF","asset_type":"行业","theme":"零售","trade_date":"2026-07-13","price":87.47,"day_open":88.21,"day_high":89.47,"day_low":87.36,"adjusted_close":87.47,"ret3":1.71,"ret5":-0.17,"ret20":-0.01,"ret60":4.5,"relative_spy20":-1.82,"relative_spy60":-2.81,"ma20":87.14,"ma60":84.8,"volume_ratio":0.72,"close_position":0.05,"max_drawdown20":-3.62,"volatility20":1.25,"trend_score":58.9,"strength_level":"C","trading_risk_score":27.2,"risk_level":"低","trade_state":"观察","momentum_pass":true,"risk_flags":["收盘偏弱","量能不足"],"support":87.14,"target":89.7,"stop":84.5,"trigger_price_basis":"raw_ohlc","return_basis":"adjusted_close"},{"symbol":"SGOV","name":"iShares 0-3 Month Treasury Bond","asset_type":"现金","theme":"现金替代","trade_date":"2026-07-13","price":100.52,"day_open":100.51,"day_high":100.52,"day_low":100.51,"adjusted_close":100.52,"ret3":0.05,"ret5":0.08,"ret20":0.32,"ret60":0.88,"relative_spy20":-1.49,"relative_spy60":-6.43,"ma20":100.37,"ma60":100.07,"volume_ratio":0.83,"close_position":1.0,"max_drawdown20":0.0,"volatility20":0.01,"trend_score":58.8,"strength_level":"C","trading_risk_score":15.0,"risk_level":"低","trade_state":"观察","momentum_pass":true,"risk_flags":[],"support":100.5,"target":100.53,"stop":100.37,"trigger_price_basis":"raw_ohlc","return_basis":"adjusted_close"},{"symbol":"XLE","name":"Energy Select Sector","asset_type":"行业","theme":"能源","trade_date":"2026-07-13","price":56.74,"day_open":55.86,"day_high":56.97,"day_low":55.86,"adjusted_close":56.74,"ret3":2.05,"ret5":6.79,"ret20":0.05,"ret60":2.49,"relative_spy20":-1.76,"relative_spy60":-4.82,"ma20":54.38,"ma60":56.39,"volume_ratio":1.01,"close_position":0.796,"max_drawdown20":-7.57,"volatility20":1.54,"trend_score":56.4,"strength_level":"C","trading_risk_score":19.9,"risk_level":"低","trade_state":"观察","momentum_pass":false,"risk_flags":["趋势未通过"],"support":55.41,"target":58.07,"stop":54.38,"trigger_price_basis":"raw_ohlc","return_basis":"adjusted_close"},{"symbol":"ETHA","name":"iShares Ethereum Trust ETF","asset_type":"加密资产","theme":"以太坊","trade_date":"2026-07-13","price":13.37,"day_open":13.35,"day_high":13.47,"day_low":13.2,"adjusted_close":13.37,"ret3":1.98,"ret5":-1.33,"ret20":5.28,"ret60":-25.6,"relative_spy20":3.47,"relative_spy60":-32.91,"ma20":12.82,"ma60":15.01,"volume_ratio":0.75,"close_position":0.63,"max_drawdown20":-14.68,"volatility20":3.54,"trend_score":53.7,"strength_level":"C","trading_risk_score":40.1,"risk_level":"中","trade_state":"回踩候选","momentum_pass":true,"risk_flags":["回撤偏大"],"support":12.82,"target":14.01,"stop":12.51,"trigger_price_basis":"raw_ohlc","return_basis":"adjusted_close"},{"symbol":"USO","name":"United States Oil Fund","asset_type":"商品","theme":"原油","trade_date":"2026-07-13","price":117.79,"day_open":111.89,"day_high":119.04,"day_low":111.71,"adjusted_close":117.79,"ret3":4.97,"ret5":12.88,"ret20":-8.57,"ret60":-3.92,"relative_spy20":-10.38,"relative_spy60":-11.23,"ma20":110.9,"ma60":128.37,"volume_ratio":1.46,"close_position":0.829,"max_drawdown20":-17.67,"volatility20":3.19,"trend_score":52.8,"strength_level":"C","trading_risk_score":51.8,"risk_level":"中","trade_state":"观察","momentum_pass":false,"risk_flags":["回撤偏大","趋势未通过"],"support":113.34,"target":122.24,"stop":110.9,"trigger_price_basis":"raw_ohlc","return_basis":"adjusted_close"},{"symbol":"DBC","name":"Invesco DB Commodity Index","asset_type":"商品","theme":"综合商品","trade_date":"2026-07-13","price":28.33,"day_open":27.85,"day_high":28.39,"day_low":27.79,"adjusted_close":28.33,"ret3":1.91,"ret5":4.93,"ret20":-1.8,"ret60":-1.94,"relative_spy20":-3.61,"relative_spy60":-9.25,"ma20":27.32,"ma60":29.23,"volume_ratio":0.85,"close_position":0.901,"max_drawdown20":-7.36,"volatility20":1.31,"trend_score":47.9,"strength_level":"D","trading_risk_score":19.4,"risk_level":"低","trade_state":"退出","momentum_pass":false,"risk_flags":["趋势未通过"],"support":27.91,"target":28.75,"stop":27.32,"trigger_price_basis":"raw_ohlc","return_basis":"adjusted_close"},{"symbol":"IGV","name":"iShares Expanded Tech-Software","asset_type":"主题","theme":"软件","trade_date":"2026-07-13","price":92.7,"day_open":92.55,"day_high":93.56,"day_low":91.49,"adjusted_close":92.7,"ret3":0.24,"ret5":-2.2,"ret20":1.98,"ret60":11.73,"relative_spy20":0.17,"relative_spy60":4.42,"ma20":90.73,"ma60":91.09,"volume_ratio":0.63,"close_position":0.585,"max_drawdown20":-8.55,"volatility20":1.75,"trend_score":47.7,"strength_level":"D","trading_risk_score":22.1,"risk_level":"低","trade_state":"退出","momentum_pass":false,"risk_flags":["量能不足","回撤偏大","趋势未通过"],"support":90.73,"target":96.26,"stop":87.95,"trigger_price_basis":"raw_ohlc","return_basis":"adjusted_close"},{"symbol":"XLC","name":"Communication Services","asset_type":"行业","theme":"通信","trade_date":"2026-07-13","price":111.59,"day_open":111.78,"day_high":112.75,"day_low":111.47,"adjusted_close":111.59,"ret3":1.95,"ret5":1.25,"ret20":-0.21,"ret60":-4.67,"relative_spy20":-2.02,"relative_spy60":-11.98,"ma20":109.23,"ma60":113.31,"volume_ratio":0.82,"close_position":0.094,"max_drawdown20":-5.76,"volatility20":1.19,"trend_score":44.2,"strength_level":"D","trading_risk_score":28.5,"risk_level":"低","trade_state":"退出","momentum_pass":false,"risk_flags":["收盘偏弱","趋势未通过"],"support":109.25,"target":113.93,"stop":108.48,"trigger_price_basis":"raw_ohlc","return_basis":"adjusted_close"},{"symbol":"KWEB","name":"KraneShares CSI China Internet","asset_type":"海外","theme":"中国资产","trade_date":"2026-07-13","price":26.23,"day_open":26.27,"day_high":26.45,"day_low":26.11,"adjusted_close":26.23,"ret3":-0.68,"ret5":2.5,"ret20":-1.28,"ret60":-11.5,"relative_spy20":-3.09,"relative_spy60":-18.81,"ma20":25.32,"ma60":27.27,"volume_ratio":0.91,"close_position":0.348,"max_drawdown20":-11.23,"volatility20":1.68,"trend_score":43.5,"strength_level":"D","trading_risk_score":23.2,"risk_level":"低","trade_state":"退出","momentum_pass":false,"risk_flags":["回撤偏大","趋势未通过"],"support":25.54,"target":26.92,"stop":25.31,"trigger_price_basis":"raw_ohlc","return_basis":"adjusted_close"},{"symbol":"XLI","name":"Industrial Select Sector","asset_type":"行业","theme":"工业","trade_date":"2026-07-13","price":180.37,"day_open":181.52,"day_high":182.18,"day_low":179.81,"adjusted_close":180.37,"ret3":-0.03,"ret5":-2.8,"ret20":3.23,"ret60":5.63,"relative_spy20":1.42,"relative_spy60":-1.68,"ma20":181.28,"ma60":175.43,"volume_ratio":0.84,"close_position":0.236,"max_drawdown20":-2.8,"volatility20":1.13,"trend_score":40.7,"strength_level":"D","trading_risk_score":26.7,"risk_level":"低","trade_state":"退出","momentum_pass":false,"risk_flags":["收盘偏弱","趋势未通过"],"support":181.28,"target":184.62,"stop":174.71,"trigger_price_basis":"raw_ohlc","return_basis":"adjusted_close"},{"symbol":"XLK","name":"Technology Select Sector","asset_type":"行业","theme":"科技","trade_date":"2026-07-13","price":181.28,"day_open":183.1,"day_high":183.88,"day_low":180.54,"adjusted_close":181.28,"ret3":-0.07,"ret5":-1.25,"ret20":-0.94,"ret60":20.76,"relative_spy20":-2.75,"relative_spy60":13.45,"ma20":185.15,"ma60":177.19,"volume_ratio":0.79,"close_position":0.221,"max_drawdown20":-6.75,"volatility20":2.26,"trend_score":40.5,"strength_level":"D","trading_risk_score":35.1,"risk_level":"中","trade_state":"退出","momentum_pass":false,"risk_flags":["收盘偏弱","趋势未通过"],"support":185.15,"target":188.27,"stop":171.96,"trigger_price_basis":"raw_ohlc","return_basis":"adjusted_close"},{"symbol":"IWM","name":"iShares Russell 2000","asset_type":"宽基","theme":"小盘股","trade_date":"2026-07-13","price":293.48,"day_open":295.06,"day_high":295.78,"day_low":292.6,"adjusted_close":293.48,"ret3":0.0,"ret5":-1.81,"ret20":1.3,"ret60":9.2,"relative_spy20":-0.51,"relative_spy60":1.89,"ma20":296.25,"ma60":286.24,"volume_ratio":0.74,"close_position":0.277,"max_drawdown20":-2.32,"volatility20":0.85,"trend_score":39.7,"strength_level":"D","trading_risk_score":26.4,"risk_level":"低","trade_state":"退出","momentum_pass":false,"risk_flags":["收盘偏弱","量能不足","趋势未通过"],"support":296.25,"target":300.04,"stop":284.73,"trigger_price_basis":"raw_ohlc","return_basis":"adjusted_close"},{"symbol":"SPMO","name":"Invesco S&P 500 Momentum ETF","asset_type":"因子","theme":"动量","trade_date":"2026-07-13","price":149.73,"day_open":151.11,"day_high":151.58,"day_low":149.26,"adjusted_close":149.73,"ret3":-0.56,"ret5":-2.12,"ret20":-0.41,"ret60":18.47,"relative_spy20":-2.22,"relative_spy60":11.16,"ma20":154.93,"ma60":145.64,"volume_ratio":0.87,"close_position":0.202,"max_drawdown20":-7.57,"volatility20":2.52,"trend_score":39.5,"strength_level":"D","trading_risk_score":37.7,"risk_level":"中","trade_state":"退出","momentum_pass":false,"risk_flags":["收盘偏弱","趋势未通过"],"support":154.93,"target":155.47,"stop":142.07,"trigger_price_basis":"raw_ohlc","return_basis":"adjusted_close"},{"symbol":"QQQ","name":"Invesco QQQ","asset_type":"宽基","theme":"科技成长","trade_date":"2026-07-13","price":711.74,"day_open":717.72,"day_high":718.74,"day_low":710.1,"adjusted_close":711.74,"ret3":0.04,"ret5":-1.53,"ret20":-0.64,"ret60":11.79,"relative_spy20":-2.45,"relative_spy60":4.48,"ma20":722.1,"ma60":705.13,"volume_ratio":0.79,"close_position":0.19,"max_drawdown20":-4.93,"volatility20":1.75,"trend_score":37.8,"strength_level":"D","trading_risk_score":30.0,"risk_level":"低","trade_state":"退出","momentum_pass":false,"risk_flags":["收盘偏弱","趋势未通过"],"support":722.1,"target":731.3,"stop":685.66,"trigger_price_basis":"raw_ohlc","return_basis":"adjusted_close"},{"symbol":"SHY","name":"iShares 1-3 Year Treasury Bond","asset_type":"债券","theme":"短债","trade_date":"2026-07-13","price":81.79,"day_open":81.87,"day_high":81.87,"day_low":81.79,"adjusted_close":81.79,"ret3":-0.06,"ret5":-0.23,"ret20":-0.08,"ret60":0.0,"relative_spy20":-1.89,"relative_spy60":-7.31,"ma20":81.84,"ma60":81.77,"volume_ratio":0.76,"close_position":0.0,"max_drawdown20":-0.3,"volatility20":0.11,"trend_score":37.0,"strength_level":"D","trading_risk_score":25.2,"risk_level":"低","trade_state":"退出","momentum_pass":false,"risk_flags":["收盘偏弱","趋势未通过"],"support":81.84,"target":81.87,"stop":81.68,"trigger_price_basis":"raw_ohlc","return_basis":"adjusted_close"},{"symbol":"MCHI","name":"iShares MSCI China","asset_type":"海外","theme":"中国资产","trade_date":"2026-07-13","price":52.53,"day_open":52.73,"day_high":52.94,"day_low":52.4,"adjusted_close":52.53,"ret3":-0.61,"ret5":0.98,"ret20":-2.69,"ret60":-8.88,"relative_spy20":-4.5,"relative_spy60":-16.19,"ma20":52.32,"ma60":55.1,"volume_ratio":0.72,"close_position":0.239,"max_drawdown20":-8.1,"volatility20":1.19,"trend_score":36.9,"strength_level":"D","trading_risk_score":29.9,"risk_level":"低","trade_state":"退出","momentum_pass":false,"risk_flags":["收盘偏弱","量能不足","回撤偏大","趋势未通过"],"support":52.32,"target":53.36,"stop":51.42,"trigger_price_basis":"raw_ohlc","return_basis":"adjusted_close"},{"symbol":"XLY","name":"Consumer Discretionary","asset_type":"行业","theme":"消费","trade_date":"2026-07-13","price":116.04,"day_open":117.2,"day_high":117.52,"day_low":115.62,"adjusted_close":116.04,"ret3":0.64,"ret5":-1.67,"ret20":-0.02,"ret60":-1.62,"relative_spy20":-1.83,"relative_spy60":-8.93,"ma20":116.35,"ma60":117.38,"volume_ratio":1.05,"close_position":0.221,"max_drawdown20":-4.21,"volatility20":1.3,"trend_score":36.8,"strength_level":"D","trading_risk_score":27.5,"risk_level":"低","trade_state":"退出","momentum_pass":false,"risk_flags":["收盘偏弱","趋势未通过"],"support":116.35,"target":119.13,"stop":111.93,"trigger_price_basis":"raw_ohlc","return_basis":"adjusted_close"},{"symbol":"EWJ","name":"iShares MSCI Japan","asset_type":"海外","theme":"日本","trade_date":"2026-07-13","price":92.72,"day_open":93.07,"day_high":93.37,"day_low":92.5,"adjusted_close":92.72,"ret3":0.19,"ret5":-2.68,"ret20":1.13,"ret60":4.66,"relative_spy20":-0.68,"relative_spy60":-2.65,"ma20":93.7,"ma60":91.35,"volume_ratio":0.87,"close_position":0.249,"max_drawdown20":-4.57,"volatility20":1.52,"trend_score":36.8,"strength_level":"D","trading_risk_score":27.9,"risk_level":"低","trade_state":"退出","momentum_pass":false,"risk_flags":["收盘偏弱","趋势未通过"],"support":93.7,"target":94.42,"stop":90.46,"trigger_price_basis":"raw_ohlc","return_basis":"adjusted_close"},{"symbol":"FBND","name":"Fidelity Total Bond ETF","asset_type":"债券","theme":"综合债券","trade_date":"2026-07-13","price":45.1,"day_open":45.2,"day_high":45.6,"day_low":45.08,"adjusted_close":45.1,"ret3":-0.27,"ret5":-0.79,"ret20":-0.71,"ret60":-0.74,"relative_spy20":-2.52,"relative_spy60":-8.05,"ma20":45.41,"ma60":45.29,"volume_ratio":0.99,"close_position":0.038,"max_drawdown20":-1.25,"volatility20":0.23,"trend_score":36.7,"strength_level":"D","trading_risk_score":25.7,"risk_level":"低","trade_state":"退出","momentum_pass":false,"risk_flags":["收盘偏弱","趋势未通过"],"support":45.41,"target":45.35,"stop":44.76,"trigger_price_basis":"raw_ohlc","return_basis":"adjusted_close"},{"symbol":"INDA","name":"iShares MSCI India","asset_type":"海外","theme":"印度","trade_date":"2026-07-13","price":48.79,"day_open":49.12,"day_high":49.15,"day_low":48.72,"adjusted_close":48.79,"ret3":0.29,"ret5":-2.19,"ret20":2.09,"ret60":-2.38,"relative_spy20":0.28,"relative_spy60":-9.69,"ma20":49.28,"ma60":48.88,"volume_ratio":0.87,"close_position":0.174,"max_drawdown20":-2.54,"volatility20":0.96,"trend_score":36.6,"strength_level":"D","trading_risk_score":26.5,"risk_level":"低","trade_state":"退出","momentum_pass":false,"risk_flags":["收盘偏弱","趋势未通过"],"support":49.28,"target":49.23,"stop":48.2,"trigger_price_basis":"raw_ohlc","return_basis":"adjusted_close"},{"symbol":"OIH","name":"VanEck Oil Services","asset_type":"行业","theme":"油服","trade_date":"2026-07-13","price":382.9,"day_open":383.52,"day_high":388.41,"day_low":382.14,"adjusted_close":382.9,"ret3":1.34,"ret5":6.41,"ret20":-10.09,"ret60":-5.06,"relative_spy20":-11.9,"relative_spy60":-12.37,"ma20":381.97,"ma60":414.78,"volume_ratio":0.97,"close_position":0.121,"max_drawdown20":-16.01,"volatility20":1.9,"trend_score":36.2,"strength_level":"D","trading_risk_score":37.8,"risk_level":"中","trade_state":"退出","momentum_pass":false,"risk_flags":["收盘偏弱","回撤偏大","趋势未通过"],"support":381.97,"target":394.61,"stop":367.29,"trigger_price_basis":"raw_ohlc","return_basis":"adjusted_close"},{"symbol":"SMH","name":"VanEck Semiconductor ETF","asset_type":"主题","theme":"半导体","trade_date":"2026-07-13","price":585.62,"day_open":598.4,"day_high":599.36,"day_low":583.28,"adjusted_close":585.62,"ret3":-1.24,"ret5":-3.09,"ret20":-3.91,"ret60":29.28,"relative_spy20":-5.72,"relative_spy60":21.97,"ma20":620.45,"ma60":573.43,"volume_ratio":0.84,"close_position":0.146,"max_drawdown20":-13.07,"volatility20":3.72,"trend_score":35.7,"strength_level":"D","trading_risk_score":50.6,"risk_level":"中","trade_state":"退出","momentum_pass":false,"risk_flags":["收盘偏弱","回撤偏大","趋势未通过"],"support":620.45,"target":619.7,"stop":540.19,"trigger_price_basis":"raw_ohlc","return_basis":"adjusted_close"},{"symbol":"IEF","name":"iShares 7-10 Year Treasury Bond","asset_type":"债券","theme":"中债","trade_date":"2026-07-13","price":93.29,"day_open":93.5,"day_high":93.52,"day_low":93.26,"adjusted_close":93.29,"ret3":-0.24,"ret5":-0.94,"ret20":-0.79,"ret60":-1.42,"relative_spy20":-2.6,"relative_spy60":-8.73,"ma20":94.01,"ma60":93.91,"volume_ratio":0.87,"close_position":0.112,"max_drawdown20":-1.54,"volatility20":0.31,"trend_score":35.2,"strength_level":"D","trading_risk_score":25.9,"risk_level":"低","trade_state":"退出","momentum_pass":false,"risk_flags":["收盘偏弱","趋势未通过"],"support":94.01,"target":93.64,"stop":92.83,"trigger_price_basis":"raw_ohlc","return_basis":"adjusted_close"},{"symbol":"EFA","name":"iShares MSCI EAFE","asset_type":"海外","theme":"发达市场","trade_date":"2026-07-13","price":103.24,"day_open":103.85,"day_high":103.98,"day_low":103.08,"adjusted_close":103.24,"ret3":-0.12,"ret5":-2.11,"ret20":0.14,"ret60":1.51,"relative_spy20":-1.67,"relative_spy60":-5.8,"ma20":103.71,"ma60":102.22,"volume_ratio":0.71,"close_position":0.173,"max_drawdown20":-2.22,"volatility20":0.85,"trend_score":34.6,"strength_level":"D","trading_risk_score":26.3,"risk_level":"低","trade_state":"退出","momentum_pass":false,"risk_flags":["收盘偏弱","量能不足","趋势未通过"],"support":103.71,"target":104.62,"stop":101.4,"trigger_price_basis":"raw_ohlc","return_basis":"adjusted_close"},{"symbol":"ARKK","name":"ARK Innovation ETF","asset_type":"主题","theme":"创新成长","trade_date":"2026-07-13","price":78.24,"day_open":79.47,"day_high":79.62,"day_low":77.89,"adjusted_close":78.24,"ret3":-2.4,"ret5":-6.42,"ret20":3.68,"ret60":0.99,"relative_spy20":1.87,"relative_spy60":-6.32,"ma20":79.45,"ma60":78.04,"volume_ratio":0.74,"close_position":0.202,"max_drawdown20":-6.42,"volatility20":2.11,"trend_score":34.2,"strength_level":"D","trading_risk_score":33.8,"risk_level":"低","trade_state":"退出","momentum_pass":false,"risk_flags":["收盘偏弱","量能不足","趋势未通过"],"support":79.45,"target":82.05,"stop":73.16,"trigger_price_basis":"raw_ohlc","return_basis":"adjusted_close"},{"symbol":"SOXX","name":"iShares Semiconductor ETF","asset_type":"主题","theme":"半导体","trade_date":"2026-07-13","price":553.61,"day_open":564.66,"day_high":566.65,"day_low":550.26,"adjusted_close":553.61,"ret3":-1.5,"ret5":-4.8,"ret20":-5.63,"ret60":37.83,"relative_spy20":-7.44,"relative_spy60":30.52,"ma20":598.14,"ma60":539.06,"volume_ratio":0.87,"close_position":0.204,"max_drawdown20":-15.77,"volatility20":4.51,"trend_score":33.4,"strength_level":"D","trading_risk_score":58.6,"risk_level":"中","trade_state":"退出","momentum_pass":false,"risk_flags":["收盘偏弱","回撤偏大","趋势未通过"],"support":598.14,"target":592.61,"stop":501.61,"trigger_price_basis":"raw_ohlc","return_basis":"adjusted_close"},{"symbol":"XHB","name":"SPDR S&P Homebuilders","asset_type":"行业","theme":"房屋建筑","trade_date":"2026-07-13","price":107.07,"day_open":108.37,"day_high":109.34,"day_low":106.69,"adjusted_close":107.07,"ret3":0.97,"ret5":-3.79,"ret20":-0.56,"ret60":4.22,"relative_spy20":-2.37,"relative_spy60":-3.09,"ma20":110.63,"ma60":105.76,"volume_ratio":0.77,"close_position":0.143,"max_drawdown20":-8.52,"volatility20":2.02,"trend_score":32.4,"strength_level":"D","trading_risk_score":34.3,"risk_level":"低","trade_state":"退出","momentum_pass":false,"risk_flags":["收盘偏弱","回撤偏大","趋势未通过"],"support":110.63,"target":110.93,"stop":101.93,"trigger_price_basis":"raw_ohlc","return_basis":"adjusted_close"},{"symbol":"XLB","name":"Materials Select Sector","asset_type":"行业","theme":"原材料","trade_date":"2026-07-13","price":50.58,"day_open":50.97,"day_high":51.35,"day_low":50.35,"adjusted_close":50.58,"ret3":0.84,"ret5":-2.69,"ret20":-0.88,"ret60":-1.19,"relative_spy20":-2.69,"relative_spy60":-8.5,"ma20":51.36,"ma60":51.13,"volume_ratio":0.89,"close_position":0.227,"max_drawdown20":-4.5,"volatility20":1.17,"trend_score":31.7,"strength_level":"D","trading_risk_score":27.7,"risk_level":"低","trade_state":"退出","momentum_pass":false,"risk_flags":["收盘偏弱","趋势未通过"],"support":51.36,"target":51.77,"stop":48.99,"trigger_price_basis":"raw_ohlc","return_basis":"adjusted_close"},{"symbol":"VXUS","name":"Vanguard Total International Stock ETF","asset_type":"海外","theme":"全球除美国","trade_date":"2026-07-13","price":83.78,"day_open":84.29,"day_high":84.49,"day_low":83.66,"adjusted_close":83.78,"ret3":-0.78,"ret5":-2.77,"ret20":-1.39,"ret60":1.82,"relative_spy20":-3.2,"relative_spy60":-5.49,"ma20":85.26,"ma60":84.19,"volume_ratio":0.79,"close_position":0.145,"max_drawdown20":-3.77,"volatility20":1.15,"trend_score":31.6,"strength_level":"D","trading_risk_score":27.3,"risk_level":"低","trade_state":"退出","momentum_pass":false,"risk_flags":["收盘偏弱","趋势未通过"],"support":85.26,"target":85.14,"stop":81.97,"trigger_price_basis":"raw_ohlc","return_basis":"adjusted_close"},{"symbol":"ITB","name":"iShares U.S. Home Construction","asset_type":"行业","theme":"房屋建筑","trade_date":"2026-07-13","price":96.3,"day_open":97.61,"day_high":98.64,"day_low":95.98,"adjusted_close":96.3,"ret3":0.41,"ret5":-4.95,"ret20":-1.31,"ret60":2.68,"relative_spy20":-3.12,"relative_spy60":-4.63,"ma20":99.79,"ma60":95.66,"volume_ratio":0.9,"close_position":0.12,"max_drawdown20":-8.57,"volatility20":2.18,"trend_score":30.8,"strength_level":"D","trading_risk_score":35.6,"risk_level":"中","trade_state":"退出","momentum_pass":false,"risk_flags":["收盘偏弱","回撤偏大","趋势未通过"],"support":99.79,"target":100.04,"stop":91.32,"trigger_price_basis":"raw_ohlc","return_basis":"adjusted_close"},{"symbol":"ITA","name":"iShares U.S. Aerospace & Defense","asset_type":"主题","theme":"国防","trade_date":"2026-07-13","price":235.05,"day_open":238.76,"day_high":238.47,"day_low":234.3,"adjusted_close":235.05,"ret3":-1.91,"ret5":-6.27,"ret20":-0.35,"ret60":0.52,"relative_spy20":-2.16,"relative_spy60":-6.79,"ma20":239.85,"ma60":229.38,"volume_ratio":0.81,"close_position":0.18,"max_drawdown20":-6.27,"volatility20":1.26,"trend_score":29.0,"strength_level":"D","trading_risk_score":28.8,"risk_level":"低","trade_state":"退出","momentum_pass":false,"risk_flags":["收盘偏弱","趋势未通过"],"support":239.85,"target":241.25,"stop":226.78,"trigger_price_basis":"raw_ohlc","return_basis":"adjusted_close"},{"symbol":"EEM","name":"iShares MSCI Emerging Markets","asset_type":"海外","theme":"新兴市场","trade_date":"2026-07-13","price":64.5,"day_open":65.19,"day_high":65.29,"day_low":64.39,"adjusted_close":64.5,"ret3":-2.61,"ret5":-4.54,"ret20":-3.95,"ret60":4.24,"relative_spy20":-5.76,"relative_spy60":-3.07,"ma20":67.59,"ma60":66.17,"volume_ratio":0.76,"close_position":0.12,"max_drawdown20":-9.42,"volatility20":2.24,"trend_score":24.9,"strength_level":"D","trading_risk_score":36.5,"risk_level":"中","trade_state":"退出","momentum_pass":false,"risk_flags":["收盘偏弱","回撤偏大","趋势未通过"],"support":67.59,"target":66.26,"stop":62.15,"trigger_price_basis":"raw_ohlc","return_basis":"adjusted_close"},{"symbol":"IBIT","name":"iShares Bitcoin Trust ETF","asset_type":"加密资产","theme":"比特币","trade_date":"2026-07-13","price":35.22,"day_open":35.38,"day_high":35.62,"day_low":34.96,"adjusted_close":35.22,"ret3":-0.03,"ret5":-2.49,"ret20":-2.3,"ret60":-17.25,"relative_spy20":-4.11,"relative_spy60":-24.56,"ma20":35.35,"ma60":40.02,"volume_ratio":0.71,"close_position":0.391,"max_drawdown20":-11.79,"volatility20":2.44,"trend_score":23.1,"strength_level":"D","trading_risk_score":29.6,"risk_level":"低","trade_state":"退出","momentum_pass":false,"risk_flags":["量能不足","回撤偏大","趋势未通过"],"support":35.35,"target":36.64,"stop":33.33,"trigger_price_basis":"raw_ohlc","return_basis":"adjusted_close"},{"symbol":"PAVE","name":"Global X U.S. Infrastructure Development","asset_type":"主题","theme":"基础设施","trade_date":"2026-07-13","price":56.23,"day_open":56.61,"day_high":56.9,"day_low":56.08,"adjusted_close":56.23,"ret3":0.34,"ret5":-2.77,"ret20":-1.49,"ret60":4.2,"relative_spy20":-3.3,"relative_spy60":-3.11,"ma20":57.81,"ma60":56.61,"volume_ratio":0.94,"close_position":0.183,"max_drawdown20":-6.42,"volatility20":1.37,"trend_score":18.8,"strength_level":"D","trading_risk_score":28.9,"risk_level":"低","trade_state":"退出","momentum_pass":false,"risk_flags":["收盘偏弱","趋势未通过"],"support":57.81,"target":57.75,"stop":54.2,"trigger_price_basis":"raw_ohlc","return_basis":"adjusted_close"},{"symbol":"TLT","name":"iShares 20+ Year Treasury Bond","asset_type":"债券","theme":"长债","trade_date":"2026-07-13","price":83.97,"day_open":84.18,"day_high":84.28,"day_low":83.93,"adjusted_close":83.97,"ret3":-0.46,"ret5":-1.73,"ret20":-1.98,"ret60":-2.2,"relative_spy20":-3.79,"relative_spy60":-9.51,"ma20":85.68,"ma60":85.08,"volume_ratio":0.83,"close_position":0.104,"max_drawdown20":-3.62,"volatility20":0.56,"trend_score":17.3,"strength_level":"D","trading_risk_score":27.2,"risk_level":"低","trade_state":"退出","momentum_pass":false,"risk_flags":["收盘偏弱","趋势未通过"],"support":85.68,"target":84.59,"stop":83.14,"trigger_price_basis":"raw_ohlc","return_basis":"adjusted_close"},{"symbol":"QTUM","name":"Defiance Quantum ETF","asset_type":"主题","theme":"量子计算","trade_date":"2026-07-13","price":149.02,"day_open":151.98,"day_high":152.04,"day_low":148.42,"adjusted_close":149.02,"ret3":-2.26,"ret5":-5.05,"ret20":-6.33,"ret60":20.97,"relative_spy20":-8.14,"relative_spy60":13.66,"ma20":159.48,"ma60":149.72,"volume_ratio":0.56,"close_position":0.166,"max_drawdown20":-11.47,"volatility20":2.56,"trend_score":10.2,"strength_level":"D","trading_risk_score":40.3,"risk_level":"中","trade_state":"退出","momentum_pass":false,"risk_flags":["收盘偏弱","量能不足","回撤偏大","趋势未通过"],"support":159.48,"target":156.02,"stop":139.69,"trigger_price_basis":"raw_ohlc","return_basis":"adjusted_close"},{"symbol":"XSD","name":"SPDR S&P Semiconductor ETF","asset_type":"主题","theme":"半导体","trade_date":"2026-07-13","price":537.38,"day_open":548.94,"day_high":549.99,"day_low":533.95,"adjusted_close":537.38,"ret3":-2.05,"ret5":-5.93,"ret20":-10.04,"ret60":36.69,"relative_spy20":-11.85,"relative_spy60":29.38,"ma20":588.35,"ma60":555.66,"volume_ratio":0.8,"close_position":0.214,"max_drawdown20":-17.46,"volatility20":4.34,"trend_score":10.0,"strength_level":"D","trading_risk_score":58.2,"risk_level":"中","trade_state":"退出","momentum_pass":false,"risk_flags":["收盘偏弱","回撤偏大","趋势未通过"],"support":588.35,"target":577.99,"stop":483.24,"trigger_price_basis":"raw_ohlc","return_basis":"adjusted_close"},{"symbol":"BOTZ","name":"Global X Robotics & AI","asset_type":"主题","theme":"人工智能","trade_date":"2026-07-13","price":35.87,"day_open":36.21,"day_high":36.31,"day_low":35.78,"adjusted_close":35.87,"ret3":-0.33,"ret5":-6.22,"ret20":-3.68,"ret60":-2.29,"relative_spy20":-5.49,"relative_spy60":-9.6,"ma20":37.18,"ma60":38.41,"volume_ratio":1.01,"close_position":0.17,"max_drawdown20":-6.47,"volatility20":2.16,"trend_score":9.4,"strength_level":"D","trading_risk_score":34.1,"risk_level":"低","trade_state":"退出","momentum_pass":false,"risk_flags":["收盘偏弱","趋势未通过"],"support":37.18,"target":36.77,"stop":34.67,"trigger_price_basis":"raw_ohlc","return_basis":"adjusted_close"},{"symbol":"DRIV","name":"Global X Autonomous & Electric Vehicles","asset_type":"主题","theme":"智能汽车","trade_date":"2026-07-13","price":35.37,"day_open":35.87,"day_high":35.93,"day_low":35.2,"adjusted_close":35.37,"ret3":-1.67,"ret5":-6.01,"ret20":-9.06,"ret60":3.69,"relative_spy20":-10.87,"relative_spy60":-3.62,"ma20":37.96,"ma60":38.44,"volume_ratio":1.44,"close_position":0.233,"max_drawdown20":-12.84,"volatility20":2.31,"trend_score":5.3,"strength_level":"D","trading_risk_score":39.2,"risk_level":"中","trade_state":"退出","momentum_pass":false,"risk_flags":["收盘偏弱","回撤偏大","趋势未通过"],"support":37.96,"target":36.84,"stop":33.41,"trigger_price_basis":"raw_ohlc","return_basis":"adjusted_close"},{"symbol":"GLD","name":"SPDR Gold Shares","asset_type":"商品","theme":"黄金","trade_date":"2026-07-13","price":367.13,"day_open":372.77,"day_high":372.89,"day_low":365.77,"adjusted_close":367.13,"ret3":-1.95,"ret5":-3.93,"ret20":-4.97,"ret60":-16.65,"relative_spy20":-6.78,"relative_spy60":-23.96,"ma20":378.47,"ma60":405.55,"volume_ratio":0.79,"close_position":0.191,"max_drawdown20":-7.97,"volatility20":1.48,"trend_score":3.9,"strength_level":"D","trading_risk_score":29.8,"risk_level":"低","trade_state":"退出","momentum_pass":false,"risk_flags":["收盘偏弱","趋势未通过"],"support":378.47,"target":374.78,"stop":356.93,"trigger_price_basis":"raw_ohlc","return_basis":"adjusted_close"},{"symbol":"XAR","name":"SPDR S&P Aerospace & Defense","asset_type":"主题","theme":"国防","trade_date":"2026-07-13","price":264.17,"day_open":269.51,"day_high":270.95,"day_low":263.19,"adjusted_close":264.17,"ret3":-3.53,"ret5":-8.82,"ret20":-7.09,"ret60":-4.08,"relative_spy20":-8.9,"relative_spy60":-11.39,"ma20":278.62,"ma60":271.83,"volume_ratio":1.03,"close_position":0.126,"max_drawdown20":-8.82,"volatility20":1.48,"trend_score":1.2,"strength_level":"D","trading_risk_score":30.3,"risk_level":"低","trade_state":"退出","momentum_pass":false,"risk_flags":["收盘偏弱","回撤偏大","趋势未通过"],"support":278.62,"target":274.2,"stop":250.8,"trigger_price_basis":"raw_ohlc","return_basis":"adjusted_close"},{"symbol":"TAN","name":"Invesco Solar ETF","asset_type":"主题","theme":"新能源","trade_date":"2026-07-13","price":53.12,"day_open":54.26,"day_high":54.6,"day_low":52.81,"adjusted_close":53.12,"ret3":-1.88,"ret5":-7.68,"ret20":-14.74,"ret60":-3.98,"relative_spy20":-16.55,"relative_spy60":-11.29,"ma20":57.91,"ma60":60.99,"volume_ratio":0.52,"close_position":0.173,"max_drawdown20":-15.72,"volatility20":2.37,"trend_score":0,"strength_level":"D","trading_risk_score":41.4,"risk_level":"中","trade_state":"退出","momentum_pass":false,"risk_flags":["收盘偏弱","量能不足","回撤偏大","趋势未通过"],"support":57.91,"target":56.04,"stop":49.23,"trigger_price_basis":"raw_ohlc","return_basis":"adjusted_close"},{"symbol":"LIT","name":"Global X Lithium & Battery Tech","asset_type":"主题","theme":"新能源","trade_date":"2026-07-13","price":70.24,"day_open":71.1,"day_high":71.24,"day_low":70.08,"adjusted_close":70.24,"ret3":-2.61,"ret5":-7.79,"ret20":-12.63,"ret60":-11.42,"relative_spy20":-14.44,"relative_spy60":-18.73,"ma20":77.68,"ma60":82.28,"volume_ratio":0.89,"close_position":0.134,"max_drawdown20":-16.1,"volatility20":1.91,"trend_score":0,"strength_level":"D","trading_risk_score":38.0,"risk_level":"中","trade_state":"退出","momentum_pass":false,"risk_flags":["收盘偏弱","回撤偏大","趋势未通过"],"support":77.68,"target":72.08,"stop":67.79,"trigger_price_basis":"raw_ohlc","return_basis":"adjusted_close"},{"symbol":"URA","name":"Global X Uranium ETF","asset_type":"主题","theme":"核能","trade_date":"2026-07-13","price":40.72,"day_open":42.0,"day_high":42.21,"day_low":40.45,"adjusted_close":40.72,"ret3":-2.26,"ret5":-7.2,"ret20":-9.17,"ret60":-25.75,"relative_spy20":-10.98,"relative_spy60":-33.06,"ma20":44.42,"ma60":49.54,"volume_ratio":0.9,"close_position":0.154,"max_drawdown20":-15.27,"volatility20":2.38,"trend_score":0,"strength_level":"D","trading_risk_score":41.2,"risk_level":"中","trade_state":"退出","momentum_pass":false,"risk_flags":["收盘偏弱","回撤偏大","趋势未通过"],"support":44.42,"target":43.03,"stop":37.64,"trigger_price_basis":"raw_ohlc","return_basis":"adjusted_close"},{"symbol":"SLV","name":"iShares Silver Trust","asset_type":"商品","theme":"贵金属","trade_date":"2026-07-13","price":52.16,"day_open":52.95,"day_high":53.0,"day_low":51.78,"adjusted_close":52.16,"ret3":-1.27,"ret5":-7.04,"ret20":-14.24,"ret60":-27.39,"relative_spy20":-16.05,"relative_spy60":-34.7,"ma20":55.94,"ma60":64.33,"volume_ratio":0.75,"close_position":0.311,"max_drawdown20":-18.42,"volatility20":2.83,"trend_score":0,"strength_level":"D","trading_risk_score":36.7,"risk_level":"中","trade_state":"退出","momentum_pass":false,"risk_flags":["回撤偏大","趋势未通过"],"support":55.94,"target":54.42,"stop":49.15,"trigger_price_basis":"raw_ohlc","return_basis":"adjusted_close"},{"symbol":"ICLN","name":"iShares Global Clean Energy","asset_type":"主题","theme":"清洁能源","trade_date":"2026-07-13","price":18.62,"day_open":18.93,"day_high":19.01,"day_low":18.55,"adjusted_close":18.625,"ret3":-2.23,"ret5":-7.43,"ret20":-9.96,"ret60":-4.38,"relative_spy20":-11.77,"relative_spy60":-11.69,"ma20":20.14,"ma60":20.88,"volume_ratio":0.81,"close_position":0.161,"max_drawdown20":-13.89,"volatility20":2.34,"trend_score":0,"strength_level":"D","trading_risk_score":40.1,"risk_level":"中","trade_state":"退出","momentum_pass":false,"risk_flags":["收盘偏弱","回撤偏大","趋势未通过"],"support":20.14,"target":19.51,"stop":17.44,"trigger_price_basis":"raw_ohlc","return_basis":"adjusted_close"},{"symbol":"XME","name":"SPDR S&P Metals & Mining","asset_type":"行业","theme":"金属矿业","trade_date":"2026-07-13","price":102.09,"day_open":102.82,"day_high":103.49,"day_low":101.45,"adjusted_close":102.09,"ret3":0.15,"ret5":-3.76,"ret20":-13.68,"ret60":-11.69,"relative_spy20":-15.49,"relative_spy60":-19.0,"ma20":109.4,"ma60":116.31,"volume_ratio":1.0,"close_position":0.314,"max_drawdown20":-15.44,"volatility20":1.59,"trend_score":0,"strength_level":"D","trading_risk_score":25.0,"risk_level":"低","trade_state":"退出","momentum_pass":false,"risk_flags":["回撤偏大","趋势未通过"],"support":109.4,"target":106.64,"stop":96.03,"trigger_price_basis":"raw_ohlc","return_basis":"adjusted_close"},{"symbol":"GDX","name":"VanEck Gold Miners","asset_type":"行业","theme":"黄金矿业","trade_date":"2026-07-13","price":73.37,"day_open":74.1,"day_high":74.62,"day_low":72.83,"adjusted_close":73.37,"ret3":-0.22,"ret5":-6.82,"ret20":-5.6,"ret60":-24.96,"relative_spy20":-7.41,"relative_spy60":-32.27,"ma20":78.16,"ma60":85.19,"volume_ratio":0.74,"close_position":0.3,"max_drawdown20":-15.9,"volatility20":3.0,"trend_score":0,"strength_level":"D","trading_risk_score":46.5,"risk_level":"中","trade_state":"退出","momentum_pass":false,"risk_flags":["收盘偏弱","量能不足","回撤偏大","趋势未通过"],"support":78.16,"target":76.9,"stop":68.67,"trigger_price_basis":"raw_ohlc","return_basis":"adjusted_close"},{"symbol":"COPX","name":"Global X Copper Miners","asset_type":"行业","theme":"铜矿","trade_date":"2026-07-13","price":74.35,"day_open":75.73,"day_high":76.11,"day_low":74.07,"adjusted_close":74.35,"ret3":1.79,"ret5":-5.26,"ret20":-10.29,"ret60":-13.33,"relative_spy20":-12.1,"relative_spy60":-20.64,"ma20":79.24,"ma60":82.3,"volume_ratio":0.73,"close_position":0.137,"max_drawdown20":-18.4,"volatility20":2.92,"trend_score":0,"strength_level":"D","trading_risk_score":47.4,"risk_level":"中","trade_state":"退出","momentum_pass":false,"risk_flags":["收盘偏弱","量能不足","回撤偏大","趋势未通过"],"support":79.24,"target":77.37,"stop":70.32,"trigger_price_basis":"raw_ohlc","return_basis":"adjusted_close"}],"failures":{},"realtime_scope":["当前价","当日涨跌","关键位触发"],"snapshot_scope":["趋势分","交易风险","交易状态","市场状态","行业广度","准备信号"]}