{"market":"US","model_version":"US ETF Garden v3 · Flower Signals","generated_at":"2026-07-21T18:31:10.536868-04:00","model_date":"2026-07-21","quote_trade_date":"2026-07-21","timezone":"America/New_York","data_source":"Yahoo Chart API","session_state":"closed","stage":"美股收盘版","trigger_base_date":"2026-07-20","trigger_base_rows":{"HACK":{"symbol":"HACK","support":105.95,"target":115.39,"stop":103.0,"price":110.08,"trade_date":"2026-07-20"},"USO":{"symbol":"USO","support":120.54,"target":130.48,"stop":111.86,"price":125.51,"trade_date":"2026-07-20"},"ETHA":{"symbol":"ETHA","support":13.82,"target":14.84,"stop":13.08,"price":14.33,"trade_date":"2026-07-20"},"CIBR":{"symbol":"CIBR","support":89.96,"target":95.93,"stop":86.26,"price":91.79,"trade_date":"2026-07-20"},"XOP":{"symbol":"XOP","support":165.04,"target":175.04,"stop":159.22,"price":170.04,"trade_date":"2026-07-20"},"KWEB":{"symbol":"KWEB","support":26.78,"target":28.1,"stop":25.59,"price":27.44,"trade_date":"2026-07-20"},"IHF":{"symbol":"IHF","support":56.06,"target":57.83,"stop":54.64,"price":56.46,"trade_date":"2026-07-20"},"KIE":{"symbol":"KIE","support":62.7,"target":65.52,"stop":62.23,"price":64.11,"trade_date":"2026-07-20"},"XLE":{"symbol":"XLE","support":56.55,"target":59.33,"stop":54.94,"price":57.94,"trade_date":"2026-07-20"},"DBC":{"symbol":"DBC","support":28.68,"target":29.6,"stop":27.51,"price":29.14,"trade_date":"2026-07-20"},"KRE":{"symbol":"KRE","support":74.99,"target":77.85,"stop":73.27,"price":75.89,"trade_date":"2026-07-20"},"XLF":{"symbol":"XLF","support":55.12,"target":57.11,"stop":54.62,"price":56.04,"trade_date":"2026-07-20"},"IYT":{"symbol":"IYT","support":87.29,"target":90.28,"stop":85.57,"price":88.26,"trade_date":"2026-07-20"},"SKYY":{"symbol":"SKYY","support":135.26,"target":142.32,"stop":129.12,"price":136.66,"trade_date":"2026-07-20"},"VNQ":{"symbol":"VNQ","support":97.74,"target":101.31,"stop":97.04,"price":99.48,"trade_date":"2026-07-20"},"SCHD":{"symbol":"SCHD","support":32.26,"target":33.24,"stop":32.1,"price":32.75,"trade_date":"2026-07-20"},"IGV":{"symbol":"IGV","support":91.43,"target":96.81,"stop":87.87,"price":92.98,"trade_date":"2026-07-20"},"XRT":{"symbol":"XRT","support":87.82,"target":91.38,"stop":85.68,"price":88.94,"trade_date":"2026-07-20"},"XLRE":{"symbol":"XLRE","support":44.63,"target":46.08,"stop":44.1,"price":45.23,"trade_date":"2026-07-20"},"IBIT":{"symbol":"IBIT","support":35.7,"target":38.08,"stop":35.3,"price":36.89,"trade_date":"2026-07-20"},"EWZ":{"symbol":"EWZ","support":34.85,"target":36.24,"stop":34.47,"price":35.48,"trade_date":"2026-07-20"},"XLP":{"symbol":"XLP","support":84.14,"target":86.81,"stop":82.27,"price":84.86,"trade_date":"2026-07-20"},"FDN":{"symbol":"FDN","support":268.1,"target":277.4,"stop":261.4,"price":270.54,"trade_date":"2026-07-20"},"SHY":{"symbol":"SHY","support":81.89,"target":82.05,"stop":81.83,"price":81.96,"trade_date":"2026-07-20"},"SGOV":{"symbol":"SGOV","support":100.57,"target":100.6,"stop":100.44,"price":100.59,"trade_date":"2026-07-20"},"XLC":{"symbol":"XLC","support":109.51,"target":113.16,"stop":107.66,"price":110.8,"trade_date":"2026-07-20"},"MCHI":{"symbol":"MCHI","support":53.25,"target":54.91,"stop":52.28,"price":54.08,"trade_date":"2026-07-20"},"XLV":{"symbol":"XLV","support":159.3,"target":162.87,"stop":154.42,"price":159.25,"trade_date":"2026-07-20"},"IBB":{"symbol":"IBB","support":189.33,"target":191.73,"stop":179.6,"price":186.53,"trade_date":"2026-07-20"},"XBI":{"symbol":"XBI","support":155.92,"target":157.28,"stop":142.48,"price":150.94,"trade_date":"2026-07-20"},"RSP":{"symbol":"RSP","support":212.82,"target":215.27,"stop":208.62,"price":212.42,"trade_date":"2026-07-20"},"IHI":{"symbol":"IHI","support":50.61,"target":52.3,"stop":48.29,"price":50.58,"trade_date":"2026-07-20"},"UUP":{"symbol":"UUP","support":28.4,"target":28.52,"stop":28.22,"price":28.39,"trade_date":"2026-07-20"},"DIA":{"symbol":"DIA","support":522.54,"target":525.2,"stop":508.26,"price":517.94,"trade_date":"2026-07-20"},"SPY":{"symbol":"SPY","support":744.79,"target":752.05,"stop":728.81,"price":742.09,"trade_date":"2026-07-20"},"VTI":{"symbol":"VTI","support":368.21,"target":371.26,"stop":359.57,"price":366.25,"trade_date":"2026-07-20"},"IWM":{"symbol":"IWM","support":296.64,"target":298.14,"stop":284.54,"price":292.31,"trade_date":"2026-07-20"},"XLU":{"symbol":"XLU","support":45.42,"target":45.96,"stop":43.57,"price":44.94,"trade_date":"2026-07-20"},"XLI":{"symbol":"XLI","support":181.53,"target":182.44,"stop":172.37,"price":178.12,"trade_date":"2026-07-20"},"ITB":{"symbol":"ITB","support":99.83,"target":99.19,"stop":90.37,"price":95.41,"trade_date":"2026-07-20"},"IEF":{"symbol":"IEF","support":93.94,"target":93.92,"stop":93.03,"price":93.54,"trade_date":"2026-07-20"},"FBND":{"symbol":"FBND","support":45.37,"target":45.45,"stop":44.79,"price":45.17,"trade_date":"2026-07-20"},"EFA":{"symbol":"EFA","support":103.62,"target":104.0,"stop":100.66,"price":102.57,"trade_date":"2026-07-20"},"XLY":{"symbol":"XLY","support":116.11,"target":117.27,"stop":111.06,"price":114.61,"trade_date":"2026-07-20"},"INDA":{"symbol":"INDA","support":49.18,"target":49.02,"stop":47.93,"price":48.55,"trade_date":"2026-07-20"},"PAVE":{"symbol":"PAVE","support":57.4,"target":57.24,"stop":53.65,"price":55.7,"trade_date":"2026-07-20"},"TLT":{"symbol":"TLT","support":85.26,"target":84.54,"stop":83.02,"price":83.89,"trade_date":"2026-07-20"},"VXUS":{"symbol":"VXUS","support":84.73,"target":84.36,"stop":81.35,"price":83.07,"trade_date":"2026-07-20"},"XLB":{"symbol":"XLB","support":50.98,"target":51.24,"stop":48.42,"price":50.03,"trade_date":"2026-07-20"},"ITA":{"symbol":"ITA","support":238.36,"target":235.85,"stop":220.5,"price":229.27,"trade_date":"2026-07-20"},"QQQ":{"symbol":"QQQ","support":716.12,"target":713.29,"stop":673.09,"price":696.06,"trade_date":"2026-07-20"},"EWJ":{"symbol":"EWJ","support":93.15,"target":92.09,"stop":88.21,"price":90.43,"trade_date":"2026-07-20"},"OIH":{"symbol":"OIH","support":375.29,"target":387.12,"stop":359.26,"price":375.18,"trade_date":"2026-07-20"},"XHB":{"symbol":"XHB","support":110.58,"target":109.85,"stop":101.03,"price":106.07,"trade_date":"2026-07-20"},"GLD":{"symbol":"GLD","support":372.92,"target":375.08,"stop":357.62,"price":367.6,"trade_date":"2026-07-20"},"XLK":{"symbol":"XLK","support":182.89,"target":182.29,"stop":166.93,"price":175.71,"trade_date":"2026-07-20"},"SPMO":{"symbol":"SPMO","support":152.8,"target":150.04,"stop":137.15,"price":144.52,"trade_date":"2026-07-20"},"EEM":{"symbol":"EEM","support":66.44,"target":65.18,"stop":61.41,"price":63.56,"trade_date":"2026-07-20"},"XAR":{"symbol":"XAR","support":273.41,"target":269.2,"stop":246.12,"price":259.31,"trade_date":"2026-07-20"},"ARKK":{"symbol":"ARKK","support":79.1,"target":78.54,"stop":70.16,"price":74.95,"trade_date":"2026-07-20"},"COPX":{"symbol":"COPX","support":76.32,"target":76.89,"stop":69.82,"price":73.86,"trade_date":"2026-07-20"},"SMH":{"symbol":"SMH","support":605.87,"target":591.93,"stop":514.7,"price":558.83,"trade_date":"2026-07-20"},"BOTZ":{"symbol":"BOTZ","support":36.53,"target":35.12,"stop":33.09,"price":34.25,"trade_date":"2026-07-20"},"TAN":{"symbol":"TAN","support":56.23,"target":55.36,"stop":49.14,"price":52.69,"trade_date":"2026-07-20"},"SOXX":{"symbol":"SOXX","support":580.38,"target":561.39,"stop":474.47,"price":524.14,"trade_date":"2026-07-20"},"LIT":{"symbol":"LIT","support":74.35,"target":68.81,"stop":64.39,"price":66.92,"trade_date":"2026-07-20"},"URA":{"symbol":"URA","support":42.55,"target":40.67,"stop":36.01,"price":38.67,"trade_date":"2026-07-20"},"SLV":{"symbol":"SLV","support":53.4,"target":52.92,"stop":48.39,"price":50.98,"trade_date":"2026-07-20"},"XSD":{"symbol":"XSD","support":564.87,"target":538.8,"stop":451.46,"price":501.37,"trade_date":"2026-07-20"},"DRIV":{"symbol":"DRIV","support":36.69,"target":35.25,"stop":31.84,"price":33.79,"trade_date":"2026-07-20"},"ICLN":{"symbol":"ICLN","support":19.58,"target":18.99,"stop":17.01,"price":18.14,"trade_date":"2026-07-20"},"XME":{"symbol":"XME","support":104.76,"target":102.22,"stop":91.77,"price":97.74,"trade_date":"2026-07-20"},"GDX":{"symbol":"GDX","support":75.3,"target":74.18,"stop":66.15,"price":70.74,"trade_date":"2026-07-20"},"QTUM":{"symbol":"QTUM","support":154.62,"target":147.56,"stop":132.68,"price":141.18,"trade_date":"2026-07-20"}},"market_regime":{"state":"偏强","equity_allocation":"60%-80%","benchmark":"SPY"},"summary":{"universe":74,"valid":74,"momentum_pass":29},"recommendations":[{"symbol":"USO","name":"United States Oil Fund","asset_type":"商品","theme":"原油","trade_date":"2026-07-21","price":128.85,"day_open":128.92,"day_high":129.38,"day_low":127.53,"adjusted_close":128.85,"ret3":8.01,"ret5":7.22,"ret20":14.34,"ret60":-4.36,"relative_spy20":13.82,"relative_spy60":-10.25,"ma20":112.66,"ma60":128.1,"volume_ratio":0.95,"close_position":0.713,"max_drawdown20":-7.18,"volatility20":3.02,"trend_score":95.3,"strength_level":"A","trading_risk_score":56.2,"risk_level":"中","trade_state":"回踩候选","momentum_pass":true,"risk_flags":[],"support":124.01,"target":133.69,"stop":112.66,"trigger_price_basis":"raw_ohlc","return_basis":"adjusted_close"},{"symbol":"HACK","name":"Amplify Cybersecurity ETF","asset_type":"主题","theme":"网络安全","trade_date":"2026-07-21","price":107.9,"day_open":110.0,"day_high":110.0,"day_low":107.04,"adjusted_close":107.9,"ret3":-2.0,"ret5":-5.59,"ret20":13.84,"ret60":38.17,"relative_spy20":13.32,"relative_spy60":32.28,"ma20":106.6,"ma60":96.21,"volume_ratio":1.18,"close_position":0.291,"max_drawdown20":-5.59,"volatility20":2.04,"trend_score":90.2,"strength_level":"A","trading_risk_score":32.7,"risk_level":"低","trade_state":"可持有","momentum_pass":true,"risk_flags":["收盘偏弱"],"support":106.6,"target":113.15,"stop":100.89,"trigger_price_basis":"raw_ohlc","return_basis":"adjusted_close"},{"symbol":"XOP","name":"SPDR S&P Oil & Gas Exploration & Production","asset_type":"行业","theme":"油气勘探","trade_date":"2026-07-21","price":173.83,"day_open":170.89,"day_high":173.86,"day_low":170.83,"adjusted_close":173.83,"ret3":4.44,"ret5":4.81,"ret20":12.22,"ret60":3.02,"relative_spy20":11.7,"relative_spy60":-2.87,"ma20":160.16,"ma60":165.15,"volume_ratio":0.83,"close_position":0.99,"max_drawdown20":-2.11,"volatility20":1.46,"trend_score":88.0,"strength_level":"A","trading_risk_score":18.7,"risk_level":"低","trade_state":"可持有","momentum_pass":true,"risk_flags":[],"support":168.82,"target":178.84,"stop":160.16,"trigger_price_basis":"raw_ohlc","return_basis":"adjusted_close"},{"symbol":"IHF","name":"iShares U.S. Healthcare Providers","asset_type":"行业","theme":"医疗服务","trade_date":"2026-07-21","price":57.34,"day_open":56.33,"day_high":57.35,"day_low":56.11,"adjusted_close":57.34,"ret3":1.65,"ret5":0.56,"ret20":8.45,"ret60":22.45,"relative_spy20":7.93,"relative_spy60":16.56,"ma20":56.28,"ma60":52.45,"volume_ratio":1.31,"close_position":0.996,"max_drawdown20":-1.91,"volatility20":1.12,"trend_score":84.8,"strength_level":"A","trading_risk_score":16.1,"risk_level":"低","trade_state":"可持有","momentum_pass":true,"risk_flags":[],"support":56.28,"target":58.78,"stop":55.42,"trigger_price_basis":"raw_ohlc","return_basis":"adjusted_close"},{"symbol":"DBC","name":"Invesco DB Commodity Index","asset_type":"商品","theme":"综合商品","trade_date":"2026-07-21","price":29.57,"day_open":29.45,"day_high":29.6,"day_low":29.43,"adjusted_close":29.57,"ret3":3.9,"ret5":3.28,"ret20":7.88,"ret60":-1.07,"relative_spy20":7.36,"relative_spy60":-6.96,"ma20":27.62,"ma60":29.21,"volume_ratio":1.41,"close_position":0.826,"max_drawdown20":-2.47,"volatility20":1.33,"trend_score":83.2,"strength_level":"A","trading_risk_score":16.5,"risk_level":"低","trade_state":"可持有","momentum_pass":true,"risk_flags":[],"support":29.11,"target":30.03,"stop":27.62,"trigger_price_basis":"raw_ohlc","return_basis":"adjusted_close"}],"flower_signals":{"ready_plant":[{"symbol":"IGV","name":"iShares Expanded Tech-Software","theme":"软件","price":91.82,"support":91.66,"target":95.62,"stop":86.76,"strength_level":"B","trend_score":68.3,"risk_level":"低","trade_state":"可持有","ret20":5.17,"relative_spy20":4.65,"support_gap":0.17,"target_gap":4.14,"trade_date":"2026-07-21","signal":"候场","trigger_level":91.66,"trigger_basis":"距伏击位3%以内"},{"symbol":"SKYY","name":"First Trust Cloud Computing","theme":"云计算","price":136.02,"support":135.58,"target":141.56,"stop":128.64,"strength_level":"B","trend_score":73.6,"risk_level":"低","trade_state":"可持有","ret20":5.0,"relative_spy20":4.48,"support_gap":0.32,"target_gap":4.07,"trade_date":"2026-07-21","signal":"候场","trigger_level":135.58,"trigger_basis":"距伏击位3%以内"},{"symbol":"XRT","name":"SPDR S&P Retail ETF","theme":"零售","price":88.46,"support":87.96,"target":90.92,"stop":85.18,"strength_level":"B","trend_score":69.1,"risk_level":"低","trade_state":"可持有","ret20":3.45,"relative_spy20":2.93,"support_gap":0.57,"target_gap":2.78,"trade_date":"2026-07-21","signal":"候场","trigger_level":87.96,"trigger_basis":"距伏击位3%以内"},{"symbol":"HACK","name":"Amplify Cybersecurity ETF","theme":"网络安全","price":107.9,"support":106.6,"target":113.15,"stop":100.89,"strength_level":"A","trend_score":90.2,"risk_level":"低","trade_state":"可持有","ret20":13.84,"relative_spy20":13.32,"support_gap":1.22,"target_gap":4.87,"trade_date":"2026-07-21","signal":"候场","trigger_level":106.6,"trigger_basis":"距伏击位3%以内"},{"symbol":"KWEB","name":"KraneShares CSI China Internet","theme":"中国资产","price":27.02,"support":26.37,"target":27.67,"stop":25.69,"strength_level":"A","trend_score":80.1,"risk_level":"低","trade_state":"可持有","ret20":7.86,"relative_spy20":7.34,"support_gap":2.46,"target_gap":2.41,"trade_date":"2026-07-21","signal":"候场","trigger_level":26.37,"trigger_basis":"距伏击位3%以内"}],"plant":[{"symbol":"CIBR","name":"First Trust Nasdaq Cybersecurity","theme":"网络安全","price":90.58,"support":90.31,"target":94.71,"stop":85.08,"strength_level":"A","trend_score":81.2,"risk_level":"低","trade_state":"可持有","ret20":8.47,"relative_spy20":7.95,"support_gap":0.3,"target_gap":4.56,"trade_date":"2026-07-21","signal":"伏击触发","trigger_level":89.96,"trigger_basis":"当日最低价≤前一快照伏击位，且收盘重新站回伏击位、未破位"},{"symbol":"KRE","name":"SPDR S&P Regional Banking","theme":"区域银行","price":75.98,"support":75.19,"target":77.97,"stop":73.32,"strength_level":"A","trend_score":75.6,"risk_level":"低","trade_state":"可持有","ret20":5.54,"relative_spy20":5.02,"support_gap":1.05,"target_gap":2.62,"trade_date":"2026-07-21","signal":"伏击触发","trigger_level":74.99,"trigger_basis":"当日最低价≤前一快照伏击位，且收盘重新站回伏击位、未破位"},{"symbol":"XLV","name":"Health Care Select Sector","theme":"医疗","price":160.25,"support":159.81,"target":163.86,"stop":155.44,"strength_level":"B","trend_score":74.8,"risk_level":"低","trade_state":"可持有","ret20":6.79,"relative_spy20":6.27,"support_gap":0.28,"target_gap":2.25,"trade_date":"2026-07-21","signal":"伏击触发","trigger_level":159.3,"trigger_basis":"当日最低价≤前一快照伏击位，且收盘重新站回伏击位、未破位"},{"symbol":"SPY","name":"SPDR S&P 500 ETF","theme":"美国宽基","price":748.28,"support":744.98,"target":757.99,"stop":735.33,"strength_level":"B","trend_score":63.6,"risk_level":"低","trade_state":"可持有","ret20":0.52,"relative_spy20":0.0,"support_gap":0.44,"target_gap":1.3,"trade_date":"2026-07-21","signal":"伏击触发","trigger_level":744.79,"trigger_basis":"当日最低价≤前一快照伏击位，且收盘重新站回伏击位、未破位"},{"symbol":"VTI","name":"Vanguard Total Stock Market","theme":"美国宽基","price":369.45,"support":368.3,"target":374.35,"stop":362.91,"strength_level":"B","trend_score":63.0,"risk_level":"低","trade_state":"可持有","ret20":0.46,"relative_spy20":-0.06,"support_gap":0.31,"target_gap":1.33,"trade_date":"2026-07-21","signal":"伏击触发","trigger_level":368.21,"trigger_basis":"当日最低价≤前一快照伏击位，且收盘重新站回伏击位、未破位"}],"ready_harvest":[{"symbol":"UUP","name":"Invesco DB US Dollar Bullish","theme":"美元","price":28.48,"support":28.4,"target":28.61,"stop":28.31,"strength_level":"B","trend_score":62.7,"risk_level":"低","trade_state":"可持有","ret20":0.42,"relative_spy20":-0.1,"support_gap":0.28,"target_gap":0.46,"trade_date":"2026-07-21","signal":"止盈观察","trigger_level":28.61,"trigger_basis":"距兑现位3%以内或20日过热"},{"symbol":"SCHD","name":"Schwab U.S. Dividend Equity ETF","theme":"红利价值","price":32.82,"support":32.34,"target":33.3,"stop":32.18,"strength_level":"B","trend_score":71.9,"risk_level":"低","trade_state":"可持有","ret20":3.74,"relative_spy20":3.22,"support_gap":1.48,"target_gap":1.46,"trade_date":"2026-07-21","signal":"止盈观察","trigger_level":33.3,"trigger_basis":"距兑现位3%以内或20日过热"},{"symbol":"MCHI","name":"iShares MSCI China","theme":"中国资产","price":54.0,"support":53.18,"target":54.82,"stop":52.34,"strength_level":"B","trend_score":66.2,"risk_level":"低","trade_state":"可持有","ret20":2.16,"relative_spy20":1.64,"support_gap":1.54,"target_gap":1.52,"trade_date":"2026-07-21","signal":"止盈观察","trigger_level":54.82,"trigger_basis":"距兑现位3%以内或20日过热"},{"symbol":"VNQ","name":"Vanguard Real Estate ETF","theme":"房地产","price":99.52,"support":97.92,"target":101.31,"stop":97.13,"strength_level":"B","trend_score":70.0,"risk_level":"低","trade_state":"可持有","ret20":3.94,"relative_spy20":3.42,"support_gap":1.63,"target_gap":1.8,"trade_date":"2026-07-21","signal":"止盈观察","trigger_level":101.31,"trigger_basis":"距兑现位3%以内或20日过热"},{"symbol":"XLF","name":"Financial Select Sector","theme":"金融","price":56.11,"support":55.24,"target":57.2,"stop":54.66,"strength_level":"B","trend_score":72.6,"risk_level":"低","trade_state":"可持有","ret20":4.49,"relative_spy20":3.97,"support_gap":1.57,"target_gap":1.94,"trade_date":"2026-07-21","signal":"止盈观察","trigger_level":57.2,"trigger_basis":"距兑现位3%以内或20日过热"},{"symbol":"EWZ","name":"iShares MSCI Brazil","theme":"巴西","price":35.62,"support":34.92,"target":36.36,"stop":34.63,"strength_level":"B","trend_score":62.6,"risk_level":"低","trade_state":"可持有","ret20":3.94,"relative_spy20":3.42,"support_gap":2.0,"target_gap":2.08,"trade_date":"2026-07-21","signal":"止盈观察","trigger_level":36.36,"trigger_basis":"距兑现位3%以内或20日过热"},{"symbol":"XLC","name":"Communication Services","theme":"通信","price":110.03,"support":109.67,"target":112.32,"stop":106.98,"strength_level":"C","trend_score":61.3,"risk_level":"低","trade_state":"观察","ret20":2.97,"relative_spy20":2.45,"support_gap":0.33,"target_gap":2.08,"trade_date":"2026-07-21","signal":"止盈观察","trigger_level":112.32,"trigger_basis":"距兑现位3%以内或20日过热"},{"symbol":"IYT","name":"iShares Transportation Average","theme":"运输","price":88.55,"support":87.48,"target":90.56,"stop":85.87,"strength_level":"B","trend_score":71.0,"risk_level":"低","trade_state":"可持有","ret20":4.67,"relative_spy20":4.15,"support_gap":1.22,"target_gap":2.27,"trade_date":"2026-07-21","signal":"止盈观察","trigger_level":90.56,"trigger_basis":"距兑现位3%以内或20日过热"}],"harvest":[{"symbol":"DBC","name":"Invesco DB Commodity Index","theme":"综合商品","price":29.57,"support":29.11,"target":30.03,"stop":27.62,"strength_level":"A","trend_score":83.2,"risk_level":"低","trade_state":"可持有","ret20":7.88,"relative_spy20":7.36,"support_gap":1.58,"target_gap":1.56,"trade_date":"2026-07-21","signal":"兑现触发","trigger_level":29.6,"trigger_basis":"当日最高价≥前一快照兑现位"}],"exit":[]},"flower_counts":{"ready_plant":5,"plant":5,"ready_harvest":8,"harvest":1,"exit":0},"breadth_groups":[{"group":"网络安全","members":["CIBR","HACK"],"passed":2,"total":2,"ratio":100.0,"avg_relative_spy20":10.63,"state":"全面扩散"},{"group":"加密资产","members":["IBIT","ETHA"],"passed":2,"total":2,"ratio":100.0,"avg_relative_spy20":6.71,"state":"全面扩散"},{"group":"金融","members":["XLF","KRE","KIE"],"passed":3,"total":3,"ratio":100.0,"avg_relative_spy20":5.93,"state":"全面扩散"},{"group":"房地产","members":["XLRE","VNQ"],"passed":2,"total":2,"ratio":100.0,"avg_relative_spy20":2.79,"state":"全面扩散"},{"group":"能源","members":["XLE","XOP","OIH"],"passed":2,"total":3,"ratio":66.7,"avg_relative_spy20":5.83,"state":"多数确认"},{"group":"科技","members":["XLK","QQQ","IGV","FDN","SKYY"],"passed":3,"total":5,"ratio":60.0,"avg_relative_spy20":0.32,"state":"多数确认"},{"group":"红利与动量因子","members":["SCHD","SPMO"],"passed":1,"total":2,"ratio":50.0,"avg_relative_spy20":-2.35,"state":"局部走强"},{"group":"医疗","members":["XLV","IHI","IHF","XBI","IBB"],"passed":2,"total":5,"ratio":40.0,"avg_relative_spy20":5.77,"state":"局部走强"},{"group":"房屋建筑","members":["ITB","XHB"],"passed":0,"total":2,"ratio":0.0,"avg_relative_spy20":-3.22,"state":"整体偏弱"},{"group":"国防","members":["ITA","XAR"],"passed":0,"total":2,"ratio":0.0,"avg_relative_spy20":-4.08,"state":"整体偏弱"},{"group":"材料矿业","members":["XLB","XME","GDX","COPX"],"passed":0,"total":4,"ratio":0.0,"avg_relative_spy20":-8.31,"state":"整体偏弱"},{"group":"量子计算","members":["QTUM"],"passed":0,"total":1,"ratio":0.0,"avg_relative_spy20":-14.26,"state":"整体偏弱"},{"group":"新能源","members":["TAN","ICLN","LIT"],"passed":0,"total":3,"ratio":0.0,"avg_relative_spy20":-14.66,"state":"整体偏弱"},{"group":"半导体","members":["SMH","SOXX","XSD"],"passed":0,"total":3,"ratio":0.0,"avg_relative_spy20":-16.1,"state":"整体偏弱"}],"rows":[{"symbol":"USO","name":"United States Oil Fund","asset_type":"商品","theme":"原油","trade_date":"2026-07-21","price":128.85,"day_open":128.92,"day_high":129.38,"day_low":127.53,"adjusted_close":128.85,"ret3":8.01,"ret5":7.22,"ret20":14.34,"ret60":-4.36,"relative_spy20":13.82,"relative_spy60":-10.25,"ma20":112.66,"ma60":128.1,"volume_ratio":0.95,"close_position":0.713,"max_drawdown20":-7.18,"volatility20":3.02,"trend_score":95.3,"strength_level":"A","trading_risk_score":56.2,"risk_level":"中","trade_state":"回踩候选","momentum_pass":true,"risk_flags":[],"support":124.01,"target":133.69,"stop":112.66,"trigger_price_basis":"raw_ohlc","return_basis":"adjusted_close"},{"symbol":"HACK","name":"Amplify Cybersecurity ETF","asset_type":"主题","theme":"网络安全","trade_date":"2026-07-21","price":107.9,"day_open":110.0,"day_high":110.0,"day_low":107.04,"adjusted_close":107.9,"ret3":-2.0,"ret5":-5.59,"ret20":13.84,"ret60":38.17,"relative_spy20":13.32,"relative_spy60":32.28,"ma20":106.6,"ma60":96.21,"volume_ratio":1.18,"close_position":0.291,"max_drawdown20":-5.59,"volatility20":2.04,"trend_score":90.2,"strength_level":"A","trading_risk_score":32.7,"risk_level":"低","trade_state":"可持有","momentum_pass":true,"risk_flags":["收盘偏弱"],"support":106.6,"target":113.15,"stop":100.89,"trigger_price_basis":"raw_ohlc","return_basis":"adjusted_close"},{"symbol":"XOP","name":"SPDR S&P Oil & Gas Exploration & Production","asset_type":"行业","theme":"油气勘探","trade_date":"2026-07-21","price":173.83,"day_open":170.89,"day_high":173.86,"day_low":170.83,"adjusted_close":173.83,"ret3":4.44,"ret5":4.81,"ret20":12.22,"ret60":3.02,"relative_spy20":11.7,"relative_spy60":-2.87,"ma20":160.16,"ma60":165.15,"volume_ratio":0.83,"close_position":0.99,"max_drawdown20":-2.11,"volatility20":1.46,"trend_score":88.0,"strength_level":"A","trading_risk_score":18.7,"risk_level":"低","trade_state":"可持有","momentum_pass":true,"risk_flags":[],"support":168.82,"target":178.84,"stop":160.16,"trigger_price_basis":"raw_ohlc","return_basis":"adjusted_close"},{"symbol":"IHF","name":"iShares U.S. Healthcare Providers","asset_type":"行业","theme":"医疗服务","trade_date":"2026-07-21","price":57.34,"day_open":56.33,"day_high":57.35,"day_low":56.11,"adjusted_close":57.34,"ret3":1.65,"ret5":0.56,"ret20":8.45,"ret60":22.45,"relative_spy20":7.93,"relative_spy60":16.56,"ma20":56.28,"ma60":52.45,"volume_ratio":1.31,"close_position":0.996,"max_drawdown20":-1.91,"volatility20":1.12,"trend_score":84.8,"strength_level":"A","trading_risk_score":16.1,"risk_level":"低","trade_state":"可持有","momentum_pass":true,"risk_flags":[],"support":56.28,"target":58.78,"stop":55.42,"trigger_price_basis":"raw_ohlc","return_basis":"adjusted_close"},{"symbol":"DBC","name":"Invesco DB Commodity Index","asset_type":"商品","theme":"综合商品","trade_date":"2026-07-21","price":29.57,"day_open":29.45,"day_high":29.6,"day_low":29.43,"adjusted_close":29.57,"ret3":3.9,"ret5":3.28,"ret20":7.88,"ret60":-1.07,"relative_spy20":7.36,"relative_spy60":-6.96,"ma20":27.62,"ma60":29.21,"volume_ratio":1.41,"close_position":0.826,"max_drawdown20":-2.47,"volatility20":1.33,"trend_score":83.2,"strength_level":"A","trading_risk_score":16.5,"risk_level":"低","trade_state":"可持有","momentum_pass":true,"risk_flags":[],"support":29.11,"target":30.03,"stop":27.62,"trigger_price_basis":"raw_ohlc","return_basis":"adjusted_close"},{"symbol":"ETHA","name":"iShares Ethereum Trust ETF","asset_type":"加密资产","theme":"以太坊","trade_date":"2026-07-21","price":14.53,"day_open":14.62,"day_high":14.66,"day_low":14.44,"adjusted_close":14.53,"ret3":2.83,"ret5":2.47,"ret20":11.26,"ret60":-16.92,"relative_spy20":10.74,"relative_spy60":-22.81,"ma20":13.16,"ma60":14.66,"volume_ratio":1.05,"close_position":0.4,"max_drawdown20":-6.23,"volatility20":3.16,"trend_score":82.0,"strength_level":"A","trading_risk_score":36.9,"risk_level":"中","trade_state":"回踩候选","momentum_pass":true,"risk_flags":[],"support":14.03,"target":15.03,"stop":13.16,"trigger_price_basis":"raw_ohlc","return_basis":"adjusted_close"},{"symbol":"CIBR","name":"First Trust Nasdaq Cybersecurity","asset_type":"主题","theme":"网络安全","trade_date":"2026-07-21","price":90.58,"day_open":92.0,"day_high":92.26,"day_low":89.9,"adjusted_close":90.58,"ret3":-1.43,"ret5":-4.38,"ret20":8.47,"ret60":36.14,"relative_spy20":7.95,"relative_spy60":30.25,"ma20":90.31,"ma60":83.44,"volume_ratio":0.97,"close_position":0.288,"max_drawdown20":-4.38,"volatility20":1.7,"trend_score":81.2,"strength_level":"A","trading_risk_score":29.2,"risk_level":"低","trade_state":"可持有","momentum_pass":true,"risk_flags":["收盘偏弱"],"support":90.31,"target":94.71,"stop":85.08,"trigger_price_basis":"raw_ohlc","return_basis":"adjusted_close"},{"symbol":"KWEB","name":"KraneShares CSI China Internet","asset_type":"海外","theme":"中国资产","trade_date":"2026-07-21","price":27.02,"day_open":27.28,"day_high":27.33,"day_low":27.0,"adjusted_close":27.02,"ret3":-1.67,"ret5":3.21,"ret20":7.86,"ret60":-4.96,"relative_spy20":7.34,"relative_spy60":-10.85,"ma20":25.69,"ma60":27.01,"volume_ratio":1.03,"close_position":0.061,"max_drawdown20":-3.51,"volatility20":1.84,"trend_score":80.1,"strength_level":"A","trading_risk_score":29.8,"risk_level":"低","trade_state":"可持有","momentum_pass":true,"risk_flags":["收盘偏弱"],"support":26.37,"target":27.67,"stop":25.69,"trigger_price_basis":"raw_ohlc","return_basis":"adjusted_close"},{"symbol":"XLE","name":"Energy Select Sector","asset_type":"行业","theme":"能源","trade_date":"2026-07-21","price":58.5,"day_open":58.16,"day_high":58.53,"day_low":57.83,"adjusted_close":58.5,"ret3":2.6,"ret5":2.72,"ret20":8.21,"ret60":3.41,"relative_spy20":7.69,"relative_spy60":-2.48,"ma20":55.16,"ma60":56.57,"volume_ratio":0.92,"close_position":0.957,"max_drawdown20":-3.03,"volatility20":1.22,"trend_score":79.7,"strength_level":"A","trading_risk_score":16.8,"risk_level":"低","trade_state":"可持有","momentum_pass":true,"risk_flags":[],"support":57.14,"target":59.86,"stop":55.16,"trigger_price_basis":"raw_ohlc","return_basis":"adjusted_close"},{"symbol":"KIE","name":"SPDR S&P Insurance","asset_type":"行业","theme":"保险","trade_date":"2026-07-21","price":63.68,"day_open":63.98,"day_high":64.19,"day_low":63.27,"adjusted_close":63.68,"ret3":0.33,"ret5":0.32,"ret20":9.32,"ret60":9.71,"relative_spy20":8.8,"relative_spy60":3.82,"ma20":62.63,"ma60":58.71,"volume_ratio":0.94,"close_position":0.446,"max_drawdown20":-3.61,"volatility20":1.49,"trend_score":78.8,"strength_level":"A","trading_risk_score":17.2,"risk_level":"低","trade_state":"可持有","momentum_pass":true,"risk_flags":[],"support":62.63,"target":65.13,"stop":61.74,"trigger_price_basis":"raw_ohlc","return_basis":"adjusted_close"},{"symbol":"KRE","name":"SPDR S&P Regional Banking","asset_type":"行业","theme":"区域银行","trade_date":"2026-07-21","price":75.98,"day_open":75.69,"day_high":76.01,"day_low":74.98,"adjusted_close":75.98,"ret3":-2.49,"ret5":1.31,"ret20":5.54,"ret60":9.18,"relative_spy20":5.02,"relative_spy60":3.29,"ma20":75.19,"ma60":71.35,"volume_ratio":1.16,"close_position":0.971,"max_drawdown20":-3.73,"volatility20":1.26,"trend_score":75.6,"strength_level":"A","trading_risk_score":17.2,"risk_level":"低","trade_state":"可持有","momentum_pass":true,"risk_flags":[],"support":75.19,"target":77.97,"stop":73.32,"trigger_price_basis":"raw_ohlc","return_basis":"adjusted_close"},{"symbol":"XLV","name":"Health Care Select Sector","asset_type":"行业","theme":"医疗","trade_date":"2026-07-21","price":160.25,"day_open":157.53,"day_high":160.37,"day_low":157.23,"adjusted_close":160.25,"ret3":-0.96,"ret5":1.24,"ret20":6.79,"ret60":10.06,"relative_spy20":6.27,"relative_spy60":4.17,"ma20":159.81,"ma60":151.57,"volume_ratio":0.84,"close_position":0.962,"max_drawdown20":-3.74,"volatility20":1.36,"trend_score":74.8,"strength_level":"B","trading_risk_score":17.2,"risk_level":"低","trade_state":"可持有","momentum_pass":true,"risk_flags":[],"support":159.81,"target":163.86,"stop":155.44,"trigger_price_basis":"raw_ohlc","return_basis":"adjusted_close"},{"symbol":"SKYY","name":"First Trust Cloud Computing","asset_type":"主题","theme":"云计算","trade_date":"2026-07-21","price":136.02,"day_open":136.17,"day_high":137.66,"day_low":135.49,"adjusted_close":136.02,"ret3":-0.26,"ret5":-2.36,"ret20":5.0,"ret60":16.22,"relative_spy20":4.48,"relative_spy60":10.33,"ma20":135.58,"ma60":133.23,"volume_ratio":1.16,"close_position":0.244,"max_drawdown20":-4.11,"volatility20":1.32,"trend_score":73.6,"strength_level":"B","trading_risk_score":27.5,"risk_level":"低","trade_state":"可持有","momentum_pass":true,"risk_flags":["收盘偏弱"],"support":135.58,"target":141.56,"stop":128.64,"trigger_price_basis":"raw_ohlc","return_basis":"adjusted_close"},{"symbol":"XLF","name":"Financial Select Sector","asset_type":"行业","theme":"金融","trade_date":"2026-07-21","price":56.11,"day_open":55.99,"day_high":56.33,"day_low":55.72,"adjusted_close":56.11,"ret3":-1.13,"ret5":-0.12,"ret20":4.49,"ret60":8.7,"relative_spy20":3.97,"relative_spy60":2.81,"ma20":55.24,"ma60":52.95,"volume_ratio":1.07,"close_position":0.634,"max_drawdown20":-2.08,"volatility20":0.85,"trend_score":72.6,"strength_level":"B","trading_risk_score":16.3,"risk_level":"低","trade_state":"可持有","momentum_pass":true,"risk_flags":[],"support":55.24,"target":57.2,"stop":54.66,"trigger_price_basis":"raw_ohlc","return_basis":"adjusted_close"},{"symbol":"SCHD","name":"Schwab U.S. Dividend Equity ETF","asset_type":"因子","theme":"红利价值","trade_date":"2026-07-21","price":32.82,"day_open":32.75,"day_high":32.83,"day_low":32.59,"adjusted_close":32.82,"ret3":-0.67,"ret5":1.93,"ret20":3.74,"ret60":5.29,"relative_spy20":3.22,"relative_spy60":-0.6,"ma20":32.29,"ma60":31.97,"volume_ratio":0.99,"close_position":0.958,"max_drawdown20":-1.18,"volatility20":0.79,"trend_score":71.9,"strength_level":"B","trading_risk_score":15.7,"risk_level":"低","trade_state":"可持有","momentum_pass":true,"risk_flags":[],"support":32.34,"target":33.3,"stop":32.18,"trigger_price_basis":"raw_ohlc","return_basis":"adjusted_close"},{"symbol":"IYT","name":"iShares Transportation Average","asset_type":"行业","theme":"运输","trade_date":"2026-07-21","price":88.55,"day_open":88.55,"day_high":88.8,"day_low":87.85,"adjusted_close":88.55,"ret3":-1.62,"ret5":1.06,"ret20":4.67,"ret60":8.71,"relative_spy20":4.15,"relative_spy60":2.82,"ma20":87.48,"ma60":84.02,"volume_ratio":0.74,"close_position":0.736,"max_drawdown20":-1.94,"volatility20":1.05,"trend_score":71.0,"strength_level":"B","trading_risk_score":16.2,"risk_level":"低","trade_state":"可持有","momentum_pass":true,"risk_flags":["量能不足"],"support":87.48,"target":90.56,"stop":85.87,"trigger_price_basis":"raw_ohlc","return_basis":"adjusted_close"},{"symbol":"VNQ","name":"Vanguard Real Estate ETF","asset_type":"行业","theme":"房地产","trade_date":"2026-07-21","price":99.52,"day_open":99.68,"day_high":99.81,"day_low":99.11,"adjusted_close":99.52,"ret3":-0.55,"ret5":2.0,"ret20":3.94,"ret60":5.14,"relative_spy20":3.42,"relative_spy60":-0.75,"ma20":97.92,"ma60":96.18,"volume_ratio":0.77,"close_position":0.586,"max_drawdown20":-2.27,"volatility20":0.98,"trend_score":70.0,"strength_level":"B","trading_risk_score":16.4,"risk_level":"低","trade_state":"可持有","momentum_pass":true,"risk_flags":[],"support":97.92,"target":101.31,"stop":97.13,"trigger_price_basis":"raw_ohlc","return_basis":"adjusted_close"},{"symbol":"XRT","name":"SPDR S&P Retail ETF","asset_type":"行业","theme":"零售","trade_date":"2026-07-21","price":88.46,"day_open":89.16,"day_high":89.36,"day_low":88.14,"adjusted_close":88.46,"ret3":-2.23,"ret5":0.77,"ret20":3.45,"ret60":3.2,"relative_spy20":2.93,"relative_spy60":-2.69,"ma20":87.96,"ma60":85.06,"volume_ratio":1.07,"close_position":0.263,"max_drawdown20":-3.07,"volatility20":1.08,"trend_score":69.1,"strength_level":"B","trading_risk_score":26.8,"risk_level":"低","trade_state":"可持有","momentum_pass":true,"risk_flags":["收盘偏弱"],"support":87.96,"target":90.92,"stop":85.18,"trigger_price_basis":"raw_ohlc","return_basis":"adjusted_close"},{"symbol":"IGV","name":"iShares Expanded Tech-Software","asset_type":"主题","theme":"软件","trade_date":"2026-07-21","price":91.82,"day_open":91.98,"day_high":93.11,"day_low":91.44,"adjusted_close":91.82,"ret3":-2.01,"ret5":-1.93,"ret20":5.17,"ret60":9.89,"relative_spy20":4.65,"relative_spy60":4.0,"ma20":91.66,"ma60":91.83,"volume_ratio":0.66,"close_position":0.228,"max_drawdown20":-3.13,"volatility20":1.53,"trend_score":68.3,"strength_level":"B","trading_risk_score":27.1,"risk_level":"低","trade_state":"可持有","momentum_pass":true,"risk_flags":["收盘偏弱","量能不足"],"support":91.66,"target":95.62,"stop":86.76,"trigger_price_basis":"raw_ohlc","return_basis":"adjusted_close"},{"symbol":"IBIT","name":"iShares Bitcoin Trust ETF","asset_type":"加密资产","theme":"比特币","trade_date":"2026-07-21","price":37.67,"day_open":37.6,"day_high":37.93,"day_low":37.4,"adjusted_close":37.67,"ret3":3.52,"ret5":2.98,"ret20":3.21,"ret60":-14.48,"relative_spy20":2.69,"relative_spy60":-20.37,"ma20":35.42,"ma60":39.35,"volume_ratio":0.83,"close_position":0.509,"max_drawdown20":-5.72,"volatility20":2.26,"trend_score":67.3,"strength_level":"B","trading_risk_score":24.5,"risk_level":"低","trade_state":"可持有","momentum_pass":true,"risk_flags":[],"support":36.49,"target":38.85,"stop":35.42,"trigger_price_basis":"raw_ohlc","return_basis":"adjusted_close"},{"symbol":"FDN","name":"First Trust Dow Jones Internet","asset_type":"主题","theme":"互联网","trade_date":"2026-07-21","price":269.82,"day_open":270.67,"day_high":271.18,"day_low":268.98,"adjusted_close":269.82,"ret3":-1.16,"ret5":-2.03,"ret20":3.88,"ret60":3.79,"relative_spy20":3.36,"relative_spy60":-2.1,"ma20":268.61,"ma60":269.16,"volume_ratio":1.03,"close_position":0.38,"max_drawdown20":-2.71,"volatility20":1.05,"trend_score":67.1,"strength_level":"B","trading_risk_score":16.6,"risk_level":"低","trade_state":"可持有","momentum_pass":true,"risk_flags":[],"support":268.61,"target":276.64,"stop":260.73,"trigger_price_basis":"raw_ohlc","return_basis":"adjusted_close"},{"symbol":"XLRE","name":"Real Estate Select Sector","asset_type":"行业","theme":"房地产","trade_date":"2026-07-21","price":45.2,"day_open":45.28,"day_high":45.37,"day_low":45.03,"adjusted_close":45.2,"ret3":-0.57,"ret5":1.62,"ret20":2.68,"ret60":3.72,"relative_spy20":2.16,"relative_spy60":-2.17,"ma20":44.69,"ma60":44.15,"volume_ratio":0.78,"close_position":0.5,"max_drawdown20":-2.67,"volatility20":1.0,"trend_score":67.0,"strength_level":"B","trading_risk_score":16.6,"risk_level":"低","trade_state":"可持有","momentum_pass":true,"risk_flags":[],"support":44.69,"target":46.03,"stop":44.1,"trigger_price_basis":"raw_ohlc","return_basis":"adjusted_close"},{"symbol":"MCHI","name":"iShares MSCI China","asset_type":"海外","theme":"中国资产","trade_date":"2026-07-21","price":54.0,"day_open":54.33,"day_high":54.35,"day_low":53.97,"adjusted_close":54.0,"ret3":-0.26,"ret5":1.45,"ret20":2.16,"ret60":-5.08,"relative_spy20":1.64,"relative_spy60":-10.97,"ma20":52.34,"ma60":54.66,"volume_ratio":0.88,"close_position":0.067,"max_drawdown20":-2.57,"volatility20":1.31,"trend_score":66.2,"strength_level":"B","trading_risk_score":26.5,"risk_level":"低","trade_state":"可持有","momentum_pass":true,"risk_flags":["收盘偏弱"],"support":53.18,"target":54.82,"stop":52.34,"trigger_price_basis":"raw_ohlc","return_basis":"adjusted_close"},{"symbol":"SPY","name":"SPDR S&P 500 ETF","asset_type":"宽基","theme":"美国宽基","trade_date":"2026-07-21","price":748.28,"day_open":746.29,"day_high":749.04,"day_low":744.19,"adjusted_close":748.28,"ret3":-0.33,"ret5":-0.47,"ret20":0.52,"ret60":5.89,"relative_spy20":0.0,"relative_spy60":0.0,"ma20":744.98,"ma60":739.51,"volume_ratio":0.92,"close_position":0.843,"max_drawdown20":-1.7,"volatility20":0.74,"trend_score":63.6,"strength_level":"B","trading_risk_score":16.0,"risk_level":"低","trade_state":"可持有","momentum_pass":true,"risk_flags":[],"support":744.98,"target":757.99,"stop":735.33,"trigger_price_basis":"raw_ohlc","return_basis":"adjusted_close"},{"symbol":"VTI","name":"Vanguard Total Stock Market","asset_type":"宽基","theme":"美国宽基","trade_date":"2026-07-21","price":369.45,"day_open":368.15,"day_high":369.85,"day_low":367.34,"adjusted_close":369.45,"ret3":-0.3,"ret5":-0.46,"ret20":0.46,"ret60":5.92,"relative_spy20":-0.06,"relative_spy60":0.03,"ma20":368.3,"ma60":364.64,"volume_ratio":0.88,"close_position":0.841,"max_drawdown20":-1.73,"volatility20":0.68,"trend_score":63.0,"strength_level":"B","trading_risk_score":16.0,"risk_level":"低","trade_state":"可持有","momentum_pass":true,"risk_flags":[],"support":368.3,"target":374.35,"stop":362.91,"trigger_price_basis":"raw_ohlc","return_basis":"adjusted_close"},{"symbol":"UUP","name":"Invesco DB US Dollar Bullish","asset_type":"宏观","theme":"美元","trade_date":"2026-07-21","price":28.48,"day_open":28.43,"day_high":28.48,"day_low":28.42,"adjusted_close":28.48,"ret3":0.49,"ret5":0.32,"ret20":0.42,"ret60":3.45,"relative_spy20":-0.1,"relative_spy60":-2.44,"ma20":28.4,"ma60":27.95,"volume_ratio":0.92,"close_position":1.0,"max_drawdown20":-0.98,"volatility20":0.28,"trend_score":62.7,"strength_level":"B","trading_risk_score":15.6,"risk_level":"低","trade_state":"可持有","momentum_pass":true,"risk_flags":[],"support":28.4,"target":28.61,"stop":28.31,"trigger_price_basis":"raw_ohlc","return_basis":"adjusted_close"},{"symbol":"EWZ","name":"iShares MSCI Brazil","asset_type":"海外","theme":"巴西","trade_date":"2026-07-21","price":35.62,"day_open":35.49,"day_high":35.67,"day_low":35.29,"adjusted_close":35.62,"ret3":0.82,"ret5":-1.14,"ret20":3.94,"ret60":-10.3,"relative_spy20":3.42,"relative_spy60":-16.19,"ma20":34.92,"ma60":35.86,"volume_ratio":0.97,"close_position":0.88,"max_drawdown20":-2.22,"volatility20":1.16,"trend_score":62.6,"strength_level":"B","trading_risk_score":16.3,"risk_level":"低","trade_state":"可持有","momentum_pass":true,"risk_flags":[],"support":34.92,"target":36.36,"stop":34.63,"trigger_price_basis":"raw_ohlc","return_basis":"adjusted_close"},{"symbol":"SGOV","name":"iShares 0-3 Month Treasury Bond","asset_type":"现金","theme":"现金替代","trade_date":"2026-07-21","price":100.6,"day_open":100.59,"day_high":100.6,"day_low":100.59,"adjusted_close":100.6,"ret3":0.05,"ret5":0.08,"ret20":0.29,"ret60":0.88,"relative_spy20":-0.23,"relative_spy60":-5.01,"ma20":100.46,"ma60":100.16,"volume_ratio":0.9,"close_position":1.0,"max_drawdown20":0.0,"volatility20":0.01,"trend_score":61.4,"strength_level":"C","trading_risk_score":15.0,"risk_level":"低","trade_state":"观察","momentum_pass":true,"risk_flags":[],"support":100.58,"target":100.61,"stop":100.46,"trigger_price_basis":"raw_ohlc","return_basis":"adjusted_close"},{"symbol":"XLC","name":"Communication Services","asset_type":"行业","theme":"通信","trade_date":"2026-07-21","price":110.03,"day_open":110.53,"day_high":110.61,"day_low":109.99,"adjusted_close":110.03,"ret3":-2.33,"ret5":-1.27,"ret20":2.97,"ret60":-6.03,"relative_spy20":2.45,"relative_spy60":-11.92,"ma20":109.67,"ma60":112.67,"volume_ratio":0.78,"close_position":0.065,"max_drawdown20":-2.95,"volatility20":1.05,"trend_score":61.3,"strength_level":"C","trading_risk_score":26.8,"risk_level":"低","trade_state":"观察","momentum_pass":true,"risk_flags":["收盘偏弱"],"support":109.67,"target":112.32,"stop":106.98,"trigger_price_basis":"raw_ohlc","return_basis":"adjusted_close"},{"symbol":"IBB","name":"iShares Biotechnology ETF","asset_type":"主题","theme":"生物科技","trade_date":"2026-07-21","price":189.31,"day_open":186.11,"day_high":189.39,"day_low":185.61,"adjusted_close":189.31,"ret3":-0.11,"ret5":0.34,"ret20":6.95,"ret60":10.38,"relative_spy20":6.43,"relative_spy60":4.49,"ma20":189.95,"ma60":176.39,"volume_ratio":0.8,"close_position":0.979,"max_drawdown20":-5.9,"volatility20":1.33,"trend_score":53.4,"strength_level":"C","trading_risk_score":18.5,"risk_level":"低","trade_state":"观察","momentum_pass":false,"risk_flags":["趋势未通过"],"support":189.95,"target":194.72,"stop":182.1,"trigger_price_basis":"raw_ohlc","return_basis":"adjusted_close"},{"symbol":"XBI","name":"SPDR S&P Biotech ETF","asset_type":"主题","theme":"生物科技","trade_date":"2026-07-21","price":154.5,"day_open":151.02,"day_high":154.7,"day_low":150.77,"adjusted_close":154.5,"ret3":1.64,"ret5":-0.61,"ret20":5.92,"ret60":14.99,"relative_spy20":5.4,"relative_spy60":9.1,"ma20":156.35,"ma60":140.86,"volume_ratio":0.84,"close_position":0.949,"max_drawdown20":-8.12,"volatility20":1.75,"trend_score":51.9,"strength_level":"C","trading_risk_score":21.9,"risk_level":"低","trade_state":"观察","momentum_pass":false,"risk_flags":["回撤偏大","趋势未通过"],"support":156.35,"target":161.0,"stop":145.84,"trigger_price_basis":"raw_ohlc","return_basis":"adjusted_close"},{"symbol":"EFA","name":"iShares MSCI EAFE","asset_type":"海外","theme":"发达市场","trade_date":"2026-07-21","price":104.06,"day_open":103.51,"day_high":104.18,"day_low":103.1,"adjusted_close":104.06,"ret3":0.24,"ret5":0.1,"ret20":-0.5,"ret60":4.41,"relative_spy20":-1.02,"relative_spy60":-1.48,"ma20":103.6,"ma60":102.49,"volume_ratio":0.85,"close_position":0.885,"max_drawdown20":-2.74,"volatility20":0.94,"trend_score":47.6,"strength_level":"D","trading_risk_score":16.6,"risk_level":"低","trade_state":"退出","momentum_pass":false,"risk_flags":["趋势未通过"],"support":103.6,"target":105.53,"stop":102.1,"trigger_price_basis":"raw_ohlc","return_basis":"adjusted_close"},{"symbol":"IHI","name":"iShares U.S. Medical Devices","asset_type":"行业","theme":"医疗器械","trade_date":"2026-07-21","price":49.95,"day_open":50.05,"day_high":50.57,"day_low":49.88,"adjusted_close":49.95,"ret3":-4.31,"ret5":1.48,"ret20":3.33,"ret60":-5.63,"relative_spy20":2.81,"relative_spy60":-11.52,"ma20":50.69,"ma60":50.03,"volume_ratio":0.99,"close_position":0.101,"max_drawdown20":-5.8,"volatility20":2.08,"trend_score":46.0,"strength_level":"D","trading_risk_score":33.1,"risk_level":"低","trade_state":"退出","momentum_pass":false,"risk_flags":["收盘偏弱","趋势未通过"],"support":50.69,"target":51.61,"stop":47.74,"trigger_price_basis":"raw_ohlc","return_basis":"adjusted_close"},{"symbol":"XLP","name":"Consumer Staples","asset_type":"行业","theme":"防御","trade_date":"2026-07-21","price":84.06,"day_open":84.43,"day_high":84.6,"day_low":83.92,"adjusted_close":84.06,"ret3":-2.04,"ret5":0.77,"ret20":2.29,"ret60":1.39,"relative_spy20":1.77,"relative_spy60":-4.5,"ma20":84.23,"ma60":83.7,"volume_ratio":0.91,"close_position":0.206,"max_drawdown20":-2.11,"volatility20":1.2,"trend_score":45.3,"strength_level":"D","trading_risk_score":26.3,"risk_level":"低","trade_state":"退出","momentum_pass":false,"risk_flags":["收盘偏弱","趋势未通过"],"support":84.23,"target":85.96,"stop":81.53,"trigger_price_basis":"raw_ohlc","return_basis":"adjusted_close"},{"symbol":"RSP","name":"Invesco S&P 500 Equal Weight","asset_type":"宽基","theme":"美国宽基","trade_date":"2026-07-21","price":212.76,"day_open":212.57,"day_high":213.15,"day_low":211.79,"adjusted_close":212.76,"ret3":-1.07,"ret5":-0.32,"ret20":1.5,"ret60":5.5,"relative_spy20":0.98,"relative_spy60":-0.39,"ma20":212.97,"ma60":207.84,"volume_ratio":0.85,"close_position":0.713,"max_drawdown20":-1.3,"volatility20":0.62,"trend_score":43.9,"strength_level":"D","trading_risk_score":15.8,"risk_level":"低","trade_state":"退出","momentum_pass":false,"risk_flags":["趋势未通过"],"support":212.97,"target":215.61,"stop":208.96,"trigger_price_basis":"raw_ohlc","return_basis":"adjusted_close"},{"symbol":"IWM","name":"iShares Russell 2000","asset_type":"宽基","theme":"小盘股","trade_date":"2026-07-21","price":296.54,"day_open":293.43,"day_high":296.75,"day_low":292.69,"adjusted_close":296.54,"ret3":0.32,"ret5":0.69,"ret20":-0.55,"ret60":7.89,"relative_spy20":-1.07,"relative_spy60":2.0,"ma20":296.56,"ma60":288.29,"volume_ratio":0.96,"close_position":0.948,"max_drawdown20":-2.71,"volatility20":0.71,"trend_score":43.5,"strength_level":"D","trading_risk_score":16.6,"risk_level":"低","trade_state":"退出","momentum_pass":false,"risk_flags":["趋势未通过"],"support":296.56,"target":302.43,"stop":288.69,"trigger_price_basis":"raw_ohlc","return_basis":"adjusted_close"},{"symbol":"DIA","name":"SPDR Dow Jones ETF","asset_type":"宽基","theme":"美国宽基","trade_date":"2026-07-21","price":521.51,"day_open":519.63,"day_high":523.0,"day_low":518.13,"adjusted_close":521.51,"ret3":-0.6,"ret5":-0.58,"ret20":0.89,"ret60":6.16,"relative_spy20":0.37,"relative_spy60":0.27,"ma20":522.77,"ma60":508.86,"volume_ratio":0.87,"close_position":0.694,"max_drawdown20":-2.26,"volatility20":0.5,"trend_score":42.9,"strength_level":"D","trading_risk_score":16.4,"risk_level":"低","trade_state":"退出","momentum_pass":false,"risk_flags":["趋势未通过"],"support":522.77,"target":528.91,"stop":511.65,"trigger_price_basis":"raw_ohlc","return_basis":"adjusted_close"},{"symbol":"SHY","name":"iShares 1-3 Year Treasury Bond","asset_type":"债券","theme":"短债","trade_date":"2026-07-21","price":81.89,"day_open":81.92,"day_high":81.93,"day_low":81.88,"adjusted_close":81.89,"ret3":-0.13,"ret5":-0.05,"ret20":0.27,"ret60":0.16,"relative_spy20":-0.25,"relative_spy60":-5.73,"ma20":81.9,"ma60":81.79,"volume_ratio":0.99,"close_position":0.2,"max_drawdown20":-0.23,"volatility20":0.09,"trend_score":41.6,"strength_level":"D","trading_risk_score":25.1,"risk_level":"低","trade_state":"退出","momentum_pass":false,"risk_flags":["收盘偏弱","趋势未通过"],"support":81.9,"target":81.99,"stop":81.76,"trigger_price_basis":"raw_ohlc","return_basis":"adjusted_close"},{"symbol":"GLD","name":"SPDR Gold Shares","asset_type":"商品","theme":"黄金","trade_date":"2026-07-21","price":374.81,"day_open":371.7,"day_high":375.01,"day_low":371.07,"adjusted_close":374.81,"ret3":2.7,"ret5":0.71,"ret20":-2.54,"ret60":-13.05,"relative_spy20":-3.06,"relative_spy60":-18.94,"ma20":372.43,"ma60":398.82,"volume_ratio":0.98,"close_position":0.949,"max_drawdown20":-4.49,"volatility20":1.46,"trend_score":40.4,"strength_level":"D","trading_risk_score":17.7,"risk_level":"低","trade_state":"退出","momentum_pass":false,"risk_flags":["趋势未通过"],"support":372.43,"target":382.23,"stop":364.92,"trigger_price_basis":"raw_ohlc","return_basis":"adjusted_close"},{"symbol":"OIH","name":"VanEck Oil Services","asset_type":"行业","theme":"油服","trade_date":"2026-07-21","price":383.49,"day_open":376.31,"day_high":384.54,"day_low":369.07,"adjusted_close":383.49,"ret3":1.7,"ret5":-0.5,"ret20":-1.39,"ret60":-9.87,"relative_spy20":-1.91,"relative_spy60":-15.76,"ma20":375.02,"ma60":411.83,"volume_ratio":0.68,"close_position":0.932,"max_drawdown20":-6.48,"volatility20":1.7,"trend_score":39.8,"strength_level":"D","trading_risk_score":20.5,"risk_level":"低","trade_state":"退出","momentum_pass":false,"risk_flags":["量能不足","趋势未通过"],"support":375.02,"target":396.39,"stop":366.29,"trigger_price_basis":"raw_ohlc","return_basis":"adjusted_close"},{"symbol":"XLU","name":"Utilities Select Sector","asset_type":"行业","theme":"防御","trade_date":"2026-07-21","price":44.92,"day_open":44.87,"day_high":45.03,"day_low":44.64,"adjusted_close":44.92,"ret3":-1.21,"ret5":-1.69,"ret20":0.45,"ret60":-1.92,"relative_spy20":-0.07,"relative_spy60":-7.81,"ma20":45.43,"ma60":44.88,"volume_ratio":0.91,"close_position":0.718,"max_drawdown20":-3.1,"volatility20":0.92,"trend_score":37.5,"strength_level":"D","trading_risk_score":16.9,"risk_level":"低","trade_state":"退出","momentum_pass":false,"risk_flags":["趋势未通过"],"support":45.43,"target":45.92,"stop":43.59,"trigger_price_basis":"raw_ohlc","return_basis":"adjusted_close"},{"symbol":"COPX","name":"Global X Copper Miners","asset_type":"行业","theme":"铜矿","trade_date":"2026-07-21","price":78.24,"day_open":76.12,"day_high":78.48,"day_low":76.02,"adjusted_close":78.24,"ret3":4.77,"ret5":-0.61,"ret20":-7.52,"ret60":-4.8,"relative_spy20":-8.04,"relative_spy60":-10.69,"ma20":76.0,"ma60":81.45,"volume_ratio":0.8,"close_position":0.902,"max_drawdown20":-7.79,"volatility20":3.29,"trend_score":33.4,"strength_level":"D","trading_risk_score":36.3,"risk_level":"中","trade_state":"退出","momentum_pass":false,"risk_flags":["趋势未通过"],"support":76.0,"target":81.39,"stop":74.03,"trigger_price_basis":"raw_ohlc","return_basis":"adjusted_close"},{"symbol":"XLY","name":"Consumer Discretionary","asset_type":"行业","theme":"消费","trade_date":"2026-07-21","price":114.87,"day_open":114.64,"day_high":115.16,"day_low":114.28,"adjusted_close":114.87,"ret3":-2.1,"ret5":-0.89,"ret20":-0.06,"ret60":-2.24,"relative_spy20":-0.58,"relative_spy60":-8.13,"ma20":116.11,"ma60":117.09,"volume_ratio":0.93,"close_position":0.67,"max_drawdown20":-2.95,"volatility20":1.09,"trend_score":24.8,"strength_level":"D","trading_risk_score":16.8,"risk_level":"低","trade_state":"退出","momentum_pass":false,"risk_flags":["趋势未通过"],"support":116.11,"target":117.49,"stop":111.38,"trigger_price_basis":"raw_ohlc","return_basis":"adjusted_close"},{"symbol":"IEF","name":"iShares 7-10 Year Treasury Bond","asset_type":"债券","theme":"中债","trade_date":"2026-07-21","price":93.31,"day_open":93.4,"day_high":93.42,"day_low":93.25,"adjusted_close":93.31,"ret3":-0.44,"ret5":-0.26,"ret20":-0.41,"ret60":-1.18,"relative_spy20":-0.93,"relative_spy60":-7.07,"ma20":93.92,"ma60":93.81,"volume_ratio":0.89,"close_position":0.344,"max_drawdown20":-1.54,"volatility20":0.29,"trend_score":24.7,"strength_level":"D","trading_risk_score":15.9,"risk_level":"低","trade_state":"退出","momentum_pass":false,"risk_flags":["趋势未通过"],"support":93.92,"target":93.67,"stop":92.83,"trigger_price_basis":"raw_ohlc","return_basis":"adjusted_close"},{"symbol":"FBND","name":"Fidelity Total Bond ETF","asset_type":"债券","theme":"综合债券","trade_date":"2026-07-21","price":45.1,"day_open":45.14,"day_high":45.21,"day_low":45.06,"adjusted_close":45.1,"ret3":-0.35,"ret5":-0.22,"ret20":-0.49,"ret60":-0.61,"relative_spy20":-1.01,"relative_spy60":-6.5,"ma20":45.36,"ma60":45.27,"volume_ratio":0.86,"close_position":0.242,"max_drawdown20":-1.25,"volatility20":0.22,"trend_score":24.6,"strength_level":"D","trading_risk_score":25.7,"risk_level":"低","trade_state":"退出","momentum_pass":false,"risk_flags":["收盘偏弱","趋势未通过"],"support":45.36,"target":45.37,"stop":44.74,"trigger_price_basis":"raw_ohlc","return_basis":"adjusted_close"},{"symbol":"XLI","name":"Industrial Select Sector","asset_type":"行业","theme":"工业","trade_date":"2026-07-21","price":178.66,"day_open":179.51,"day_high":179.94,"day_low":177.76,"adjusted_close":178.66,"ret3":-0.83,"ret5":-0.99,"ret20":-1.73,"ret60":2.89,"relative_spy20":-2.25,"relative_spy60":-3.0,"ma20":181.38,"ma60":176.18,"volume_ratio":0.94,"close_position":0.413,"max_drawdown20":-4.01,"volatility20":1.07,"trend_score":23.5,"strength_level":"D","trading_risk_score":17.4,"risk_level":"低","trade_state":"退出","momentum_pass":false,"risk_flags":["趋势未通过"],"support":181.38,"target":182.92,"stop":172.98,"trigger_price_basis":"raw_ohlc","return_basis":"adjusted_close"},{"symbol":"INDA","name":"iShares MSCI India","asset_type":"海外","theme":"印度","trade_date":"2026-07-21","price":48.78,"day_open":48.85,"day_high":48.88,"day_low":48.71,"adjusted_close":48.78,"ret3":0.18,"ret5":0.1,"ret20":-2.28,"ret60":-1.28,"relative_spy20":-2.8,"relative_spy60":-7.17,"ma20":49.12,"ma60":48.73,"volume_ratio":0.92,"close_position":0.429,"max_drawdown20":-2.67,"volatility20":0.78,"trend_score":22.9,"strength_level":"D","trading_risk_score":16.6,"risk_level":"低","trade_state":"退出","momentum_pass":false,"risk_flags":["趋势未通过"],"support":49.12,"target":49.24,"stop":48.16,"trigger_price_basis":"raw_ohlc","return_basis":"adjusted_close"},{"symbol":"VXUS","name":"Vanguard Total International Stock ETF","asset_type":"海外","theme":"全球除美国","trade_date":"2026-07-21","price":84.45,"day_open":84.02,"day_high":84.56,"day_low":83.71,"adjusted_close":84.45,"ret3":0.46,"ret5":-0.25,"ret20":-3.0,"ret60":3.81,"relative_spy20":-3.52,"relative_spy60":-2.08,"ma20":84.6,"ma60":84.37,"volume_ratio":0.83,"close_position":0.871,"max_drawdown20":-3.6,"volatility20":1.18,"trend_score":22.8,"strength_level":"D","trading_risk_score":17.2,"risk_level":"低","trade_state":"退出","momentum_pass":false,"risk_flags":["趋势未通过"],"support":84.6,"target":85.75,"stop":82.71,"trigger_price_basis":"raw_ohlc","return_basis":"adjusted_close"},{"symbol":"QQQ","name":"Invesco QQQ","asset_type":"宽基","theme":"科技成长","trade_date":"2026-07-21","price":708.97,"day_open":706.68,"day_high":710.05,"day_low":702.81,"adjusted_close":708.97,"ret3":0.43,"ret5":-1.49,"ret20":-3.93,"ret60":8.95,"relative_spy20":-4.45,"relative_spy60":3.06,"ma20":714.67,"ma60":711.14,"volume_ratio":0.94,"close_position":0.851,"max_drawdown20":-5.58,"volatility20":1.57,"trend_score":22.3,"strength_level":"D","trading_risk_score":18.9,"risk_level":"低","trade_state":"退出","momentum_pass":false,"risk_flags":["趋势未通过"],"support":714.67,"target":725.5,"stop":686.93,"trigger_price_basis":"raw_ohlc","return_basis":"adjusted_close"},{"symbol":"EWJ","name":"iShares MSCI Japan","asset_type":"海外","theme":"日本","trade_date":"2026-07-21","price":92.74,"day_open":92.08,"day_high":92.97,"day_low":91.71,"adjusted_close":92.74,"ret3":0.9,"ret5":-1.22,"ret20":-4.36,"ret60":7.09,"relative_spy20":-4.88,"relative_spy60":1.2,"ma20":92.94,"ma60":91.76,"volume_ratio":0.95,"close_position":0.817,"max_drawdown20":-5.08,"volatility20":1.58,"trend_score":21.8,"strength_level":"D","trading_risk_score":18.7,"risk_level":"低","trade_state":"退出","momentum_pass":false,"risk_flags":["趋势未通过"],"support":92.94,"target":94.45,"stop":90.46,"trigger_price_basis":"raw_ohlc","return_basis":"adjusted_close"},{"symbol":"XLK","name":"Technology Select Sector","asset_type":"行业","theme":"科技","trade_date":"2026-07-21","price":180.78,"day_open":179.56,"day_high":181.01,"day_low":178.17,"adjusted_close":180.78,"ret3":1.84,"ret5":-1.55,"ret20":-5.92,"ret60":16.14,"relative_spy20":-6.44,"relative_spy60":10.25,"ma20":182.32,"ma60":179.63,"volume_ratio":0.88,"close_position":0.917,"max_drawdown20":-7.84,"volatility20":2.07,"trend_score":21.0,"strength_level":"D","trading_risk_score":24.2,"risk_level":"低","trade_state":"退出","momentum_pass":false,"risk_flags":["趋势未通过"],"support":182.32,"target":187.1,"stop":172.36,"trigger_price_basis":"raw_ohlc","return_basis":"adjusted_close"},{"symbol":"ARKK","name":"ARK Innovation ETF","asset_type":"主题","theme":"创新成长","trade_date":"2026-07-21","price":77.69,"day_open":75.68,"day_high":77.93,"day_low":75.68,"adjusted_close":77.695,"ret3":1.34,"ret5":-2.3,"ret20":-0.94,"ret60":1.56,"relative_spy20":-1.46,"relative_spy60":-4.33,"ma20":79.06,"ma60":77.95,"volume_ratio":0.82,"close_position":0.896,"max_drawdown20":-10.36,"volatility20":2.07,"trend_score":21.0,"strength_level":"D","trading_risk_score":25.7,"risk_level":"低","trade_state":"退出","momentum_pass":false,"risk_flags":["回撤偏大","趋势未通过"],"support":79.06,"target":81.37,"stop":72.8,"trigger_price_basis":"raw_ohlc","return_basis":"adjusted_close"},{"symbol":"ITA","name":"iShares U.S. Aerospace & Defense","asset_type":"主题","theme":"国防","trade_date":"2026-07-21","price":229.74,"day_open":229.38,"day_high":232.08,"day_low":226.6,"adjusted_close":229.74,"ret3":-0.5,"ret5":-2.35,"ret20":-2.45,"ret60":4.93,"relative_spy20":-2.97,"relative_spy60":-0.96,"ma20":238.07,"ma60":230.03,"volume_ratio":0.97,"close_position":0.573,"max_drawdown20":-8.58,"volatility20":1.16,"trend_score":20.7,"strength_level":"D","trading_risk_score":20.1,"risk_level":"低","trade_state":"退出","momentum_pass":false,"risk_flags":["回撤偏大","趋势未通过"],"support":238.07,"target":236.54,"stop":220.68,"trigger_price_basis":"raw_ohlc","return_basis":"adjusted_close"},{"symbol":"TLT","name":"iShares 20+ Year Treasury Bond","asset_type":"债券","theme":"长债","trade_date":"2026-07-21","price":83.66,"day_open":83.74,"day_high":83.77,"day_low":83.43,"adjusted_close":83.66,"ret3":-0.65,"ret5":-0.5,"ret20":-2.46,"ret60":-2.24,"relative_spy20":-2.98,"relative_spy60":-8.13,"ma20":85.16,"ma60":84.91,"volume_ratio":0.87,"close_position":0.675,"max_drawdown20":-3.98,"volatility20":0.54,"trend_score":20.1,"strength_level":"D","trading_risk_score":17.4,"risk_level":"低","trade_state":"退出","momentum_pass":false,"risk_flags":["趋势未通过"],"support":85.16,"target":84.26,"stop":82.86,"trigger_price_basis":"raw_ohlc","return_basis":"adjusted_close"},{"symbol":"XLB","name":"Materials Select Sector","asset_type":"行业","theme":"原材料","trade_date":"2026-07-21","price":50.1,"day_open":50.5,"day_high":50.52,"day_low":49.85,"adjusted_close":50.1,"ret3":-1.55,"ret5":-1.07,"ret20":-2.94,"ret60":-2.94,"relative_spy20":-3.46,"relative_spy60":-8.83,"ma20":50.9,"ma60":51.0,"volume_ratio":0.86,"close_position":0.373,"max_drawdown20":-3.81,"volatility20":1.08,"trend_score":19.1,"strength_level":"D","trading_risk_score":17.3,"risk_level":"低","trade_state":"退出","momentum_pass":false,"risk_flags":["趋势未通过"],"support":50.9,"target":51.33,"stop":48.47,"trigger_price_basis":"raw_ohlc","return_basis":"adjusted_close"},{"symbol":"SPMO","name":"Invesco S&P 500 Momentum ETF","asset_type":"因子","theme":"动量","trade_date":"2026-07-21","price":149.7,"day_open":148.41,"day_high":150.15,"day_low":147.3,"adjusted_close":149.7,"ret3":3.04,"ret5":-2.07,"ret20":-7.4,"ret60":16.02,"relative_spy20":-7.92,"relative_spy60":10.13,"ma20":152.2,"ma60":147.64,"volume_ratio":1.12,"close_position":0.844,"max_drawdown20":-10.93,"volatility20":2.53,"trend_score":18.8,"strength_level":"D","trading_risk_score":29.8,"risk_level":"低","trade_state":"退出","momentum_pass":false,"risk_flags":["回撤偏大","趋势未通过"],"support":152.2,"target":155.16,"stop":142.42,"trigger_price_basis":"raw_ohlc","return_basis":"adjusted_close"},{"symbol":"XAR","name":"SPDR S&P Aerospace & Defense","asset_type":"主题","theme":"国防","trade_date":"2026-07-21","price":264.91,"day_open":260.54,"day_high":266.29,"day_low":258.38,"adjusted_close":264.91,"ret3":2.26,"ret5":-0.62,"ret20":-4.66,"ret60":1.3,"relative_spy20":-5.18,"relative_spy60":-4.59,"ma20":272.76,"ma60":271.11,"volume_ratio":0.87,"close_position":0.826,"max_drawdown20":-10.75,"volatility20":1.54,"trend_score":17.2,"strength_level":"D","trading_risk_score":21.8,"risk_level":"低","trade_state":"退出","momentum_pass":false,"risk_flags":["回撤偏大","趋势未通过"],"support":272.76,"target":275.1,"stop":251.33,"trigger_price_basis":"raw_ohlc","return_basis":"adjusted_close"},{"symbol":"EEM","name":"iShares MSCI Emerging Markets","asset_type":"海外","theme":"新兴市场","trade_date":"2026-07-21","price":65.34,"day_open":65.12,"day_high":65.5,"day_low":64.82,"adjusted_close":65.34,"ret3":1.79,"ret5":-0.5,"ret20":-8.24,"ret60":5.34,"relative_spy20":-8.76,"relative_spy60":-0.55,"ma20":66.15,"ma60":66.38,"volume_ratio":1.03,"close_position":0.765,"max_drawdown20":-7.48,"volatility20":2.13,"trend_score":16.4,"strength_level":"D","trading_risk_score":24.5,"risk_level":"低","trade_state":"退出","momentum_pass":false,"risk_flags":["趋势未通过"],"support":66.15,"target":66.92,"stop":63.23,"trigger_price_basis":"raw_ohlc","return_basis":"adjusted_close"},{"symbol":"PAVE","name":"Global X U.S. Infrastructure Development","asset_type":"主题","theme":"基础设施","trade_date":"2026-07-21","price":56.2,"day_open":56.29,"day_high":56.52,"day_low":55.61,"adjusted_close":56.2,"ret3":-1.02,"ret5":-0.9,"ret20":-4.97,"ret60":-0.09,"relative_spy20":-5.49,"relative_spy60":-5.98,"ma20":57.25,"ma60":56.74,"volume_ratio":0.66,"close_position":0.648,"max_drawdown20":-6.99,"volatility20":1.32,"trend_score":15.0,"strength_level":"D","trading_risk_score":19.2,"risk_level":"低","trade_state":"退出","momentum_pass":false,"risk_flags":["量能不足","趋势未通过"],"support":57.25,"target":57.78,"stop":54.09,"trigger_price_basis":"raw_ohlc","return_basis":"adjusted_close"},{"symbol":"XHB","name":"SPDR S&P Homebuilders","asset_type":"行业","theme":"房屋建筑","trade_date":"2026-07-21","price":105.94,"day_open":106.0,"day_high":106.56,"day_low":105.04,"adjusted_close":105.94,"ret3":-4.39,"ret5":-2.05,"ret20":-2.92,"ret60":-3.06,"relative_spy20":-3.44,"relative_spy60":-8.95,"ma20":110.42,"ma60":105.81,"volume_ratio":0.75,"close_position":0.594,"max_drawdown20":-8.61,"volatility20":1.91,"trend_score":14.6,"strength_level":"D","trading_risk_score":23.5,"risk_level":"低","trade_state":"退出","momentum_pass":false,"risk_flags":["回撤偏大","趋势未通过"],"support":110.42,"target":109.72,"stop":100.9,"trigger_price_basis":"raw_ohlc","return_basis":"adjusted_close"},{"symbol":"ITB","name":"iShares U.S. Home Construction","asset_type":"行业","theme":"房屋建筑","trade_date":"2026-07-21","price":94.93,"day_open":95.49,"day_high":95.55,"day_low":94.22,"adjusted_close":94.93,"ret3":-5.25,"ret5":-2.27,"ret20":-2.48,"ret60":-5.7,"relative_spy20":-3.0,"relative_spy60":-11.59,"ma20":99.71,"ma60":95.52,"volume_ratio":0.79,"close_position":0.534,"max_drawdown20":-9.5,"volatility20":2.11,"trend_score":13.9,"strength_level":"D","trading_risk_score":25.5,"risk_level":"低","trade_state":"退出","momentum_pass":false,"risk_flags":["回撤偏大","趋势未通过"],"support":99.71,"target":98.72,"stop":89.88,"trigger_price_basis":"raw_ohlc","return_basis":"adjusted_close"},{"symbol":"SMH","name":"VanEck Semiconductor ETF","asset_type":"主题","theme":"半导体","trade_date":"2026-07-21","price":584.08,"day_open":580.96,"day_high":586.0,"day_low":572.05,"adjusted_close":584.08,"ret3":2.66,"ret5":-2.7,"ret20":-12.68,"ret60":21.22,"relative_spy20":-13.2,"relative_spy60":15.33,"ma20":601.63,"ma60":584.32,"volume_ratio":1.0,"close_position":0.862,"max_drawdown20":-15.15,"volatility20":3.43,"trend_score":10.9,"strength_level":"D","trading_risk_score":39.5,"risk_level":"中","trade_state":"退出","momentum_pass":false,"risk_flags":["回撤偏大","趋势未通过"],"support":601.63,"target":615.98,"stop":541.55,"trigger_price_basis":"raw_ohlc","return_basis":"adjusted_close"},{"symbol":"SOXX","name":"iShares Semiconductor ETF","asset_type":"主题","theme":"半导体","trade_date":"2026-07-21","price":552.69,"day_open":549.42,"day_high":555.16,"day_low":540.15,"adjusted_close":552.69,"ret3":4.18,"ret5":-2.68,"ret20":-15.62,"ret60":25.39,"relative_spy20":-16.14,"relative_spy60":19.5,"ma20":575.27,"ma60":551.07,"volume_ratio":1.02,"close_position":0.835,"max_drawdown20":-18.56,"volatility20":4.13,"trend_score":7.2,"strength_level":"D","trading_risk_score":47.7,"risk_level":"中","trade_state":"退出","momentum_pass":false,"risk_flags":["回撤偏大","趋势未通过"],"support":575.27,"target":588.47,"stop":504.99,"trigger_price_basis":"raw_ohlc","return_basis":"adjusted_close"},{"symbol":"BOTZ","name":"Global X Robotics & AI","asset_type":"主题","theme":"人工智能","trade_date":"2026-07-21","price":34.89,"day_open":34.72,"day_high":34.99,"day_low":34.63,"adjusted_close":34.89,"ret3":-1.8,"ret5":-2.76,"ret20":-8.93,"ret60":-4.78,"relative_spy20":-9.45,"relative_spy60":-10.67,"ma20":36.36,"ma60":38.23,"volume_ratio":0.89,"close_position":0.712,"max_drawdown20":-10.46,"volatility20":2.12,"trend_score":7.2,"strength_level":"D","trading_risk_score":26.3,"risk_level":"低","trade_state":"退出","momentum_pass":false,"risk_flags":["回撤偏大","趋势未通过"],"support":36.36,"target":35.74,"stop":33.76,"trigger_price_basis":"raw_ohlc","return_basis":"adjusted_close"},{"symbol":"GDX","name":"VanEck Gold Miners","asset_type":"行业","theme":"黄金矿业","trade_date":"2026-07-21","price":74.19,"day_open":72.44,"day_high":74.22,"day_low":72.11,"adjusted_close":74.19,"ret3":3.91,"ret5":-0.92,"ret20":-8.9,"ret60":-19.52,"relative_spy20":-9.42,"relative_spy60":-25.41,"ma20":74.94,"ma60":82.85,"volume_ratio":0.86,"close_position":0.983,"max_drawdown20":-10.16,"volatility20":2.69,"trend_score":4.6,"strength_level":"D","trading_risk_score":30.7,"risk_level":"低","trade_state":"退出","momentum_pass":false,"risk_flags":["回撤偏大","趋势未通过"],"support":74.94,"target":77.64,"stop":69.59,"trigger_price_basis":"raw_ohlc","return_basis":"adjusted_close"},{"symbol":"SLV","name":"iShares Silver Trust","asset_type":"商品","theme":"贵金属","trade_date":"2026-07-21","price":53.08,"day_open":52.86,"day_high":53.52,"day_low":52.66,"adjusted_close":53.08,"ret3":5.34,"ret5":-0.17,"ret20":-9.9,"ret60":-22.37,"relative_spy20":-10.42,"relative_spy60":-28.26,"ma20":53.11,"ma60":62.44,"volume_ratio":0.86,"close_position":0.488,"max_drawdown20":-10.19,"volatility20":2.88,"trend_score":4.5,"strength_level":"D","trading_risk_score":36.2,"risk_level":"中","trade_state":"退出","momentum_pass":false,"risk_flags":["回撤偏大","趋势未通过"],"support":53.11,"target":54.96,"stop":50.57,"trigger_price_basis":"raw_ohlc","return_basis":"adjusted_close"},{"symbol":"QTUM","name":"Defiance Quantum ETF","asset_type":"主题","theme":"量子计算","trade_date":"2026-07-21","price":145.2,"day_open":144.54,"day_high":145.74,"day_low":143.5,"adjusted_close":145.2,"ret3":1.62,"ret5":-3.1,"ret20":-13.74,"ret60":12.09,"relative_spy20":-14.26,"relative_spy60":6.2,"ma20":153.47,"ma60":151.39,"volume_ratio":0.94,"close_position":0.759,"max_drawdown20":-14.63,"volatility20":2.26,"trend_score":4.2,"strength_level":"D","trading_risk_score":29.9,"risk_level":"低","trade_state":"退出","momentum_pass":false,"risk_flags":["回撤偏大","趋势未通过"],"support":153.47,"target":151.27,"stop":137.1,"trigger_price_basis":"raw_ohlc","return_basis":"adjusted_close"},{"symbol":"DRIV","name":"Global X Autonomous & Electric Vehicles","asset_type":"主题","theme":"智能汽车","trade_date":"2026-07-21","price":35.0,"day_open":34.42,"day_high":35.02,"day_low":34.39,"adjusted_close":35.0,"ret3":1.79,"ret5":-1.85,"ret20":-12.89,"ret60":-1.21,"relative_spy20":-13.41,"relative_spy60":-7.1,"ma20":36.43,"ma60":38.38,"volume_ratio":0.59,"close_position":0.968,"max_drawdown20":-12.39,"volatility20":2.33,"trend_score":0.5,"strength_level":"D","trading_risk_score":29.1,"risk_level":"低","trade_state":"退出","momentum_pass":false,"risk_flags":["量能不足","回撤偏大","趋势未通过"],"support":36.43,"target":36.41,"stop":33.12,"trigger_price_basis":"raw_ohlc","return_basis":"adjusted_close"},{"symbol":"TAN","name":"Invesco Solar ETF","asset_type":"主题","theme":"新能源","trade_date":"2026-07-21","price":53.74,"day_open":53.64,"day_high":54.05,"day_low":53.12,"adjusted_close":53.74,"ret3":-0.81,"ret5":-2.52,"ret20":-12.06,"ret60":-8.29,"relative_spy20":-12.58,"relative_spy60":-14.18,"ma20":55.86,"ma60":60.83,"volume_ratio":0.66,"close_position":0.667,"max_drawdown20":-10.92,"volatility20":2.35,"trend_score":0,"strength_level":"D","trading_risk_score":28.3,"risk_level":"低","trade_state":"退出","momentum_pass":false,"risk_flags":["量能不足","回撤偏大","趋势未通过"],"support":55.86,"target":56.34,"stop":50.27,"trigger_price_basis":"raw_ohlc","return_basis":"adjusted_close"},{"symbol":"LIT","name":"Global X Lithium & Battery Tech","asset_type":"主题","theme":"新能源","trade_date":"2026-07-21","price":69.08,"day_open":68.54,"day_high":69.35,"day_low":68.35,"adjusted_close":69.08,"ret3":0.32,"ret5":-3.49,"ret20":-15.98,"ret60":-15.55,"relative_spy20":-16.5,"relative_spy60":-21.44,"ma20":73.69,"ma60":80.94,"volume_ratio":1.01,"close_position":0.734,"max_drawdown20":-14.83,"volatility20":2.07,"trend_score":0,"strength_level":"D","trading_risk_score":28.5,"risk_level":"低","trade_state":"退出","momentum_pass":false,"risk_flags":["回撤偏大","趋势未通过"],"support":73.69,"target":70.99,"stop":66.54,"trigger_price_basis":"raw_ohlc","return_basis":"adjusted_close"},{"symbol":"URA","name":"Global X Uranium ETF","asset_type":"主题","theme":"核能","trade_date":"2026-07-21","price":40.25,"day_open":39.18,"day_high":40.27,"day_low":39.24,"adjusted_close":40.25,"ret3":2.91,"ret5":-3.13,"ret20":-14.0,"ret60":-28.72,"relative_spy20":-14.52,"relative_spy60":-34.61,"ma20":42.22,"ma60":47.94,"volume_ratio":1.12,"close_position":0.981,"max_drawdown20":-15.16,"volatility20":2.32,"trend_score":0,"strength_level":"D","trading_risk_score":30.6,"risk_level":"低","trade_state":"退出","momentum_pass":false,"risk_flags":["回撤偏大","趋势未通过"],"support":42.22,"target":42.26,"stop":37.58,"trigger_price_basis":"raw_ohlc","return_basis":"adjusted_close"},{"symbol":"XSD","name":"SPDR S&P Semiconductor ETF","asset_type":"主题","theme":"半导体","trade_date":"2026-07-21","price":528.66,"day_open":521.39,"day_high":529.48,"day_low":515.87,"adjusted_close":528.66,"ret3":4.31,"ret5":-3.38,"ret20":-18.44,"ret60":17.27,"relative_spy20":-18.96,"relative_spy60":11.38,"ma20":558.89,"ma60":564.94,"volume_ratio":0.73,"close_position":0.939,"max_drawdown20":-19.8,"volatility20":4.01,"trend_score":0,"strength_level":"D","trading_risk_score":55.9,"risk_level":"中","trade_state":"退出","momentum_pass":false,"risk_flags":["量能不足","回撤偏大","趋势未通过"],"support":558.89,"target":563.71,"stop":481.92,"trigger_price_basis":"raw_ohlc","return_basis":"adjusted_close"},{"symbol":"ICLN","name":"iShares Global Clean Energy","asset_type":"主题","theme":"清洁能源","trade_date":"2026-07-21","price":18.52,"day_open":18.32,"day_high":18.62,"day_low":18.26,"adjusted_close":18.52,"ret3":0.93,"ret5":-2.88,"ret20":-14.38,"ret60":-7.8,"relative_spy20":-14.9,"relative_spy60":-13.69,"ma20":19.42,"ma60":20.78,"volume_ratio":0.82,"close_position":0.722,"max_drawdown20":-12.24,"volatility20":2.33,"trend_score":0,"strength_level":"D","trading_risk_score":29.0,"risk_level":"低","trade_state":"退出","momentum_pass":false,"risk_flags":["回撤偏大","趋势未通过"],"support":19.42,"target":19.36,"stop":17.4,"trigger_price_basis":"raw_ohlc","return_basis":"adjusted_close"},{"symbol":"XME","name":"SPDR S&P Metals & Mining","asset_type":"行业","theme":"金属矿业","trade_date":"2026-07-21","price":101.6,"day_open":99.47,"day_high":101.86,"day_low":99.06,"adjusted_close":101.6,"ret3":2.64,"ret5":-2.7,"ret20":-11.82,"ret60":-13.58,"relative_spy20":-12.34,"relative_spy60":-19.47,"ma20":104.08,"ma60":114.56,"volume_ratio":0.84,"close_position":0.907,"max_drawdown20":-11.87,"volatility20":2.06,"trend_score":0,"strength_level":"D","trading_risk_score":26.6,"risk_level":"低","trade_state":"退出","momentum_pass":false,"risk_flags":["回撤偏大","趋势未通过"],"support":104.08,"target":106.18,"stop":95.49,"trigger_price_basis":"raw_ohlc","return_basis":"adjusted_close"}],"failures":{},"realtime_scope":["当前价","当日涨跌","关键位触发"],"snapshot_scope":["趋势分","交易风险","交易状态","市场状态","行业广度","准备信号"]}